Workbook
Name Slicer_Date: #N/A
Name Slicer_Date1: #N/A
Name Slicer_Party: #N/A
Name Slicer_Party_Name: #N/A
Name Slicer_Party_Name1: #N/A
Name Slicer_Party_Name2: #N/A
Name Slicer_Person: #N/A
Name Slicer_Shipment_Number: #N/A

Sheet Billing
B1: Party Name | C1: Tiyaar | D1: Rate | E1: Total | G1: Billing
B2: =B57 -> BSC | C2: =SUMIFS(ledger!G:G, ledger!B:B, B2, ledger!E:E, "<>*RD*") / 1.0936 -> 1315881.5 | D2: 10 | E2: =(SUMIFS(ledger!G:G, ledger!B:B, B2, ledger!E:E, "<>*RD*",ledger!D:D, "Silky") / 1.0936)*12 + (SUMIFS(ledger!G:G, ledger!B:B, B2, ledger!E:E, "<>*RD*",ledger!D:D, "Chamki") / 1.0936)*10 -> 12508742 | I2: BSC | S2: Billing Total
B3: =B58 -> Ejaz Sahab | C3: =SUMIFS(ledger!G:G, ledger!B:B, B3, ledger!E:E, "<>*RD*") / 1.0936 -> 49525.421 | D3: 10 | E3: =(SUMIFS(ledger!G:G, ledger!B:B, B3, ledger!E:E, "<>*RD*",ledger!D:D, "Silky") / 1.0936)*12 + (SUMIFS(ledger!G:G, ledger!B:B, B3, ledger!E:E, "<>*RD*",ledger!D:D, "Chamki") / 1.0936)*10 -> 594305.05 | I3: Ejaz Sahab
B4: =B59 -> Arshad | C4: =SUMIFS(ledger!G:G, ledger!B:B, B4, ledger!E:E, "<>*RD*") / 1.0936 -> 77906.913 | D4: 10 | E4: =(SUMIFS(ledger!G:G, ledger!B:B, B4, ledger!E:E, "<>*RD*",ledger!D:D, "Silky") / 1.0936)*12 + (SUMIFS(ledger!G:G, ledger!B:B, B4, ledger!E:E, "<>*RD*",ledger!D:D, "Chamki") / 1.0936)*10 -> 779069.13 | I4: Arshad | T4: Gaz | U4: Total Metres | V4: Total Chamki | W4: Total Super Silky | X4: Billing (Chamki/Crinkle) | Y4: Billing (Super Chamki) | Z4: Billing (Slub) | AA4: Billing (Satin) | AB4: Billing (Black-chamki) | AC4: Billing (Kataan) | AD4: Billing (Munaar) | AE4: Billing (Super kataan) | AF4: Billing (Custom) | AG4: Adjusted Bill | AH4: Amount Paid | AI4: Balance | AJ4: Rate (Chamki) | AK4: Rate (Super Silky) | AN4: SUM
B5: =B60 -> Shehzad Kamoki | C5: =SUMIFS(ledger!G:G, ledger!B:B, B5, ledger!E:E, "<>*RD*") / 1.0936 -> 0 | D5: 10.5 | E5: =(SUMIFS(ledger!G:G, ledger!B:B, B5, ledger!E:E, "<>*RD*",ledger!D:D, "Silky") / 1.0936)*12 + (SUMIFS(ledger!G:G, ledger!B:B, B5, ledger!E:E, "<>*RD*",ledger!D:D, "Chamki") / 1.0936)*10.5 -> 0 | I5: Shehzad Kamoki | S5: {=_xlfn.UNIQUE(Table1[Party Name])} -> BSC | T5: {=_xlfn.BYROW(B57,_xlfn.LAMBDA(_xlpm.party,SUMIFS(ledger!G:G,ledger!B:B,_xlpm.party,ledger!E:E,"<>*RD*")))+_xlfn.IFNA(C126,0)} -> 5785561.9 | U5: {=_xlfn.BYROW(B57, _xlfn.LAMBDA(_xlpm.party, SUMIFS(ledger!G:G, ledger!B:B, _xlpm.party, ledger!E:E, "<>*RD*") / 1.0936 ))+_xlfn.IFNA(E126,0)} -> 4442568.5 | V5: {=(_xlfn.BYROW(B57,_xlfn.LAMBDA(_xlpm.party,SUMIFS(ledger!G:G,ledger!B:B,_xlpm.party,ledger!E:E,"<>*RD*",ledger!D:D,"Chamki")+SUMIFS(ledger!G:G, ledger!B:B, _xlpm.party, ledger!E:E, "<>*RD*", ledger!D:D, "Crinkle")))/1.0936)+_xlfn.IFNA(E126,0)} -> 3957426.7 | W5: {=(_xlfn.BYROW(B57,_xlfn.LAMBDA(_xlpm.party,SUMIFS(ledger!G:G,ledger!B:B,_xlpm.party,ledger!E:E,"<>*RD*",ledger!D:D,"Silky")))/1.0936)+_xlfn.IFNA(F126,0)} -> 1138082.5 | X5: {=(_xlfn.BYROW(B57,_xlfn.LAMBDA(_xlpm.party, (SUMIFS(ledger!J:J,ledger!B:B,_xlpm.party,ledger!E:E,"<>*RD*",ledger!D:D,"Chamki",ledger!C:C,"<>Closing CF")+ SUMIFS(ledger!J:J,ledger!B:B,_xlpm.party,ledger!E:E,"<>*RD*",ledger!D:D,"Crinkle",ledger!C:C,"<>Closing CF") )+_xlfn.IFNA(G126,0))))} -> 39574267 | Y5: {=_xlfn.BYROW(B57, _xlfn.LAMBDA(_xlpm.party, SUMIFS(ledger!J:J, ledger!B:B, _xlpm.party, ledger!E:E, "<>*RD*", ledger!D:D, "Silky", ledger!C:C, "<>Closing CF") )) + _xlfn.IFNA(H126, 0)} -> 14443232 | Z5: {=_xlfn.BYROW(B57, _xlfn.LAMBDA(_xlpm.party, SUMIFS(ledger!J:J, ledger!B:B, _xlpm.party, ledger!E:E, "<>*RD*", ledger!D:D, "Slub", ledger!C:C, "<>Closing CF") ))+ _xlfn.IFNA(I126, 0)} -> 0 | AA5: {=_xlfn.BYROW(B57, _xlfn.LAMBDA(_xlpm.party, SUMIFS(ledger!J:J, ledger!B:B, _xlpm.party, ledger!E:E, "<>*RD*", ledger!D:D, "Satin", ledger!C:C, "<>Closing CF") ))+ _xlfn.IFNA(J126, 0)} -> 0 | AB5: {=_xlfn.BYROW(B57, _xlfn.LAMBDA(_xlpm.party, SUMIFS(ledger!J:J, ledger!B:B, _xlpm.party, ledger!E:E, "<>*RD*", ledger!D:D, "Black-Chamki", ledger!C:C, "<>Closing CF") ))+ _xlfn.IFNA(K126, 0)} -> 0 | AC5: {=_xlfn.BYROW(B57, _xlfn.LAMBDA(_xlpm.party, SUMIFS(ledger!J:J, ledger!B:B, _xlpm.party, ledger!E:E, "<>*RD*", ledger!D:D, "Kataan", ledger!C:C, "<>Closing CF") ))+ _xlfn.IFNA(L126, 0)} -> 2127095.8 | AD5: {=_xlfn.BYROW(B57, _xlfn.LAMBDA(_xlpm.party, SUMIFS(ledger!J:J, ledger!B:B, _xlpm.party, ledger!E:E, "<>*RD*", ledger!D:D, "Munaar", ledger!C:C, "<>Closing CF") ))+ _xlfn.IFNA(M126, 0)} -> 0 | AE5: {=_xlfn.BYROW(B57, _xlfn.LAMBDA(_xlpm.party, SUMIFS(ledger!J:J, ledger!B:B, _xlpm.party, ledger!E:E, "<>*RD*", ledger!D:D, "Super Kataan", ledger!C:C, "<>Closing CF") ))+ _xlfn.IFNA(N126, 0)} -> 0 | AF5: {=_xlfn.BYROW(B57, _xlfn.LAMBDA(_xlpm.party, SUMIFS(ledger!J:J, ledger!B:B, _xlpm.party, ledger!E:E, "<>*RD*", ledger!D:D, "Custom", ledger!C:C, "<>Closing CF") ))+ _xlfn.IFNA(O126, 0)} -> 18006.584 | AG5: =X5+Y5+Z5+AA5+AB5+AC5+AD5+AF5+AE5 -> 56162601 | AH5: =(SUMIF(Table14[Party],#REF!,Table14[Credit]))+_xlfn.IFNA(Q126,0) -> 19750734 | AI5: =AG5-AH5 -> 36411867 | AJ5: 10 | AK5: 13 | AN5: =SUM(AI5:AI47) -> 42660365
B6: =B61 -> Sufi Nawaz Sahab | C6: =SUMIFS(ledger!G:G, ledger!B:B, B6, ledger!E:E, "<>*RD*") / 1.0936 -> 160812 | D6: 10 | E6: =((SUMIFS(ledger!G:G, ledger!B:B, B6, ledger!E:E, "<>*RD*",ledger!D:D, "Silky") / 1.0936) *12) + ((SUMIFS(ledger!G:G, ledger!B:B, B6, ledger!E:E, "<>*RD*",ledger!D:D, "Chamki") / 1.0936)* 9) -> 1198266.3 | I6: Sufi Nawaz Sahab | S6: Ejaz Sahab | T6: {=_xlfn.BYROW(B58,_xlfn.LAMBDA(_xlpm.party,SUMIFS(ledger!G:G,ledger!B:B,_xlpm.party,ledger!E:E,"<>*RD*")))+_xlfn.IFNA(C127,0)} -> 703440 | U6: {=_xlfn.BYROW(B58, _xlfn.LAMBDA(_xlpm.party, SUMIFS(ledger!G:G, ledger!B:B, _xlpm.party, ledger!E:E, "<>*RD*") / 1.0936 ))+_xlfn.IFNA(D127,0)} -> 643233.36 | V6: {=(_xlfn.BYROW(B58,_xlfn.LAMBDA(_xlpm.party,SUMIFS(ledger!G:G,ledger!B:B,_xlpm.party,ledger!E:E,"<>*RD*",ledger!D:D,"Chamki")+SUMIFS(ledger!G:G, ledger!B:B, _xlpm.party, ledger!E:E, "<>*RD*", ledger!D:D, "Crinkle")))/1.0936)+_xlfn.IFNA(E127,0)} -> 148145.57 | W6: {=(_xlfn.BYROW(B58,_xlfn.LAMBDA(_xlpm.party,SUMIFS(ledger!G:G,ledger!B:B,_xlpm.party,ledger!E:E,"<>*RD*",ledger!D:D,"Silky")))/1.0936)+_xlfn.IFNA(F127,0)} -> 495087.78 | X6: {=(_xlfn.BYROW(B58,_xlfn.LAMBDA(_xlpm.party, (SUMIFS(ledger!J:J,ledger!B:B,_xlpm.party,ledger!E:E,"<>*RD*",ledger!D:D,"Chamki",ledger!C:C,"<>Closing CF")+ SUMIFS(ledger!J:J,ledger!B:B,_xlpm.party,ledger!E:E,"<>*RD*",ledger!D:D,"Crinkle",ledger!C:C,"<>Closing CF") )+_xlfn.IFNA(G127,0))))} -> 1481455.7 | Y6: {=_xlfn.BYROW(B58, _xlfn.LAMBDA(_xlpm.party, SUMIFS(ledger!J:J, ledger!B:B, _xlpm.party, ledger!E:E, "<>*RD*", ledger!D:D, "Silky", ledger!C:C, "<>Closing CF") )) + _xlfn.IFNA(H127, 0)} -> 6376997.1 | Z6: {=_xlfn.BYROW(B58, _xlfn.LAMBDA(_xlpm.party, SUMIFS(ledger!J:J, ledger!B:B, _xlpm.party, ledger!E:E, "<>*RD*", ledger!D:D, "Slub", ledger!C:C, "<>Closing CF") ))+ _xlfn.IFNA(I127, 0)} -> 0 | AA6: {=_xlfn.BYROW(B58, _xlfn.LAMBDA(_xlpm.party, SUMIFS(ledger!J:J, ledger!B:B, _xlpm.party, ledger!E:E, "<>*RD*", ledger!D:D, "Satin", ledger!C:C, "<>Closing CF") ))+ _xlfn.IFNA(J127, 0)} -> 0 | AB6: {=_xlfn.BYROW(B58, _xlfn.LAMBDA(_xlpm.party, SUMIFS(ledger!J:J, ledger!B:B, _xlpm.party, ledger!E:E, "<>*RD*", ledger!D:D, "Black-Chamki", ledger!C:C, "<>Closing CF") ))+ _xlfn.IFNA(K127, 0)} -> 0 | AC6: {=_xlfn.BYROW(B58, _xlfn.LAMBDA(_xlpm.party, SUMIFS(ledger!J:J, ledger!B:B, _xlpm.party, ledger!E:E, "<>*RD*", ledger!D:D, "Kataan", ledger!C:C, "<>Closing CF") ))+ _xlfn.IFNA(L127, 0)} -> 0 | AD6: {=_xlfn.BYROW(B58, _xlfn.LAMBDA(_xlpm.party, SUMIFS(ledger!J:J, ledger!B:B, _xlpm.party, ledger!E:E, "<>*RD*", ledger!D:D, "Munaar", ledger!C:C, "<>Closing CF") ))+ _xlfn.IFNA(M127, 0)} -> 0 | AE6: {=_xlfn.BYROW(B58, _xlfn.LAMBDA(_xlpm.party, SUMIFS(ledger!J:J, ledger!B:B, _xlpm.party, ledger!E:E, "<>*RD*", ledger!D:D, "Super Kataan", ledger!C:C, "<>Closing CF") ))+ _xlfn.IFNA(N127, 0)} -> 0 | AF6: {=_xlfn.BYROW(B58, _xlfn.LAMBDA(_xlpm.party, SUMIFS(ledger!J:J, ledger!B:B, _xlpm.party, ledger!E:E, "<>*RD*", ledger!D:D, "Custom", ledger!C:C, "<>Closing CF") ))+ _xlfn.IFNA(O127, 0)} -> 0 | AG6: =X6+Y6+Z6+AA6+AB6+AC6+AD6+AF6+AE6 -> 7858452.8 | AH6: =(SUMIF(Table14[Party],S6,Table14[Credit]))+_xlfn.IFNA(Q127,0) -> 7214622 | AI6: =AG6-AH6 -> 643830.82 | AJ6: 10 | AK6: 13
B7: =B62 -> Sajad Khan | C7: =SUMIFS(ledger!G:G, ledger!B:B, B7, ledger!E:E, "<>*RD*") / 1.0936 -> 0 | D7: 10 | E7: {=(SUMIFS(ledger!G:G, ledger!B:B, B7, ledger!E:E, "<>*RD*",ledger!D:D, "Silky") / 1.0936)*12 + (SUMIFS(ledger!G:G, ledger!B:B, B7, ledger!E:E, "<>*RD*",ledger!D:D, "Chamki") / 1.0936)*10 +(SUMIFS(ledger!G:G, ledger!B:B, party, ledger!E:E, "<>*RD*", ledger!D:D, "Crinkle")/ 1.0936)*10} -> 0 | I7: Sajad Khan | S7: Arshad | T7: {=_xlfn.BYROW(B59,_xlfn.LAMBDA(_xlpm.party,SUMIFS(ledger!G:G,ledger!B:B,_xlpm.party,ledger!E:E,"<>*RD*")))+_xlfn.IFNA(C128,0)} -> 1052426 | U7: {=_xlfn.BYROW(B59, _xlfn.LAMBDA(_xlpm.party, SUMIFS(ledger!G:G, ledger!B:B, _xlpm.party, ledger!E:E, "<>*RD*") / 1.0936 ))+_xlfn.IFNA(D128,0)} -> 962350.04 | V7: {=(_xlfn.BYROW(B59,_xlfn.LAMBDA(_xlpm.party,SUMIFS(ledger!G:G,ledger!B:B,_xlpm.party,ledger!E:E,"<>*RD*",ledger!D:D,"Chamki")+SUMIFS(ledger!G:G, ledger!B:B, _xlpm.party, ledger!E:E, "<>*RD*", ledger!D:D, "Crinkle")))/1.0936)+_xlfn.IFNA(E128,0)} -> 796824.25 | W7: {=(_xlfn.BYROW(B59,_xlfn.LAMBDA(_xlpm.party,SUMIFS(ledger!G:G,ledger!B:B,_xlpm.party,ledger!E:E,"<>*RD*",ledger!D:D,"Silky")))/1.0936)+_xlfn.IFNA(F128,0)} -> 165525.79 | X7: {=(_xlfn.BYROW(B59,_xlfn.LAMBDA(_xlpm.party, (SUMIFS(ledger!J:J,ledger!B:B,_xlpm.party,ledger!E:E,"<>*RD*",ledger!D:D,"Chamki",ledger!C:C,"<>Closing CF")+ SUMIFS(ledger!J:J,ledger!B:B,_xlpm.party,ledger!E:E,"<>*RD*",ledger!D:D,"Crinkle",ledger!C:C,"<>Closing CF") )+_xlfn.IFNA(G128,0))))} -> 7968242.5 | Y7: {=_xlfn.BYROW(B59, _xlfn.LAMBDA(_xlpm.party, SUMIFS(ledger!J:J, ledger!B:B, _xlpm.party, ledger!E:E, "<>*RD*", ledger!D:D, "Silky", ledger!C:C, "<>Closing CF") )) + _xlfn.IFNA(H128, 0)} -> 2137041 | Z7: {=_xlfn.BYROW(B59, _xlfn.LAMBDA(_xlpm.party, SUMIFS(ledger!J:J, ledger!B:B, _xlpm.party, ledger!E:E, "<>*RD*", ledger!D:D, "Slub", ledger!C:C, "<>Closing CF") ))+ _xlfn.IFNA(I128, 0)} -> 0 | AA7: {=_xlfn.BYROW(B59, _xlfn.LAMBDA(_xlpm.party, SUMIFS(ledger!J:J, ledger!B:B, _xlpm.party, ledger!E:E, "<>*RD*", ledger!D:D, "Satin", ledger!C:C, "<>Closing CF") ))+ _xlfn.IFNA(J128, 0)} -> 0 | AB7: {=_xlfn.BYROW(B59, _xlfn.LAMBDA(_xlpm.party, SUMIFS(ledger!J:J, ledger!B:B, _xlpm.party, ledger!E:E, "<>*RD*", ledger!D:D, "Black-Chamki", ledger!C:C, "<>Closing CF") ))+ _xlfn.IFNA(K128, 0)} -> 0 | AC7: {=_xlfn.BYROW(B59, _xlfn.LAMBDA(_xlpm.party, SUMIFS(ledger!J:J, ledger!B:B, _xlpm.party, ledger!E:E, "<>*RD*", ledger!D:D, "Kataan", ledger!C:C, "<>Closing CF") ))+ _xlfn.IFNA(L128, 0)} -> 0 | AD7: {=_xlfn.BYROW(B59, _xlfn.LAMBDA(_xlpm.party, SUMIFS(ledger!J:J, ledger!B:B, _xlpm.party, ledger!E:E, "<>*RD*", ledger!D:D, "Munaar", ledger!C:C, "<>Closing CF") ))+ _xlfn.IFNA(M128, 0)} -> 0 | AE7: {=_xlfn.BYROW(B59, _xlfn.LAMBDA(_xlpm.party, SUMIFS(ledger!J:J, ledger!B:B, _xlpm.party, ledger!E:E, "<>*RD*", ledger!D:D, "Super Kataan", ledger!C:C, "<>Closing CF") ))+ _xlfn.IFNA(N128, 0)} -> 0 | AF7: {=_xlfn.BYROW(B59, _xlfn.LAMBDA(_xlpm.party, SUMIFS(ledger!J:J, ledger!B:B, _xlpm.party, ledger!E:E, "<>*RD*", ledger!D:D, "Custom", ledger!C:C, "<>Closing CF") ))+ _xlfn.IFNA(O128, 0)} -> 0 | AG7: =X7+Y7+Z7+AA7+AB7+AC7+AD7+AF7+AE7 -> 10105283 | AH7: =(SUMIF(Table14[Party],S7,Table14[Credit]))+_xlfn.IFNA(Q128,0) -> 9812586 | AI7: =AG7-AH7 -> 292697.47 | AJ7: 10 | AK7: 13
B8: =B63 -> Raaz Fabrics | C8: =SUMIFS(ledger!G:G, ledger!B:B, B8, ledger!E:E, "<>*RD*") / 1.0936 -> 73510.424 | D8: 10 | E8: =(SUMIFS(ledger!G:G, ledger!B:B, B8, ledger!E:E, "<>*RD*",ledger!D:D, "Silky") / 1.0936)*12 + (SUMIFS(ledger!G:G, ledger!B:B, B8, ledger!E:E, "<>*RD*",ledger!D:D, "chamki") / 1.0936)*10 +(SUMIFS(ledger!G:G, ledger!B:B, B8, ledger!E:E, "<>*RD*",ledger!D:D, "Crinkle") / 1.0936)*10 -> 735104.24 | I8: Raaz Fabrics | S8: Shehzad Kamoki | T8: {=_xlfn.BYROW(B60,_xlfn.LAMBDA(_xlpm.party,SUMIFS(ledger!G:G,ledger!B:B,_xlpm.party,ledger!E:E,"<>*RD*")))+_xlfn.IFNA(C129,0)} -> 143457 | U8: {=_xlfn.BYROW(B60, _xlfn.LAMBDA(_xlpm.party, SUMIFS(ledger!G:G, ledger!B:B, _xlpm.party, ledger!E:E, "<>*RD*") / 1.0936 ))+_xlfn.IFNA(D129,0)} -> 131178.68 | V8: {=(_xlfn.BYROW(B60,_xlfn.LAMBDA(_xlpm.party,SUMIFS(ledger!G:G,ledger!B:B,_xlpm.party,ledger!E:E,"<>*RD*",ledger!D:D,"Chamki")+SUMIFS(ledger!G:G, ledger!B:B, _xlpm.party, ledger!E:E, "<>*RD*", ledger!D:D, "Crinkle")))/1.0936)+_xlfn.IFNA(E129,0)} -> 131178.68 | W8: {=(_xlfn.BYROW(B60,_xlfn.LAMBDA(_xlpm.party,SUMIFS(ledger!G:G,ledger!B:B,_xlpm.party,ledger!E:E,"<>*RD*",ledger!D:D,"Silky")))/1.0936)+_xlfn.IFNA(F129,0)} -> 0 | X8: {=(_xlfn.BYROW(B60,_xlfn.LAMBDA(_xlpm.party, (SUMIFS(ledger!J:J,ledger!B:B,_xlpm.party,ledger!E:E,"<>*RD*",ledger!D:D,"Chamki",ledger!C:C,"<>Closing CF")+ SUMIFS(ledger!J:J,ledger!B:B,_xlpm.party,ledger!E:E,"<>*RD*",ledger!D:D,"Crinkle",ledger!C:C,"<>Closing CF") )+_xlfn.IFNA(G129,0))))} -> 1354242 | Y8: {=_xlfn.BYROW(B60, _xlfn.LAMBDA(_xlpm.party, SUMIFS(ledger!J:J, ledger!B:B, _xlpm.party, ledger!E:E, "<>*RD*", ledger!D:D, "Silky", ledger!C:C, "<>Closing CF") )) + _xlfn.IFNA(H129, 0)} -> 0 | Z8: {=_xlfn.BYROW(B60, _xlfn.LAMBDA(_xlpm.party, SUMIFS(ledger!J:J, ledger!B:B, _xlpm.party, ledger!E:E, "<>*RD*", ledger!D:D, "Slub", ledger!C:C, "<>Closing CF") ))+ _xlfn.IFNA(I129, 0)} -> 0 | AA8: {=_xlfn.BYROW(B60, _xlfn.LAMBDA(_xlpm.party, SUMIFS(ledger!J:J, ledger!B:B, _xlpm.party, ledger!E:E, "<>*RD*", ledger!D:D, "Satin", ledger!C:C, "<>Closing CF") ))+ _xlfn.IFNA(J129, 0)} -> 0 | AB8: {=_xlfn.BYROW(B60, _xlfn.LAMBDA(_xlpm.party, SUMIFS(ledger!J:J, ledger!B:B, _xlpm.party, ledger!E:E, "<>*RD*", ledger!D:D, "Black-Chamki", ledger!C:C, "<>Closing CF") ))+ _xlfn.IFNA(K129, 0)} -> 0 | AC8: {=_xlfn.BYROW(B60, _xlfn.LAMBDA(_xlpm.party, SUMIFS(ledger!J:J, ledger!B:B, _xlpm.party, ledger!E:E, "<>*RD*", ledger!D:D, "Kataan", ledger!C:C, "<>Closing CF") ))+ _xlfn.IFNA(L129, 0)} -> 0 | AD8: {=_xlfn.BYROW(B60, _xlfn.LAMBDA(_xlpm.party, SUMIFS(ledger!J:J, ledger!B:B, _xlpm.party, ledger!E:E, "<>*RD*", ledger!D:D, "Munaar", ledger!C:C, "<>Closing CF") ))+ _xlfn.IFNA(M129, 0)} -> 0 | AE8: {=_xlfn.BYROW(B60, _xlfn.LAMBDA(_xlpm.party, SUMIFS(ledger!J:J, ledger!B:B, _xlpm.party, ledger!E:E, "<>*RD*", ledger!D:D, "Super Kataan", ledger!C:C, "<>Closing CF") ))+ _xlfn.IFNA(N129, 0)} -> 0 | AF8: {=_xlfn.BYROW(B60, _xlfn.LAMBDA(_xlpm.party, SUMIFS(ledger!J:J, ledger!B:B, _xlpm.party, ledger!E:E, "<>*RD*", ledger!D:D, "Custom", ledger!C:C, "<>Closing CF") ))+ _xlfn.IFNA(O129, 0)} -> 0 | AG8: =X8+Y8+Z8+AA8+AB8+AC8+AD8+AF8+AE8 -> 1354242 | AH8: =(SUMIF(Table14[Party],S8,Table14[Credit]))+_xlfn.IFNA(Q129,0) -> 1353710 | AI8: =AG8-AH8 -> 531.99729 | AJ8: 10.5 | AK8: 13
B9: =B64 -> Azam | C9: =SUMIFS(ledger!G:G, ledger!B:B, B9, ledger!E:E, "<>*RD*") / 1.0936 -> 0 | D9: 10 | E9: =(SUMIFS(ledger!G:G, ledger!B:B, B9, ledger!E:E, "<>*RD*",ledger!D:D, "Silky") / 1.0936)*12 + (SUMIFS(ledger!G:G, ledger!B:B, B9, ledger!E:E, "<>*RD*",ledger!D:D, "Chamki") / 1.0936)*10 -> 0 | I9: Azam | S9: Sufi Nawaz Sahab | T9: {=_xlfn.BYROW(B61,_xlfn.LAMBDA(_xlpm.party,SUMIFS(ledger!G:G,ledger!B:B,_xlpm.party,ledger!E:E,"<>*RD*")))+_xlfn.IFNA(C130,0)} -> 1388831 | U9: {=_xlfn.BYROW(B61, _xlfn.LAMBDA(_xlpm.party, SUMIFS(ledger!G:G, ledger!B:B, _xlpm.party, ledger!E:E, "<>*RD*") / 1.0936 ))+_xlfn.IFNA(D130,0)} -> 1269962.5 | V9: {=(_xlfn.BYROW(B61,_xlfn.LAMBDA(_xlpm.party,SUMIFS(ledger!G:G,ledger!B:B,_xlpm.party,ledger!E:E,"<>*RD*",ledger!D:D,"Chamki")+SUMIFS(ledger!G:G, ledger!B:B, _xlpm.party, ledger!E:E, "<>*RD*", ledger!D:D, "Crinkle")))/1.0936)+_xlfn.IFNA(E130,0)} -> 599330.65 | W9: {=(_xlfn.BYROW(B61,_xlfn.LAMBDA(_xlpm.party,SUMIFS(ledger!G:G,ledger!B:B,_xlpm.party,ledger!E:E,"<>*RD*",ledger!D:D,"Silky")))/1.0936)+_xlfn.IFNA(F130,0)} -> 585679.41 | X9: {=(_xlfn.BYROW(B61,_xlfn.LAMBDA(_xlpm.party, (SUMIFS(ledger!J:J,ledger!B:B,_xlpm.party,ledger!E:E,"<>*RD*",ledger!D:D,"Chamki",ledger!C:C,"<>Closing CF")+ SUMIFS(ledger!J:J,ledger!B:B,_xlpm.party,ledger!E:E,"<>*RD*",ledger!D:D,"Crinkle",ledger!C:C,"<>Closing CF") )+_xlfn.IFNA(G130,0))))} -> 5408917.9 | Y9: {=_xlfn.BYROW(B61, _xlfn.LAMBDA(_xlpm.party, SUMIFS(ledger!J:J, ledger!B:B, _xlpm.party, ledger!E:E, "<>*RD*", ledger!D:D, "Silky", ledger!C:C, "<>Closing CF") )) + _xlfn.IFNA(H130, 0)} -> 6928297.4 | Z9: {=_xlfn.BYROW(B61, _xlfn.LAMBDA(_xlpm.party, SUMIFS(ledger!J:J, ledger!B:B, _xlpm.party, ledger!E:E, "<>*RD*", ledger!D:D, "Slub", ledger!C:C, "<>Closing CF") ))+ _xlfn.IFNA(I130, 0)} -> 0 | AA9: {=_xlfn.BYROW(B61, _xlfn.LAMBDA(_xlpm.party, SUMIFS(ledger!J:J, ledger!B:B, _xlpm.party, ledger!E:E, "<>*RD*", ledger!D:D, "Satin", ledger!C:C, "<>Closing CF") ))+ _xlfn.IFNA(J130, 0)} -> 239959.77 | AB9: {=_xlfn.BYROW(B61, _xlfn.LAMBDA(_xlpm.party, SUMIFS(ledger!J:J, ledger!B:B, _xlpm.party, ledger!E:E, "<>*RD*", ledger!D:D, "Black-Chamki", ledger!C:C, "<>Closing CF") ))+ _xlfn.IFNA(K130, 0)} -> 0 | AC9: {=_xlfn.BYROW(B61, _xlfn.LAMBDA(_xlpm.party, SUMIFS(ledger!J:J, ledger!B:B, _xlpm.party, ledger!E:E, "<>*RD*", ledger!D:D, "Kataan", ledger!C:C, "<>Closing CF") ))+ _xlfn.IFNA(L130, 0)} -> 0 | AD9: {=_xlfn.BYROW(B61, _xlfn.LAMBDA(_xlpm.party, SUMIFS(ledger!J:J, ledger!B:B, _xlpm.party, ledger!E:E, "<>*RD*", ledger!D:D, "Munaar", ledger!C:C, "<>Closing CF") ))+ _xlfn.IFNA(M130, 0)} -> 0 | AE9: {=_xlfn.BYROW(B61, _xlfn.LAMBDA(_xlpm.party, SUMIFS(ledger!J:J, ledger!B:B, _xlpm.party, ledger!E:E, "<>*RD*", ledger!D:D, "Super Kataan", ledger!C:C, "<>Closing CF") ))+ _xlfn.IFNA(N130, 0)} -> 914347.11 | AF9: {=_xlfn.BYROW(B61, _xlfn.LAMBDA(_xlpm.party, SUMIFS(ledger!J:J, ledger!B:B, _xlpm.party, ledger!E:E, "<>*RD*", ledger!D:D, "Custom", ledger!C:C, "<>Closing CF") ))+ _xlfn.IFNA(O130, 0)} -> 0 | AG9: =X9+Y9+Z9+AA9+AB9+AC9+AD9+AF9+AE9 -> 13491522 | AH9: =(SUMIF(Table14[Party],S9,Table14[Credit]))+_xlfn.IFNA(Q130,0) -> 12178764 | AI9: =AG9-AH9 -> 1312758.1 | AJ9: 10 | AK9: 13
B10: =B65 -> Ubaidullah | C10: =SUMIFS(ledger!G:G, ledger!B:B, B10, ledger!E:E, "<>*RD*") / 1.0936 -> 149238.3 | D10: 10 | E10: =(SUMIFS(ledger!G:G, ledger!B:B, B10, ledger!E:E, "<>*RD*",ledger!D:D, "Silky") / 1.0936)*12 + (SUMIFS(ledger!G:G, ledger!B:B, B10, ledger!E:E, "<>*RD*",ledger!D:D, "Chamki") / 1.0936)*10 -> 1790859.5 | I10: Ubaidullah | S10: Sajad Khan | T10: {=_xlfn.BYROW(B62,_xlfn.LAMBDA(_xlpm.party,SUMIFS(ledger!G:G,ledger!B:B,_xlpm.party,ledger!E:E,"<>*RD*")))+_xlfn.IFNA(C131,0)} -> 1135029 | U10: {=_xlfn.BYROW(B62, _xlfn.LAMBDA(_xlpm.party, SUMIFS(ledger!G:G, ledger!B:B, _xlpm.party, ledger!E:E, "<>*RD*") / 1.0936 ))+_xlfn.IFNA(D131,0)} -> 1037883.1 | V10: {=(_xlfn.BYROW(B62,_xlfn.LAMBDA(_xlpm.party,SUMIFS(ledger!G:G,ledger!B:B,_xlpm.party,ledger!E:E,"<>*RD*",ledger!D:D,"Chamki")+SUMIFS(ledger!G:G, ledger!B:B, _xlpm.party, ledger!E:E, "<>*RD*", ledger!D:D, "Crinkle")))/1.0936)+_xlfn.IFNA(E131,0)} -> 1005535.8 | W10: {=(_xlfn.BYROW(B62,_xlfn.LAMBDA(_xlpm.party,SUMIFS(ledger!G:G,ledger!B:B,_xlpm.party,ledger!E:E,"<>*RD*",ledger!D:D,"Silky")))/1.0936)+_xlfn.IFNA(F131,0)} -> 0 | X10: {=(_xlfn.BYROW(B62,_xlfn.LAMBDA(_xlpm.party, (SUMIFS(ledger!J:J,ledger!B:B,_xlpm.party,ledger!E:E,"<>*RD*",ledger!D:D,"Chamki",ledger!C:C,"<>Closing CF")+ SUMIFS(ledger!J:J,ledger!B:B,_xlpm.party,ledger!E:E,"<>*RD*",ledger!D:D,"Crinkle",ledger!C:C,"<>Closing CF") )+_xlfn.IFNA(G131,0))))} -> 10055358 | Y10: {=_xlfn.BYROW(B62, _xlfn.LAMBDA(_xlpm.party, SUMIFS(ledger!J:J, ledger!B:B, _xlpm.party, ledger!E:E, "<>*RD*", ledger!D:D, "Silky", ledger!C:C, "<>Closing CF") )) + _xlfn.IFNA(H131, 0)} -> 0 | Z10: {=_xlfn.BYROW(B62, _xlfn.LAMBDA(_xlpm.party, SUMIFS(ledger!J:J, ledger!B:B, _xlpm.party, ledger!E:E, "<>*RD*", ledger!D:D, "Slub", ledger!C:C, "<>Closing CF") ))+ _xlfn.IFNA(I131, 0)} -> 71359.729 | AA10: {=_xlfn.BYROW(B62, _xlfn.LAMBDA(_xlpm.party, SUMIFS(ledger!J:J, ledger!B:B, _xlpm.party, ledger!E:E, "<>*RD*", ledger!D:D, "Satin", ledger!C:C, "<>Closing CF") ))+ _xlfn.IFNA(J131, 0)} -> 0 | AB10: {=_xlfn.BYROW(B62, _xlfn.LAMBDA(_xlpm.party, SUMIFS(ledger!J:J, ledger!B:B, _xlpm.party, ledger!E:E, "<>*RD*", ledger!D:D, "Black-Chamki", ledger!C:C, "<>Closing CF") ))+ _xlfn.IFNA(K131, 0)} -> 322297 | AC10: {=_xlfn.BYROW(B62, _xlfn.LAMBDA(_xlpm.party, SUMIFS(ledger!J:J, ledger!B:B, _xlpm.party, ledger!E:E, "<>*RD*", ledger!D:D, "Kataan", ledger!C:C, "<>Closing CF") ))+ _xlfn.IFNA(L131, 0)} -> 0 | AD10: {=_xlfn.BYROW(B62, _xlfn.LAMBDA(_xlpm.party, SUMIFS(ledger!J:J, ledger!B:B, _xlpm.party, ledger!E:E, "<>*RD*", ledger!D:D, "Munaar", ledger!C:C, "<>Closing CF") ))+ _xlfn.IFNA(M131, 0)} -> 0 | AE10: {=_xlfn.BYROW(B62, _xlfn.LAMBDA(_xlpm.party, SUMIFS(ledger!J:J, ledger!B:B, _xlpm.party, ledger!E:E, "<>*RD*", ledger!D:D, "Super Kataan", ledger!C:C, "<>Closing CF") ))+ _xlfn.IFNA(N131, 0)} -> 0 | AF10: {=_xlfn.BYROW(B62, _xlfn.LAMBDA(_xlpm.party, SUMIFS(ledger!J:J, ledger!B:B, _xlpm.party, ledger!E:E, "<>*RD*", ledger!D:D, "Custom", ledger!C:C, "<>Closing CF") ))+ _xlfn.IFNA(O131, 0)} -> 0 | AG10: =X10+Y10+Z10+AA10+AB10+AC10+AD10+AF10+AE10 -> 10449015 | AH10: =(SUMIF(Table14[Party],S10,Table14[Credit]))+_xlfn.IFNA(Q131,0) -> 10448871 | AI10: =AG10-AH10 -> 144.17922 | AJ10: 10 | AK10: 13
B11: =B66 -> Ashraf Zia | C11: =SUMIFS(ledger!G:G, ledger!B:B, B11, ledger!E:E, "<>*RD*") / 1.0936 -> 0 | D11: 12 | E11: =(SUMIFS(ledger!G:G, ledger!B:B, B11, ledger!E:E, "<>*RD*",ledger!D:D, "Silky") / 1.0936)*12 + (SUMIFS(ledger!G:G, ledger!B:B, B11, ledger!E:E, "<>*RD*",ledger!D:D, "Chamki") / 1.0936)*10 -> 0 | I11: Ashraf Zia | S11: Raaz Fabrics | T11: {=_xlfn.BYROW(B63,_xlfn.LAMBDA(_xlpm.party,SUMIFS(ledger!G:G,ledger!B:B,_xlpm.party,ledger!E:E,"<>*RD*")))+_xlfn.IFNA(C132,0)} -> 283694 | U11: {=_xlfn.BYROW(B63, _xlfn.LAMBDA(_xlpm.party, SUMIFS(ledger!G:G, ledger!B:B, _xlpm.party, ledger!E:E, "<>*RD*") / 1.0936 ))+_xlfn.IFNA(D132,0)} -> 259412.95 | V11: {=(_xlfn.BYROW(B63,_xlfn.LAMBDA(_xlpm.party,SUMIFS(ledger!G:G,ledger!B:B,_xlpm.party,ledger!E:E,"<>*RD*",ledger!D:D,"Chamki")+SUMIFS(ledger!G:G, ledger!B:B, _xlpm.party, ledger!E:E, "<>*RD*", ledger!D:D, "Crinkle")))/1.0936)+_xlfn.IFNA(E132,0)} -> 259412.95 | W11: {=(_xlfn.BYROW(B63,_xlfn.LAMBDA(_xlpm.party,SUMIFS(ledger!G:G,ledger!B:B,_xlpm.party,ledger!E:E,"<>*RD*",ledger!D:D,"Silky")))/1.0936)+_xlfn.IFNA(F132,0)} -> 0 | X11: {=(_xlfn.BYROW(B63,_xlfn.LAMBDA(_xlpm.party, (SUMIFS(ledger!J:J,ledger!B:B,_xlpm.party,ledger!E:E,"<>*RD*",ledger!D:D,"Chamki",ledger!C:C,"<>Closing CF")+ SUMIFS(ledger!J:J,ledger!B:B,_xlpm.party,ledger!E:E,"<>*RD*",ledger!D:D,"Crinkle",ledger!C:C,"<>Closing CF") )+_xlfn.IFNA(G132,0))))} -> 2594129.5 | Y11: {=_xlfn.BYROW(B63, _xlfn.LAMBDA(_xlpm.party, SUMIFS(ledger!J:J, ledger!B:B, _xlpm.party, ledger!E:E, "<>*RD*", ledger!D:D, "Silky", ledger!C:C, "<>Closing CF") )) + _xlfn.IFNA(H132, 0)} -> 0 | Z11: {=_xlfn.BYROW(B63, _xlfn.LAMBDA(_xlpm.party, SUMIFS(ledger!J:J, ledger!B:B, _xlpm.party, ledger!E:E, "<>*RD*", ledger!D:D, "Slub", ledger!C:C, "<>Closing CF") ))+ _xlfn.IFNA(I132, 0)} -> 0 | AA11: {=_xlfn.BYROW(B63, _xlfn.LAMBDA(_xlpm.party, SUMIFS(ledger!J:J, ledger!B:B, _xlpm.party, ledger!E:E, "<>*RD*", ledger!D:D, "Satin", ledger!C:C, "<>Closing CF") ))+ _xlfn.IFNA(J132, 0)} -> 0 | AB11: {=_xlfn.BYROW(B63, _xlfn.LAMBDA(_xlpm.party, SUMIFS(ledger!J:J, ledger!B:B, _xlpm.party, ledger!E:E, "<>*RD*", ledger!D:D, "Black-Chamki", ledger!C:C, "<>Closing CF") ))+ _xlfn.IFNA(K132, 0)} -> 0 | AC11: {=_xlfn.BYROW(B63, _xlfn.LAMBDA(_xlpm.party, SUMIFS(ledger!J:J, ledger!B:B, _xlpm.party, ledger!E:E, "<>*RD*", ledger!D:D, "Kataan", ledger!C:C, "<>Closing CF") ))+ _xlfn.IFNA(L132, 0)} -> 0 | AD11: {=_xlfn.BYROW(B63, _xlfn.LAMBDA(_xlpm.party, SUMIFS(ledger!J:J, ledger!B:B, _xlpm.party, ledger!E:E, "<>*RD*", ledger!D:D, "Munaar", ledger!C:C, "<>Closing CF") ))+ _xlfn.IFNA(M132, 0)} -> 0 | AE11: {=_xlfn.BYROW(B63, _xlfn.LAMBDA(_xlpm.party, SUMIFS(ledger!J:J, ledger!B:B, _xlpm.party, ledger!E:E, "<>*RD*", ledger!D:D, "Super Kataan", ledger!C:C, "<>Closing CF") ))+ _xlfn.IFNA(N132, 0)} -> 0 | AF11: {=_xlfn.BYROW(B63, _xlfn.LAMBDA(_xlpm.party, SUMIFS(ledger!J:J, ledger!B:B, _xlpm.party, ledger!E:E, "<>*RD*", ledger!D:D, "Custom", ledger!C:C, "<>Closing CF") ))+ _xlfn.IFNA(O132, 0)} -> 0 | AG11: =X11+Y11+Z11+AA11+AB11+AC11+AD11+AF11+AE11 -> 2594129.5 | AH11: =(SUMIF(Table14[Party],S11,Table14[Credit]))+_xlfn.IFNA(Q132,0) -> 2176321 | AI11: =AG11-AH11 -> 417808.48 | AJ11: 10 | AK11: 13
B12: =B67 -> Hafiz Qureshi | C12: =SUMIFS(ledger!G:G, ledger!B:B, B12, ledger!E:E, "<>*RD*") / 1.0936 -> 157118.69 | E12: =(SUMIFS(ledger!G:G, ledger!B:B, B12, ledger!E:E, "<>*RD*",ledger!D:D, "Silky") / 1.0936)*12 + (SUMIFS(ledger!G:G, ledger!B:B, B12, ledger!E:E, "<>*RD*",ledger!D:D, "Chamki") / 1.0936)*10 -> 1212006.2 | I12: Hafiz Qureshi | S12: Azam | T12: {=_xlfn.BYROW(B64,_xlfn.LAMBDA(_xlpm.party,SUMIFS(ledger!G:G,ledger!B:B,_xlpm.party,ledger!E:E,"<>*RD*")))+_xlfn.IFNA(C133,0)} -> 749236 | U12: {=_xlfn.BYROW(B64, _xlfn.LAMBDA(_xlpm.party, SUMIFS(ledger!G:G, ledger!B:B, _xlpm.party, ledger!E:E, "<>*RD*") / 1.0936 ))+_xlfn.IFNA(D133,0)} -> 685109.73 | V12: {=(_xlfn.BYROW(B64,_xlfn.LAMBDA(_xlpm.party,SUMIFS(ledger!G:G,ledger!B:B,_xlpm.party,ledger!E:E,"<>*RD*",ledger!D:D,"Chamki")+SUMIFS(ledger!G:G, ledger!B:B, _xlpm.party, ledger!E:E, "<>*RD*", ledger!D:D, "Crinkle")))/1.0936)+_xlfn.IFNA(E133,0)} -> 501118.32 | W12: {=(_xlfn.BYROW(B64,_xlfn.LAMBDA(_xlpm.party,SUMIFS(ledger!G:G,ledger!B:B,_xlpm.party,ledger!E:E,"<>*RD*",ledger!D:D,"Silky")))/1.0936)+_xlfn.IFNA(F133,0)} -> 183991.4 | X12: {=(_xlfn.BYROW(B64,_xlfn.LAMBDA(_xlpm.party, (SUMIFS(ledger!J:J,ledger!B:B,_xlpm.party,ledger!E:E,"<>*RD*",ledger!D:D,"Chamki",ledger!C:C,"<>Closing CF")+ SUMIFS(ledger!J:J,ledger!B:B,_xlpm.party,ledger!E:E,"<>*RD*",ledger!D:D,"Crinkle",ledger!C:C,"<>Closing CF") )+_xlfn.IFNA(G133,0))))} -> 5011183.2 | Y12: {=_xlfn.BYROW(B64, _xlfn.LAMBDA(_xlpm.party, SUMIFS(ledger!J:J, ledger!B:B, _xlpm.party, ledger!E:E, "<>*RD*", ledger!D:D, "Silky", ledger!C:C, "<>Closing CF") )) + _xlfn.IFNA(H133, 0)} -> 2391888.3 | Z12: {=_xlfn.BYROW(B64, _xlfn.LAMBDA(_xlpm.party, SUMIFS(ledger!J:J, ledger!B:B, _xlpm.party, ledger!E:E, "<>*RD*", ledger!D:D, "Slub", ledger!C:C, "<>Closing CF") ))+ _xlfn.IFNA(I133, 0)} -> 0 | AA12: {=_xlfn.BYROW(B64, _xlfn.LAMBDA(_xlpm.party, SUMIFS(ledger!J:J, ledger!B:B, _xlpm.party, ledger!E:E, "<>*RD*", ledger!D:D, "Satin", ledger!C:C, "<>Closing CF") ))+ _xlfn.IFNA(J133, 0)} -> 0 | AB12: {=_xlfn.BYROW(B64, _xlfn.LAMBDA(_xlpm.party, SUMIFS(ledger!J:J, ledger!B:B, _xlpm.party, ledger!E:E, "<>*RD*", ledger!D:D, "Black-Chamki", ledger!C:C, "<>Closing CF") ))+ _xlfn.IFNA(K133, 0)} -> 0 | AC12: {=_xlfn.BYROW(B64, _xlfn.LAMBDA(_xlpm.party, SUMIFS(ledger!J:J, ledger!B:B, _xlpm.party, ledger!E:E, "<>*RD*", ledger!D:D, "Kataan", ledger!C:C, "<>Closing CF") ))+ _xlfn.IFNA(L133, 0)} -> 0 | AD12: {=_xlfn.BYROW(B64, _xlfn.LAMBDA(_xlpm.party, SUMIFS(ledger!J:J, ledger!B:B, _xlpm.party, ledger!E:E, "<>*RD*", ledger!D:D, "Munaar", ledger!C:C, "<>Closing CF") ))+ _xlfn.IFNA(M133, 0)} -> 0 | AE12: {=_xlfn.BYROW(B64, _xlfn.LAMBDA(_xlpm.party, SUMIFS(ledger!J:J, ledger!B:B, _xlpm.party, ledger!E:E, "<>*RD*", ledger!D:D, "Super Kataan", ledger!C:C, "<>Closing CF") ))+ _xlfn.IFNA(N133, 0)} -> 0 | AF12: {=_xlfn.BYROW(B64, _xlfn.LAMBDA(_xlpm.party, SUMIFS(ledger!J:J, ledger!B:B, _xlpm.party, ledger!E:E, "<>*RD*", ledger!D:D, "Custom", ledger!C:C, "<>Closing CF") ))+ _xlfn.IFNA(O133, 0)} -> 0 | AG12: =X12+Y12+Z12+AA12+AB12+AC12+AD12+AF12+AE12 -> 7403071.5 | AH12: =(SUMIF(Table14[Party],S12,Table14[Credit]))+_xlfn.IFNA(Q133,0) -> 7402540 | AI12: =AG12-AH12 -> 531.50695 | AJ12: 10 | AK12: 13
B13: =B68 -> Badshah Fabrics | C13: =SUMIFS(ledger!G:G, ledger!B:B, B13, ledger!E:E, "<>*RD*") / 1.0936 -> 0 | E13: =(SUMIFS(ledger!G:G, ledger!B:B, B13, ledger!E:E, "<>*RD*",ledger!D:D, "Silky") / 1.0936)*12 + (SUMIFS(ledger!G:G, ledger!B:B, B13, ledger!E:E, "<>*RD*",ledger!D:D, "Chamki") / 1.0936)*10 -> 0 | I13: Badshah Fabrics | S13: Ubaidullah | T13: {=_xlfn.BYROW(B65,_xlfn.LAMBDA(_xlpm.party,SUMIFS(ledger!G:G,ledger!B:B,_xlpm.party,ledger!E:E,"<>*RD*")))+_xlfn.IFNA(C134,0)} -> 336741 | U13: {=_xlfn.BYROW(B65, _xlfn.LAMBDA(_xlpm.party, SUMIFS(ledger!G:G, ledger!B:B, _xlpm.party, ledger!E:E, "<>*RD*") / 1.0936 ))+_xlfn.IFNA(D134,0)} -> 307919.71 | V13: {=(_xlfn.BYROW(B65,_xlfn.LAMBDA(_xlpm.party,SUMIFS(ledger!G:G,ledger!B:B,_xlpm.party,ledger!E:E,"<>*RD*",ledger!D:D,"Chamki")+SUMIFS(ledger!G:G, ledger!B:B, _xlpm.party, ledger!E:E, "<>*RD*", ledger!D:D, "Crinkle")))/1.0936)+_xlfn.IFNA(E134,0)} -> 46132.955 | W13: {=(_xlfn.BYROW(B65,_xlfn.LAMBDA(_xlpm.party,SUMIFS(ledger!G:G,ledger!B:B,_xlpm.party,ledger!E:E,"<>*RD*",ledger!D:D,"Silky")))/1.0936)+_xlfn.IFNA(F134,0)} -> 261786.76 | X13: {=(_xlfn.BYROW(B65,_xlfn.LAMBDA(_xlpm.party, (SUMIFS(ledger!J:J,ledger!B:B,_xlpm.party,ledger!E:E,"<>*RD*",ledger!D:D,"Chamki",ledger!C:C,"<>Closing CF")+ SUMIFS(ledger!J:J,ledger!B:B,_xlpm.party,ledger!E:E,"<>*RD*",ledger!D:D,"Crinkle",ledger!C:C,"<>Closing CF") )+_xlfn.IFNA(G134,0))))} -> 461329.55 | Y13: {=_xlfn.BYROW(B65, _xlfn.LAMBDA(_xlpm.party, SUMIFS(ledger!J:J, ledger!B:B, _xlpm.party, ledger!E:E, "<>*RD*", ledger!D:D, "Silky", ledger!C:C, "<>Closing CF") )) + _xlfn.IFNA(H134, 0)} -> 3189934.2 | Z13: {=_xlfn.BYROW(B65, _xlfn.LAMBDA(_xlpm.party, SUMIFS(ledger!J:J, ledger!B:B, _xlpm.party, ledger!E:E, "<>*RD*", ledger!D:D, "Slub", ledger!C:C, "<>Closing CF") ))+ _xlfn.IFNA(I134, 0)} -> 0 | AA13: {=_xlfn.BYROW(B65, _xlfn.LAMBDA(_xlpm.party, SUMIFS(ledger!J:J, ledger!B:B, _xlpm.party, ledger!E:E, "<>*RD*", ledger!D:D, "Satin", ledger!C:C, "<>Closing CF") ))+ _xlfn.IFNA(J134, 0)} -> 0 | AB13: {=_xlfn.BYROW(B65, _xlfn.LAMBDA(_xlpm.party, SUMIFS(ledger!J:J, ledger!B:B, _xlpm.party, ledger!E:E, "<>*RD*", ledger!D:D, "Black-Chamki", ledger!C:C, "<>Closing CF") ))+ _xlfn.IFNA(K134, 0)} -> 0 | AC13: {=_xlfn.BYROW(B65, _xlfn.LAMBDA(_xlpm.party, SUMIFS(ledger!J:J, ledger!B:B, _xlpm.party, ledger!E:E, "<>*RD*", ledger!D:D, "Kataan", ledger!C:C, "<>Closing CF") ))+ _xlfn.IFNA(L134, 0)} -> 0 | AD13: {=_xlfn.BYROW(B65, _xlfn.LAMBDA(_xlpm.party, SUMIFS(ledger!J:J, ledger!B:B, _xlpm.party, ledger!E:E, "<>*RD*", ledger!D:D, "Munaar", ledger!C:C, "<>Closing CF") ))+ _xlfn.IFNA(M134, 0)} -> 0 | AE13: {=_xlfn.BYROW(B65, _xlfn.LAMBDA(_xlpm.party, SUMIFS(ledger!J:J, ledger!B:B, _xlpm.party, ledger!E:E, "<>*RD*", ledger!D:D, "Super Kataan", ledger!C:C, "<>Closing CF") ))+ _xlfn.IFNA(N134, 0)} -> 0 | AF13: {=_xlfn.BYROW(B65, _xlfn.LAMBDA(_xlpm.party, SUMIFS(ledger!J:J, ledger!B:B, _xlpm.party, ledger!E:E, "<>*RD*", ledger!D:D, "Custom", ledger!C:C, "<>Closing CF") ))+ _xlfn.IFNA(O134, 0)} -> 0 | AG13: =X13+Y13+Z13+AA13+AB13+AC13+AD13+AF13+AE13 -> 3651263.7 | AH13: =(SUMIF(Table14[Party],S13,Table14[Credit]))+_xlfn.IFNA(Q134,0) -> 3649649 | AI13: =AG13-AH13 -> 1614.7162 | AJ13: 10 | AK13: 13
B14: =B69 -> Gauhar Kashif | C14: =SUMIFS(ledger!G:G, ledger!B:B, B14, ledger!E:E, "<>*RD*") / 1.0936 -> 0 | E14: =(SUMIFS(ledger!G:G, ledger!B:B, B14, ledger!E:E, "<>*RD*",ledger!D:D, "Silky") / 1.0936)*12 + (SUMIFS(ledger!G:G, ledger!B:B, B14, ledger!E:E, "<>*RD*",ledger!D:D, "Chamki") / 1.0936)*10 -> 0 | I14: Reject | S14: Ashraf Zia | T14: {=_xlfn.BYROW(B66,_xlfn.LAMBDA(_xlpm.party,SUMIFS(ledger!G:G,ledger!B:B,_xlpm.party,ledger!E:E,"<>*RD*")))+_xlfn.IFNA(C135,0)} -> 23305 | U14: {=_xlfn.BYROW(B66, _xlfn.LAMBDA(_xlpm.party, SUMIFS(ledger!G:G, ledger!B:B, _xlpm.party, ledger!E:E, "<>*RD*") / 1.0936 ))+_xlfn.IFNA(D135,0)} -> 21310.351 | V14: {=(_xlfn.BYROW(B66,_xlfn.LAMBDA(_xlpm.party,SUMIFS(ledger!G:G,ledger!B:B,_xlpm.party,ledger!E:E,"<>*RD*",ledger!D:D,"Chamki")+SUMIFS(ledger!G:G, ledger!B:B, _xlpm.party, ledger!E:E, "<>*RD*", ledger!D:D, "Crinkle")))/1.0936)+_xlfn.IFNA(E135,0)} -> 21310.351 | W14: {=(_xlfn.BYROW(B66,_xlfn.LAMBDA(_xlpm.party,SUMIFS(ledger!G:G,ledger!B:B,_xlpm.party,ledger!E:E,"<>*RD*",ledger!D:D,"Silky")))/1.0936)+_xlfn.IFNA(F135,0)} -> 0 | X14: {=(_xlfn.BYROW(B66,_xlfn.LAMBDA(_xlpm.party, (SUMIFS(ledger!J:J,ledger!B:B,_xlpm.party,ledger!E:E,"<>*RD*",ledger!D:D,"Chamki",ledger!C:C,"<>Closing CF")+ SUMIFS(ledger!J:J,ledger!B:B,_xlpm.party,ledger!E:E,"<>*RD*",ledger!D:D,"Crinkle",ledger!C:C,"<>Closing CF") )+_xlfn.IFNA(G135,0))))} -> 255724.21 | Y14: {=_xlfn.BYROW(B66, _xlfn.LAMBDA(_xlpm.party, SUMIFS(ledger!J:J, ledger!B:B, _xlpm.party, ledger!E:E, "<>*RD*", ledger!D:D, "Silky", ledger!C:C, "<>Closing CF") )) + _xlfn.IFNA(H135, 0)} -> 0 | Z14: {=_xlfn.BYROW(B66, _xlfn.LAMBDA(_xlpm.party, SUMIFS(ledger!J:J, ledger!B:B, _xlpm.party, ledger!E:E, "<>*RD*", ledger!D:D, "Slub", ledger!C:C, "<>Closing CF") ))+ _xlfn.IFNA(I135, 0)} -> 0 | AA14: {=_xlfn.BYROW(B66, _xlfn.LAMBDA(_xlpm.party, SUMIFS(ledger!J:J, ledger!B:B, _xlpm.party, ledger!E:E, "<>*RD*", ledger!D:D, "Satin", ledger!C:C, "<>Closing CF") ))+ _xlfn.IFNA(J135, 0)} -> 0 | AB14: {=_xlfn.BYROW(B66, _xlfn.LAMBDA(_xlpm.party, SUMIFS(ledger!J:J, ledger!B:B, _xlpm.party, ledger!E:E, "<>*RD*", ledger!D:D, "Black-Chamki", ledger!C:C, "<>Closing CF") ))+ _xlfn.IFNA(K135, 0)} -> 0 | AC14: {=_xlfn.BYROW(B66, _xlfn.LAMBDA(_xlpm.party, SUMIFS(ledger!J:J, ledger!B:B, _xlpm.party, ledger!E:E, "<>*RD*", ledger!D:D, "Kataan", ledger!C:C, "<>Closing CF") ))+ _xlfn.IFNA(L135, 0)} -> 0 | AD14: {=_xlfn.BYROW(B66, _xlfn.LAMBDA(_xlpm.party, SUMIFS(ledger!J:J, ledger!B:B, _xlpm.party, ledger!E:E, "<>*RD*", ledger!D:D, "Munaar", ledger!C:C, "<>Closing CF") ))+ _xlfn.IFNA(M135, 0)} -> 0 | AE14: {=_xlfn.BYROW(B66, _xlfn.LAMBDA(_xlpm.party, SUMIFS(ledger!J:J, ledger!B:B, _xlpm.party, ledger!E:E, "<>*RD*", ledger!D:D, "Super Kataan", ledger!C:C, "<>Closing CF") ))+ _xlfn.IFNA(N135, 0)} -> 0 | AF14: {=_xlfn.BYROW(B66, _xlfn.LAMBDA(_xlpm.party, SUMIFS(ledger!J:J, ledger!B:B, _xlpm.party, ledger!E:E, "<>*RD*", ledger!D:D, "Custom", ledger!C:C, "<>Closing CF") ))+ _xlfn.IFNA(O135, 0)} -> 0 | AG14: =X14+Y14+Z14+AA14+AB14+AC14+AD14+AF14+AE14 -> 255724.21 | AH14: =(SUMIF(Table14[Party],S14,Table14[Credit]))+_xlfn.IFNA(Q135,0) -> 130000 | AI14: =AG14-AH14 -> 125724.21 | AJ14: 12 | AK14: 13
B15: =B70 -> Amjad 7up | C15: =SUMIFS(ledger!G:G, ledger!B:B, B15, ledger!E:E, "<>*RD*") / 1.0936 -> 0 | E15: =(SUMIFS(ledger!G:G, ledger!B:B, B15, ledger!E:E, "<>*RD*",ledger!D:D, "Silky") / 1.0936)*12 + (SUMIFS(ledger!G:G, ledger!B:B, B15, ledger!E:E, "<>*RD*",ledger!D:D, "Chamki") / 1.0936)*10 -> 0 | I15: Amjad 7up | S15: Hafiz Qureshi | T15: {=_xlfn.BYROW(B67,_xlfn.LAMBDA(_xlpm.party,SUMIFS(ledger!G:G,ledger!B:B,_xlpm.party,ledger!E:E,"<>*RD*")))+_xlfn.IFNA(C136,0)} -> 809806 | U15: {=_xlfn.BYROW(B67, _xlfn.LAMBDA(_xlpm.party, SUMIFS(ledger!G:G, ledger!B:B, _xlpm.party, ledger!E:E, "<>*RD*") / 1.0936 ))+_xlfn.IFNA(D136,0)} -> 740495.61 | V15: {=(_xlfn.BYROW(B67,_xlfn.LAMBDA(_xlpm.party,SUMIFS(ledger!G:G,ledger!B:B,_xlpm.party,ledger!E:E,"<>*RD*",ledger!D:D,"Chamki")+SUMIFS(ledger!G:G, ledger!B:B, _xlpm.party, ledger!E:E, "<>*RD*", ledger!D:D, "Crinkle")))/1.0936)+_xlfn.IFNA(E136,0)} -> 635991.22 | W15: {=(_xlfn.BYROW(B67,_xlfn.LAMBDA(_xlpm.party,SUMIFS(ledger!G:G,ledger!B:B,_xlpm.party,ledger!E:E,"<>*RD*",ledger!D:D,"Silky")))/1.0936)+_xlfn.IFNA(F136,0)} -> 57155.267 | X15: {=(_xlfn.BYROW(B67,_xlfn.LAMBDA(_xlpm.party, (SUMIFS(ledger!J:J,ledger!B:B,_xlpm.party,ledger!E:E,"<>*RD*",ledger!D:D,"Chamki",ledger!C:C,"<>Closing CF")+ SUMIFS(ledger!J:J,ledger!B:B,_xlpm.party,ledger!E:E,"<>*RD*",ledger!D:D,"Crinkle",ledger!C:C,"<>Closing CF") )+_xlfn.IFNA(G136,0))))} -> 6359912.2 | Y15: {=_xlfn.BYROW(B67, _xlfn.LAMBDA(_xlpm.party, SUMIFS(ledger!J:J, ledger!B:B, _xlpm.party, ledger!E:E, "<>*RD*", ledger!D:D, "Silky", ledger!C:C, "<>Closing CF") )) + _xlfn.IFNA(H136, 0)} -> 743018.47 | Z15: {=_xlfn.BYROW(B67, _xlfn.LAMBDA(_xlpm.party, SUMIFS(ledger!J:J, ledger!B:B, _xlpm.party, ledger!E:E, "<>*RD*", ledger!D:D, "Slub", ledger!C:C, "<>Closing CF") ))+ _xlfn.IFNA(I136, 0)} -> 0 | AA15: {=_xlfn.BYROW(B67, _xlfn.LAMBDA(_xlpm.party, SUMIFS(ledger!J:J, ledger!B:B, _xlpm.party, ledger!E:E, "<>*RD*", ledger!D:D, "Satin", ledger!C:C, "<>Closing CF") ))+ _xlfn.IFNA(J136, 0)} -> 0 | AB15: {=_xlfn.BYROW(B67, _xlfn.LAMBDA(_xlpm.party, SUMIFS(ledger!J:J, ledger!B:B, _xlpm.party, ledger!E:E, "<>*RD*", ledger!D:D, "Black-Chamki", ledger!C:C, "<>Closing CF") ))+ _xlfn.IFNA(K136, 0)} -> 0 | AC15: {=_xlfn.BYROW(B67, _xlfn.LAMBDA(_xlpm.party, SUMIFS(ledger!J:J, ledger!B:B, _xlpm.party, ledger!E:E, "<>*RD*", ledger!D:D, "Kataan", ledger!C:C, "<>Closing CF") ))+ _xlfn.IFNA(L136, 0)} -> 520840.34 | AD15: {=_xlfn.BYROW(B67, _xlfn.LAMBDA(_xlpm.party, SUMIFS(ledger!J:J, ledger!B:B, _xlpm.party, ledger!E:E, "<>*RD*", ledger!D:D, "Munaar", ledger!C:C, "<>Closing CF") ))+ _xlfn.IFNA(M136, 0)} -> 0 | AE15: {=_xlfn.BYROW(B67, _xlfn.LAMBDA(_xlpm.party, SUMIFS(ledger!J:J, ledger!B:B, _xlpm.party, ledger!E:E, "<>*RD*", ledger!D:D, "Super Kataan", ledger!C:C, "<>Closing CF") ))+ _xlfn.IFNA(N136, 0)} -> 0 | AF15: {=_xlfn.BYROW(B67, _xlfn.LAMBDA(_xlpm.party, SUMIFS(ledger!J:J, ledger!B:B, _xlpm.party, ledger!E:E, "<>*RD*", ledger!D:D, "Custom", ledger!C:C, "<>Closing CF") ))+ _xlfn.IFNA(O136, 0)} -> 0 | AG15: =X15+Y15+Z15+AA15+AB15+AC15+AD15+AF15+AE15 -> 7623771 | AH15: =(SUMIF(Table14[Party],S15,Table14[Credit]))+_xlfn.IFNA(Q136,0) -> 6835303 | AI15: =AG15-AH15 -> 788468.03 | AJ15: 10 | AK15: 13
B16: =B71 -> Hazrat Khan | C16: =SUMIFS(ledger!G:G, ledger!B:B, B16, ledger!E:E, "<>*RD*") / 1.0936 -> 0 | E16: =(SUMIFS(ledger!G:G, ledger!B:B, B16, ledger!E:E, "<>*RD*",ledger!D:D, "Silky") / 1.0936)*12 + (SUMIFS(ledger!G:G, ledger!B:B, B16, ledger!E:E, "<>*RD*",ledger!D:D, "Chamki") / 1.0936)*10 -> 0 | I16: Hazrat Khan | S16: Badshah Fabrics | T16: {=_xlfn.BYROW(B68,_xlfn.LAMBDA(_xlpm.party,SUMIFS(ledger!G:G,ledger!B:B,_xlpm.party,ledger!E:E,"<>*RD*")))+_xlfn.IFNA(C137,0)} -> 681314 | U16: {=_xlfn.BYROW(B68, _xlfn.LAMBDA(_xlpm.party, SUMIFS(ledger!G:G, ledger!B:B, _xlpm.party, ledger!E:E, "<>*RD*") / 1.0936 ))+_xlfn.IFNA(D137,0)} -> 623001.1 | V16: {=(_xlfn.BYROW(B68,_xlfn.LAMBDA(_xlpm.party,SUMIFS(ledger!G:G,ledger!B:B,_xlpm.party,ledger!E:E,"<>*RD*",ledger!D:D,"Chamki")+SUMIFS(ledger!G:G, ledger!B:B, _xlpm.party, ledger!E:E, "<>*RD*", ledger!D:D, "Crinkle")))/1.0936)+_xlfn.IFNA(E137,0)} -> 481526.15 | W16: {=(_xlfn.BYROW(B68,_xlfn.LAMBDA(_xlpm.party,SUMIFS(ledger!G:G,ledger!B:B,_xlpm.party,ledger!E:E,"<>*RD*",ledger!D:D,"Silky")))/1.0936)+_xlfn.IFNA(F137,0)} -> 141474.95 | X16: {=(_xlfn.BYROW(B68,_xlfn.LAMBDA(_xlpm.party, (SUMIFS(ledger!J:J,ledger!B:B,_xlpm.party,ledger!E:E,"<>*RD*",ledger!D:D,"Chamki",ledger!C:C,"<>Closing CF")+ SUMIFS(ledger!J:J,ledger!B:B,_xlpm.party,ledger!E:E,"<>*RD*",ledger!D:D,"Crinkle",ledger!C:C,"<>Closing CF") )+_xlfn.IFNA(G137,0))))} -> 4861679.8 | Y16: {=_xlfn.BYROW(B68, _xlfn.LAMBDA(_xlpm.party, SUMIFS(ledger!J:J, ledger!B:B, _xlpm.party, ledger!E:E, "<>*RD*", ledger!D:D, "Silky", ledger!C:C, "<>Closing CF") )) + _xlfn.IFNA(H137, 0)} -> 1776019.6 | Z16: {=_xlfn.BYROW(B68, _xlfn.LAMBDA(_xlpm.party, SUMIFS(ledger!J:J, ledger!B:B, _xlpm.party, ledger!E:E, "<>*RD*", ledger!D:D, "Slub", ledger!C:C, "<>Closing CF") ))+ _xlfn.IFNA(I137, 0)} -> 0 | AA16: {=_xlfn.BYROW(B68, _xlfn.LAMBDA(_xlpm.party, SUMIFS(ledger!J:J, ledger!B:B, _xlpm.party, ledger!E:E, "<>*RD*", ledger!D:D, "Satin", ledger!C:C, "<>Closing CF") ))+ _xlfn.IFNA(J137, 0)} -> 0 | AB16: {=_xlfn.BYROW(B68, _xlfn.LAMBDA(_xlpm.party, SUMIFS(ledger!J:J, ledger!B:B, _xlpm.party, ledger!E:E, "<>*RD*", ledger!D:D, "Black-Chamki", ledger!C:C, "<>Closing CF") ))+ _xlfn.IFNA(K137, 0)} -> 0 | AC16: {=_xlfn.BYROW(B68, _xlfn.LAMBDA(_xlpm.party, SUMIFS(ledger!J:J, ledger!B:B, _xlpm.party, ledger!E:E, "<>*RD*", ledger!D:D, "Kataan", ledger!C:C, "<>Closing CF") ))+ _xlfn.IFNA(L137, 0)} -> 0 | AD16: {=_xlfn.BYROW(B68, _xlfn.LAMBDA(_xlpm.party, SUMIFS(ledger!J:J, ledger!B:B, _xlpm.party, ledger!E:E, "<>*RD*", ledger!D:D, "Munaar", ledger!C:C, "<>Closing CF") ))+ _xlfn.IFNA(M137, 0)} -> 0 | AE16: {=_xlfn.BYROW(B68, _xlfn.LAMBDA(_xlpm.party, SUMIFS(ledger!J:J, ledger!B:B, _xlpm.party, ledger!E:E, "<>*RD*", ledger!D:D, "Super Kataan", ledger!C:C, "<>Closing CF") ))+ _xlfn.IFNA(N137, 0)} -> 0 | AF16: {=_xlfn.BYROW(B68, _xlfn.LAMBDA(_xlpm.party, SUMIFS(ledger!J:J, ledger!B:B, _xlpm.party, ledger!E:E, "<>*RD*", ledger!D:D, "Custom", ledger!C:C, "<>Closing CF") ))+ _xlfn.IFNA(O137, 0)} -> 0 | AG16: =X16+Y16+Z16+AA16+AB16+AC16+AD16+AF16+AE16 -> 6637699.3 | AH16: =(SUMIF(Table14[Party],S16,Table14[Credit]))+_xlfn.IFNA(Q137,0) -> 6545761 | AI16: =AG16-AH16 -> 91938.342 | AJ16: 10 | AK16: 13
B17: =B72 -> Haseeb Shamsi | C17: =SUMIFS(ledger!G:G, ledger!B:B, B17, ledger!E:E, "<>*RD*") / 1.0936 -> 0 | E17: =(SUMIFS(ledger!G:G, ledger!B:B, B17, ledger!E:E, "<>*RD*",ledger!D:D, "Silky") / 1.0936)*12 + (SUMIFS(ledger!G:G, ledger!B:B, B17, ledger!E:E, "<>*RD*",ledger!D:D, "Chamki") / 1.0936)*10 -> 0 | I17: Haseeb Shamsi | S17: Gauhar Kashif | T17: {=_xlfn.BYROW(B69,_xlfn.LAMBDA(_xlpm.party,SUMIFS(ledger!G:G,ledger!B:B,_xlpm.party,ledger!E:E,"<>*RD*")))+_xlfn.IFNA(C138,0)} -> 132768 | U17: {=_xlfn.BYROW(B69, _xlfn.LAMBDA(_xlpm.party, SUMIFS(ledger!G:G, ledger!B:B, _xlpm.party, ledger!E:E, "<>*RD*") / 1.0936 ))+_xlfn.IFNA(D138,0)} -> 121404.54 | V17: {=(_xlfn.BYROW(B69,_xlfn.LAMBDA(_xlpm.party,SUMIFS(ledger!G:G,ledger!B:B,_xlpm.party,ledger!E:E,"<>*RD*",ledger!D:D,"Chamki")+SUMIFS(ledger!G:G, ledger!B:B, _xlpm.party, ledger!E:E, "<>*RD*", ledger!D:D, "Crinkle")))/1.0936)+_xlfn.IFNA(E138,0)} -> 121404.54 | W17: {=(_xlfn.BYROW(B69,_xlfn.LAMBDA(_xlpm.party,SUMIFS(ledger!G:G,ledger!B:B,_xlpm.party,ledger!E:E,"<>*RD*",ledger!D:D,"Silky")))/1.0936)+_xlfn.IFNA(F138,0)} -> 0 | X17: {=(_xlfn.BYROW(B69,_xlfn.LAMBDA(_xlpm.party, (SUMIFS(ledger!J:J,ledger!B:B,_xlpm.party,ledger!E:E,"<>*RD*",ledger!D:D,"Chamki",ledger!C:C,"<>Closing CF")+ SUMIFS(ledger!J:J,ledger!B:B,_xlpm.party,ledger!E:E,"<>*RD*",ledger!D:D,"Crinkle",ledger!C:C,"<>Closing CF") )+_xlfn.IFNA(G138,0))))} -> 1214045.4 | Y17: {=_xlfn.BYROW(B69, _xlfn.LAMBDA(_xlpm.party, SUMIFS(ledger!J:J, ledger!B:B, _xlpm.party, ledger!E:E, "<>*RD*", ledger!D:D, "Silky", ledger!C:C, "<>Closing CF") )) + _xlfn.IFNA(H138, 0)} -> 0 | Z17: {=_xlfn.BYROW(B69, _xlfn.LAMBDA(_xlpm.party, SUMIFS(ledger!J:J, ledger!B:B, _xlpm.party, ledger!E:E, "<>*RD*", ledger!D:D, "Slub", ledger!C:C, "<>Closing CF") ))+ _xlfn.IFNA(I138, 0)} -> 0 | AA17: {=_xlfn.BYROW(B69, _xlfn.LAMBDA(_xlpm.party, SUMIFS(ledger!J:J, ledger!B:B, _xlpm.party, ledger!E:E, "<>*RD*", ledger!D:D, "Satin", ledger!C:C, "<>Closing CF") ))+ _xlfn.IFNA(J138, 0)} -> 0 | AB17: {=_xlfn.BYROW(B69, _xlfn.LAMBDA(_xlpm.party, SUMIFS(ledger!J:J, ledger!B:B, _xlpm.party, ledger!E:E, "<>*RD*", ledger!D:D, "Black-Chamki", ledger!C:C, "<>Closing CF") ))+ _xlfn.IFNA(K138, 0)} -> 0 | AC17: {=_xlfn.BYROW(B69, _xlfn.LAMBDA(_xlpm.party, SUMIFS(ledger!J:J, ledger!B:B, _xlpm.party, ledger!E:E, "<>*RD*", ledger!D:D, "Kataan", ledger!C:C, "<>Closing CF") ))+ _xlfn.IFNA(L138, 0)} -> 0 | AD17: {=_xlfn.BYROW(B69, _xlfn.LAMBDA(_xlpm.party, SUMIFS(ledger!J:J, ledger!B:B, _xlpm.party, ledger!E:E, "<>*RD*", ledger!D:D, "Munaar", ledger!C:C, "<>Closing CF") ))+ _xlfn.IFNA(M138, 0)} -> 0 | AE17: {=_xlfn.BYROW(B69, _xlfn.LAMBDA(_xlpm.party, SUMIFS(ledger!J:J, ledger!B:B, _xlpm.party, ledger!E:E, "<>*RD*", ledger!D:D, "Super Kataan", ledger!C:C, "<>Closing CF") ))+ _xlfn.IFNA(N138, 0)} -> 0 | AF17: {=_xlfn.BYROW(B69, _xlfn.LAMBDA(_xlpm.party, SUMIFS(ledger!J:J, ledger!B:B, _xlpm.party, ledger!E:E, "<>*RD*", ledger!D:D, "Custom", ledger!C:C, "<>Closing CF") ))+ _xlfn.IFNA(O138, 0)} -> 0 | AG17: =X17+Y17+Z17+AA17+AB17+AC17+AD17+AF17+AE17 -> 1214045.4 | AH17: =(SUMIF(Table14[Party],S17,Table14[Credit]))+_xlfn.IFNA(Q138,0) -> 1214045 | AI17: =AG17-AH17 -> 0.35479151 | AJ17: 10 | AK17: 13
B18: =B73 -> Faizan | C18: =SUMIFS(ledger!G:G, ledger!B:B, B18, ledger!E:E, "<>*RD*") / 1.0936 -> 0 | E18: =(SUMIFS(ledger!G:G, ledger!B:B, B18, ledger!E:E, "<>*RD*",ledger!D:D, "Silky") / 1.0936)*12 + (SUMIFS(ledger!G:G, ledger!B:B, B18, ledger!E:E, "<>*RD*",ledger!D:D, "Chamki") / 1.0936)*10 -> 0 | I18: Faizan | S18: Amjad 7up | T18: {=_xlfn.BYROW(B70,_xlfn.LAMBDA(_xlpm.party,SUMIFS(ledger!G:G,ledger!B:B,_xlpm.party,ledger!E:E,"<>*RD*")))+_xlfn.IFNA(C139,0)} -> 52914 | U18: {=_xlfn.BYROW(B70, _xlfn.LAMBDA(_xlpm.party, SUMIFS(ledger!G:G, ledger!B:B, _xlpm.party, ledger!E:E, "<>*RD*") / 1.0936 ))+_xlfn.IFNA(D139,0)} -> 48385.15 | V18: {=(_xlfn.BYROW(B70,_xlfn.LAMBDA(_xlpm.party,SUMIFS(ledger!G:G,ledger!B:B,_xlpm.party,ledger!E:E,"<>*RD*",ledger!D:D,"Chamki")+SUMIFS(ledger!G:G, ledger!B:B, _xlpm.party, ledger!E:E, "<>*RD*", ledger!D:D, "Crinkle")))/1.0936)+_xlfn.IFNA(E139,0)} -> 48385.15 | W18: {=(_xlfn.BYROW(B70,_xlfn.LAMBDA(_xlpm.party,SUMIFS(ledger!G:G,ledger!B:B,_xlpm.party,ledger!E:E,"<>*RD*",ledger!D:D,"Silky")))/1.0936)+_xlfn.IFNA(F139,0)} -> 0 | X18: {=(_xlfn.BYROW(B70,_xlfn.LAMBDA(_xlpm.party, (SUMIFS(ledger!J:J,ledger!B:B,_xlpm.party,ledger!E:E,"<>*RD*",ledger!D:D,"Chamki",ledger!C:C,"<>Closing CF")+ SUMIFS(ledger!J:J,ledger!B:B,_xlpm.party,ledger!E:E,"<>*RD*",ledger!D:D,"Crinkle",ledger!C:C,"<>Closing CF") )+_xlfn.IFNA(G139,0))))} -> 483851.5 | Y18: {=_xlfn.BYROW(B70, _xlfn.LAMBDA(_xlpm.party, SUMIFS(ledger!J:J, ledger!B:B, _xlpm.party, ledger!E:E, "<>*RD*", ledger!D:D, "Silky", ledger!C:C, "<>Closing CF") )) + _xlfn.IFNA(H139, 0)} -> 0 | Z18: {=_xlfn.BYROW(B70, _xlfn.LAMBDA(_xlpm.party, SUMIFS(ledger!J:J, ledger!B:B, _xlpm.party, ledger!E:E, "<>*RD*", ledger!D:D, "Slub", ledger!C:C, "<>Closing CF") ))+ _xlfn.IFNA(I139, 0)} -> 0 | AA18: {=_xlfn.BYROW(B70, _xlfn.LAMBDA(_xlpm.party, SUMIFS(ledger!J:J, ledger!B:B, _xlpm.party, ledger!E:E, "<>*RD*", ledger!D:D, "Satin", ledger!C:C, "<>Closing CF") ))+ _xlfn.IFNA(J139, 0)} -> 0 | AB18: {=_xlfn.BYROW(B70, _xlfn.LAMBDA(_xlpm.party, SUMIFS(ledger!J:J, ledger!B:B, _xlpm.party, ledger!E:E, "<>*RD*", ledger!D:D, "Black-Chamki", ledger!C:C, "<>Closing CF") ))+ _xlfn.IFNA(K139, 0)} -> 0 | AC18: {=_xlfn.BYROW(B70, _xlfn.LAMBDA(_xlpm.party, SUMIFS(ledger!J:J, ledger!B:B, _xlpm.party, ledger!E:E, "<>*RD*", ledger!D:D, "Kataan", ledger!C:C, "<>Closing CF") ))+ _xlfn.IFNA(L139, 0)} -> 0 | AD18: {=_xlfn.BYROW(B70, _xlfn.LAMBDA(_xlpm.party, SUMIFS(ledger!J:J, ledger!B:B, _xlpm.party, ledger!E:E, "<>*RD*", ledger!D:D, "Munaar", ledger!C:C, "<>Closing CF") ))+ _xlfn.IFNA(M139, 0)} -> 0 | AE18: {=_xlfn.BYROW(B70, _xlfn.LAMBDA(_xlpm.party, SUMIFS(ledger!J:J, ledger!B:B, _xlpm.party, ledger!E:E, "<>*RD*", ledger!D:D, "Super Kataan", ledger!C:C, "<>Closing CF") ))+ _xlfn.IFNA(N139, 0)} -> 0 | AF18: {=_xlfn.BYROW(B70, _xlfn.LAMBDA(_xlpm.party, SUMIFS(ledger!J:J, ledger!B:B, _xlpm.party, ledger!E:E, "<>*RD*", ledger!D:D, "Custom", ledger!C:C, "<>Closing CF") ))+ _xlfn.IFNA(O139, 0)} -> 0 | AG18: =X18+Y18+Z18+AA18+AB18+AC18+AD18+AF18+AE18 -> 483851.5 | AH18: =(SUMIF(Table14[Party],S18,Table14[Credit]))+_xlfn.IFNA(Q139,0) -> 480000 | AI18: =AG18-AH18 -> 3851.4996 | AJ18: 10 | AK18: 13
I19: Shafique Ansari | S19: Hazrat Khan | T19: {=_xlfn.BYROW(B71,_xlfn.LAMBDA(_xlpm.party,SUMIFS(ledger!G:G,ledger!B:B,_xlpm.party,ledger!E:E,"<>*RD*")))+_xlfn.IFNA(C140,0)} -> 9750 | U19: {=_xlfn.BYROW(B71, _xlfn.LAMBDA(_xlpm.party, SUMIFS(ledger!G:G, ledger!B:B, _xlpm.party, ledger!E:E, "<>*RD*") / 1.0936 ))+_xlfn.IFNA(D140,0)} -> 8915.5084 | V19: {=(_xlfn.BYROW(B71,_xlfn.LAMBDA(_xlpm.party,SUMIFS(ledger!G:G,ledger!B:B,_xlpm.party,ledger!E:E,"<>*RD*",ledger!D:D,"Chamki")+SUMIFS(ledger!G:G, ledger!B:B, _xlpm.party, ledger!E:E, "<>*RD*", ledger!D:D, "Crinkle")))/1.0936)+_xlfn.IFNA(E140,0)} -> 8915.5084 | W19: {=(_xlfn.BYROW(B71,_xlfn.LAMBDA(_xlpm.party,SUMIFS(ledger!G:G,ledger!B:B,_xlpm.party,ledger!E:E,"<>*RD*",ledger!D:D,"Silky")))/1.0936)+_xlfn.IFNA(F140,0)} -> 0 | X19: {=(_xlfn.BYROW(B71,_xlfn.LAMBDA(_xlpm.party, (SUMIFS(ledger!J:J,ledger!B:B,_xlpm.party,ledger!E:E,"<>*RD*",ledger!D:D,"Chamki",ledger!C:C,"<>Closing CF")+ SUMIFS(ledger!J:J,ledger!B:B,_xlpm.party,ledger!E:E,"<>*RD*",ledger!D:D,"Crinkle",ledger!C:C,"<>Closing CF") )+_xlfn.IFNA(G140,0))))} -> 89155.084 | Y19: {=_xlfn.BYROW(B71, _xlfn.LAMBDA(_xlpm.party, SUMIFS(ledger!J:J, ledger!B:B, _xlpm.party, ledger!E:E, "<>*RD*", ledger!D:D, "Silky", ledger!C:C, "<>Closing CF") )) + _xlfn.IFNA(H140, 0)} -> 0 | Z19: {=_xlfn.BYROW(B71, _xlfn.LAMBDA(_xlpm.party, SUMIFS(ledger!J:J, ledger!B:B, _xlpm.party, ledger!E:E, "<>*RD*", ledger!D:D, "Slub", ledger!C:C, "<>Closing CF") ))+ _xlfn.IFNA(I140, 0)} -> 0 | AA19: {=_xlfn.BYROW(B71, _xlfn.LAMBDA(_xlpm.party, SUMIFS(ledger!J:J, ledger!B:B, _xlpm.party, ledger!E:E, "<>*RD*", ledger!D:D, "Satin", ledger!C:C, "<>Closing CF") ))+ _xlfn.IFNA(J140, 0)} -> 0 | AB19: {=_xlfn.BYROW(B71, _xlfn.LAMBDA(_xlpm.party, SUMIFS(ledger!J:J, ledger!B:B, _xlpm.party, ledger!E:E, "<>*RD*", ledger!D:D, "Black-Chamki", ledger!C:C, "<>Closing CF") ))+ _xlfn.IFNA(K140, 0)} -> 0 | AC19: {=_xlfn.BYROW(B71, _xlfn.LAMBDA(_xlpm.party, SUMIFS(ledger!J:J, ledger!B:B, _xlpm.party, ledger!E:E, "<>*RD*", ledger!D:D, "Kataan", ledger!C:C, "<>Closing CF") ))+ _xlfn.IFNA(L140, 0)} -> 0 | AD19: {=_xlfn.BYROW(B71, _xlfn.LAMBDA(_xlpm.party, SUMIFS(ledger!J:J, ledger!B:B, _xlpm.party, ledger!E:E, "<>*RD*", ledger!D:D, "Munaar", ledger!C:C, "<>Closing CF") ))+ _xlfn.IFNA(M140, 0)} -> 0 | AE19: {=_xlfn.BYROW(B71, _xlfn.LAMBDA(_xlpm.party, SUMIFS(ledger!J:J, ledger!B:B, _xlpm.party, ledger!E:E, "<>*RD*", ledger!D:D, "Super Kataan", ledger!C:C, "<>Closing CF") ))+ _xlfn.IFNA(N140, 0)} -> 0 | AF19: {=_xlfn.BYROW(B71, _xlfn.LAMBDA(_xlpm.party, SUMIFS(ledger!J:J, ledger!B:B, _xlpm.party, ledger!E:E, "<>*RD*", ledger!D:D, "Custom", ledger!C:C, "<>Closing CF") ))+ _xlfn.IFNA(O140, 0)} -> 0 | AG19: =X19+Y19+Z19+AA19+AB19+AC19+AD19+AF19+AE19 -> 89155.084 | AH19: =(SUMIF(Table14[Party],S19,Table14[Credit]))+_xlfn.IFNA(Q140,0) -> 95000 | AI19: =AG19-AH19 -> -5844.9159 | AJ19: 10 | AK19: 13
I20: Amjad sohail | S20: Haseeb Shamsi | T20: {=_xlfn.BYROW(B72,_xlfn.LAMBDA(_xlpm.party,SUMIFS(ledger!G:G,ledger!B:B,_xlpm.party,ledger!E:E,"<>*RD*")))+_xlfn.IFNA(C141,0)} -> 61975 | U20: {=_xlfn.BYROW(B72, _xlfn.LAMBDA(_xlpm.party, SUMIFS(ledger!G:G, ledger!B:B, _xlpm.party, ledger!E:E, "<>*RD*") / 1.0936 ))+_xlfn.IFNA(D141,0)} -> 56670.629 | V20: {=(_xlfn.BYROW(B72,_xlfn.LAMBDA(_xlpm.party,SUMIFS(ledger!G:G,ledger!B:B,_xlpm.party,ledger!E:E,"<>*RD*",ledger!D:D,"Chamki")+SUMIFS(ledger!G:G, ledger!B:B, _xlpm.party, ledger!E:E, "<>*RD*", ledger!D:D, "Crinkle")))/1.0936)+_xlfn.IFNA(E141,0)} -> 47437.82 | W20: {=(_xlfn.BYROW(B72,_xlfn.LAMBDA(_xlpm.party,SUMIFS(ledger!G:G,ledger!B:B,_xlpm.party,ledger!E:E,"<>*RD*",ledger!D:D,"Silky")))/1.0936)+_xlfn.IFNA(F141,0)} -> 9232.8091 | X20: {=(_xlfn.BYROW(B72,_xlfn.LAMBDA(_xlpm.party, (SUMIFS(ledger!J:J,ledger!B:B,_xlpm.party,ledger!E:E,"<>*RD*",ledger!D:D,"Chamki",ledger!C:C,"<>Closing CF")+ SUMIFS(ledger!J:J,ledger!B:B,_xlpm.party,ledger!E:E,"<>*RD*",ledger!D:D,"Crinkle",ledger!C:C,"<>Closing CF") )+_xlfn.IFNA(G141,0))))} -> 474378.2 | Y20: {=_xlfn.BYROW(B72, _xlfn.LAMBDA(_xlpm.party, SUMIFS(ledger!J:J, ledger!B:B, _xlpm.party, ledger!E:E, "<>*RD*", ledger!D:D, "Silky", ledger!C:C, "<>Closing CF") )) + _xlfn.IFNA(H141, 0)} -> 120026.52 | Z20: {=_xlfn.BYROW(B72, _xlfn.LAMBDA(_xlpm.party, SUMIFS(ledger!J:J, ledger!B:B, _xlpm.party, ledger!E:E, "<>*RD*", ledger!D:D, "Slub", ledger!C:C, "<>Closing CF") ))+ _xlfn.IFNA(I141, 0)} -> 0 | AA20: {=_xlfn.BYROW(B72, _xlfn.LAMBDA(_xlpm.party, SUMIFS(ledger!J:J, ledger!B:B, _xlpm.party, ledger!E:E, "<>*RD*", ledger!D:D, "Satin", ledger!C:C, "<>Closing CF") ))+ _xlfn.IFNA(J141, 0)} -> 0 | AB20: {=_xlfn.BYROW(B72, _xlfn.LAMBDA(_xlpm.party, SUMIFS(ledger!J:J, ledger!B:B, _xlpm.party, ledger!E:E, "<>*RD*", ledger!D:D, "Black-Chamki", ledger!C:C, "<>Closing CF") ))+ _xlfn.IFNA(K141, 0)} -> 0 | AC20: {=_xlfn.BYROW(B72, _xlfn.LAMBDA(_xlpm.party, SUMIFS(ledger!J:J, ledger!B:B, _xlpm.party, ledger!E:E, "<>*RD*", ledger!D:D, "Kataan", ledger!C:C, "<>Closing CF") ))+ _xlfn.IFNA(L141, 0)} -> 0 | AD20: {=_xlfn.BYROW(B72, _xlfn.LAMBDA(_xlpm.party, SUMIFS(ledger!J:J, ledger!B:B, _xlpm.party, ledger!E:E, "<>*RD*", ledger!D:D, "Munaar", ledger!C:C, "<>Closing CF") ))+ _xlfn.IFNA(M141, 0)} -> 0 | AE20: {=_xlfn.BYROW(B72, _xlfn.LAMBDA(_xlpm.party, SUMIFS(ledger!J:J, ledger!B:B, _xlpm.party, ledger!E:E, "<>*RD*", ledger!D:D, "Super Kataan", ledger!C:C, "<>Closing CF") ))+ _xlfn.IFNA(N141, 0)} -> 0 | AF20: {=_xlfn.BYROW(B72, _xlfn.LAMBDA(_xlpm.party, SUMIFS(ledger!J:J, ledger!B:B, _xlpm.party, ledger!E:E, "<>*RD*", ledger!D:D, "Custom", ledger!C:C, "<>Closing CF") ))+ _xlfn.IFNA(O141, 0)} -> 0 | AG20: =X20+Y20+Z20+AA20+AB20+AC20+AD20+AF20+AE20 -> 594404.72 | AH20: =(SUMIF(Table14[Party],S20,Table14[Credit]))+_xlfn.IFNA(Q141,0) -> 594405 | AI20: =AG20-AH20 -> -0.28163862 | AJ20: 10 | AK20: 13
B21: Total: | C21: =SUM(P57:P103) -> 52727241 | D21: (Real Figure) | I21: Salman Zaffar | S21: Faizan | T21: {=_xlfn.BYROW(B73,_xlfn.LAMBDA(_xlpm.party,SUMIFS(ledger!G:G,ledger!B:B,_xlpm.party,ledger!E:E,"<>*RD*")))+_xlfn.IFNA(C142,0)} -> 565150 | U21: {=_xlfn.BYROW(B73, _xlfn.LAMBDA(_xlpm.party, SUMIFS(ledger!G:G, ledger!B:B, _xlpm.party, ledger!E:E, "<>*RD*") / 1.0936 ))+_xlfn.IFNA(D142,0)} -> 516779.44 | V21: {=(_xlfn.BYROW(B73,_xlfn.LAMBDA(_xlpm.party,SUMIFS(ledger!G:G,ledger!B:B,_xlpm.party,ledger!E:E,"<>*RD*",ledger!D:D,"Chamki")+SUMIFS(ledger!G:G, ledger!B:B, _xlpm.party, ledger!E:E, "<>*RD*", ledger!D:D, "Crinkle")))/1.0936)+_xlfn.IFNA(E142,0)} -> 0 | W21: {=(_xlfn.BYROW(B73,_xlfn.LAMBDA(_xlpm.party,SUMIFS(ledger!G:G,ledger!B:B,_xlpm.party,ledger!E:E,"<>*RD*",ledger!D:D,"Silky")))/1.0936)+_xlfn.IFNA(F142,0)} -> 513809.44 | X21: {=(_xlfn.BYROW(B73,_xlfn.LAMBDA(_xlpm.party, (SUMIFS(ledger!J:J,ledger!B:B,_xlpm.party,ledger!E:E,"<>*RD*",ledger!D:D,"Chamki",ledger!C:C,"<>Closing CF")+ SUMIFS(ledger!J:J,ledger!B:B,_xlpm.party,ledger!E:E,"<>*RD*",ledger!D:D,"Crinkle",ledger!C:C,"<>Closing CF") )+_xlfn.IFNA(G142,0))))} -> 30000 | Y21: {=_xlfn.BYROW(B73, _xlfn.LAMBDA(_xlpm.party, SUMIFS(ledger!J:J, ledger!B:B, _xlpm.party, ledger!E:E, "<>*RD*", ledger!D:D, "Silky", ledger!C:C, "<>Closing CF") )) + _xlfn.IFNA(H142, 0)} -> 6679522.7 | Z21: {=_xlfn.BYROW(B73, _xlfn.LAMBDA(_xlpm.party, SUMIFS(ledger!J:J, ledger!B:B, _xlpm.party, ledger!E:E, "<>*RD*", ledger!D:D, "Slub", ledger!C:C, "<>Closing CF") ))+ _xlfn.IFNA(I142, 0)} -> 44550.11 | AA21: {=_xlfn.BYROW(B73, _xlfn.LAMBDA(_xlpm.party, SUMIFS(ledger!J:J, ledger!B:B, _xlpm.party, ledger!E:E, "<>*RD*", ledger!D:D, "Satin", ledger!C:C, "<>Closing CF") ))+ _xlfn.IFNA(J142, 0)} -> 0 | AB21: {=_xlfn.BYROW(B73, _xlfn.LAMBDA(_xlpm.party, SUMIFS(ledger!J:J, ledger!B:B, _xlpm.party, ledger!E:E, "<>*RD*", ledger!D:D, "Black-Chamki", ledger!C:C, "<>Closing CF") ))+ _xlfn.IFNA(K142, 0)} -> 0 | AC21: {=_xlfn.BYROW(B73, _xlfn.LAMBDA(_xlpm.party, SUMIFS(ledger!J:J, ledger!B:B, _xlpm.party, ledger!E:E, "<>*RD*", ledger!D:D, "Kataan", ledger!C:C, "<>Closing CF") ))+ _xlfn.IFNA(L142, 0)} -> 0 | AD21: {=_xlfn.BYROW(B73, _xlfn.LAMBDA(_xlpm.party, SUMIFS(ledger!J:J, ledger!B:B, _xlpm.party, ledger!E:E, "<>*RD*", ledger!D:D, "Munaar", ledger!C:C, "<>Closing CF") ))+ _xlfn.IFNA(M142, 0)} -> 0 | AE21: {=_xlfn.BYROW(B73, _xlfn.LAMBDA(_xlpm.party, SUMIFS(ledger!J:J, ledger!B:B, _xlpm.party, ledger!E:E, "<>*RD*", ledger!D:D, "Super Kataan", ledger!C:C, "<>Closing CF") ))+ _xlfn.IFNA(N142, 0)} -> 0 | AF21: {=_xlfn.BYROW(B73, _xlfn.LAMBDA(_xlpm.party, SUMIFS(ledger!J:J, ledger!B:B, _xlpm.party, ledger!E:E, "<>*RD*", ledger!D:D, "Custom", ledger!C:C, "<>Closing CF") ))+ _xlfn.IFNA(O142, 0)} -> 0 | AG21: =X21+Y21+Z21+AA21+AB21+AC21+AD21+AF21+AE21 -> 6754072.8 | AH21: =(SUMIF(Table14[Party],S21,Table14[Credit]))+_xlfn.IFNA(Q142,0) -> 6728187 | AI21: =AG21-AH21 -> 25885.787 | AJ21: 10 | AK21: 13
I22: Shahid Qasayi | S22: Shafique Ansari | T22: {=_xlfn.BYROW(B74,_xlfn.LAMBDA(_xlpm.party,SUMIFS(ledger!G:G,ledger!B:B,_xlpm.party,ledger!E:E,"<>*RD*")))+_xlfn.IFNA(C143,0)} -> 517899 | U22: {=_xlfn.BYROW(B74, _xlfn.LAMBDA(_xlpm.party, SUMIFS(ledger!G:G, ledger!B:B, _xlpm.party, ledger!E:E, "<>*RD*") / 1.0936 ))+_xlfn.IFNA(D143,0)} -> 473572.6 | V22: {=(_xlfn.BYROW(B74,_xlfn.LAMBDA(_xlpm.party,SUMIFS(ledger!G:G,ledger!B:B,_xlpm.party,ledger!E:E,"<>*RD*",ledger!D:D,"Chamki")+SUMIFS(ledger!G:G, ledger!B:B, _xlpm.party, ledger!E:E, "<>*RD*", ledger!D:D, "Crinkle")))/1.0936)+_xlfn.IFNA(E143,0)} -> 90599.854 | W22: {=(_xlfn.BYROW(B74,_xlfn.LAMBDA(_xlpm.party,SUMIFS(ledger!G:G,ledger!B:B,_xlpm.party,ledger!E:E,"<>*RD*",ledger!D:D,"Silky")))/1.0936)+_xlfn.IFNA(F143,0)} -> 78055.962 | X22: {=(_xlfn.BYROW(B74,_xlfn.LAMBDA(_xlpm.party, (SUMIFS(ledger!J:J,ledger!B:B,_xlpm.party,ledger!E:E,"<>*RD*",ledger!D:D,"Chamki",ledger!C:C,"<>Closing CF")+ SUMIFS(ledger!J:J,ledger!B:B,_xlpm.party,ledger!E:E,"<>*RD*",ledger!D:D,"Crinkle",ledger!C:C,"<>Closing CF") )+_xlfn.IFNA(G143,0))))} -> 932297.92 | Y22: {=_xlfn.BYROW(B74, _xlfn.LAMBDA(_xlpm.party, SUMIFS(ledger!J:J, ledger!B:B, _xlpm.party, ledger!E:E, "<>*RD*", ledger!D:D, "Silky", ledger!C:C, "<>Closing CF") )) + _xlfn.IFNA(H143, 0)} -> 980700.44 | Z22: {=_xlfn.BYROW(B74, _xlfn.LAMBDA(_xlpm.party, SUMIFS(ledger!J:J, ledger!B:B, _xlpm.party, ledger!E:E, "<>*RD*", ledger!D:D, "Slub", ledger!C:C, "<>Closing CF") ))+ _xlfn.IFNA(I143, 0)} -> 0 | AA22: {=_xlfn.BYROW(B74, _xlfn.LAMBDA(_xlpm.party, SUMIFS(ledger!J:J, ledger!B:B, _xlpm.party, ledger!E:E, "<>*RD*", ledger!D:D, "Satin", ledger!C:C, "<>Closing CF") ))+ _xlfn.IFNA(J143, 0)} -> 470003.66 | AB22: {=_xlfn.BYROW(B74, _xlfn.LAMBDA(_xlpm.party, SUMIFS(ledger!J:J, ledger!B:B, _xlpm.party, ledger!E:E, "<>*RD*", ledger!D:D, "Black-Chamki", ledger!C:C, "<>Closing CF") ))+ _xlfn.IFNA(K143, 0)} -> 0 | AC22: {=_xlfn.BYROW(B74, _xlfn.LAMBDA(_xlpm.party, SUMIFS(ledger!J:J, ledger!B:B, _xlpm.party, ledger!E:E, "<>*RD*", ledger!D:D, "Kataan", ledger!C:C, "<>Closing CF") ))+ _xlfn.IFNA(L143, 0)} -> 2653520.5 | AD22: {=_xlfn.BYROW(B74, _xlfn.LAMBDA(_xlpm.party, SUMIFS(ledger!J:J, ledger!B:B, _xlpm.party, ledger!E:E, "<>*RD*", ledger!D:D, "Munaar", ledger!C:C, "<>Closing CF") ))+ _xlfn.IFNA(M143, 0)} -> 0 | AE22: {=_xlfn.BYROW(B74, _xlfn.LAMBDA(_xlpm.party, SUMIFS(ledger!J:J, ledger!B:B, _xlpm.party, ledger!E:E, "<>*RD*", ledger!D:D, "Super Kataan", ledger!C:C, "<>Closing CF") ))+ _xlfn.IFNA(N143, 0)} -> 0 | AF22: {=_xlfn.BYROW(B74, _xlfn.LAMBDA(_xlpm.party, SUMIFS(ledger!J:J, ledger!B:B, _xlpm.party, ledger!E:E, "<>*RD*", ledger!D:D, "Custom", ledger!C:C, "<>Closing CF") ))+ _xlfn.IFNA(O143, 0)} -> 701356.99 | AG22: =X22+Y22+Z22+AA22+AB22+AC22+AD22+AF22+AE22 -> 5737879.5 | AH22: =(SUMIF(Table14[Party],S22,Table14[Credit]))+_xlfn.IFNA(Q143,0) -> 4935017 | AI22: =AG22-AH22 -> 802862.48 | AJ22: 10 | AK22: 13
B23: Total influx | C23: =SUM(P57:P103) -> 52727241 | D23: (considering 10.5) | I23: Hameed corporation | S23: Amjad sohail | T23: {=_xlfn.BYROW(B75,_xlfn.LAMBDA(_xlpm.party,SUMIFS(ledger!G:G,ledger!B:B,_xlpm.party,ledger!E:E,"<>*RD*")))+_xlfn.IFNA(C144,0)} -> 544943 | U23: {=_xlfn.BYROW(B75, _xlfn.LAMBDA(_xlpm.party, SUMIFS(ledger!G:G, ledger!B:B, _xlpm.party, ledger!E:E, "<>*RD*") / 1.0936 ))+_xlfn.IFNA(D144,0)} -> 498301.94 | V23: {=(_xlfn.BYROW(B75,_xlfn.LAMBDA(_xlpm.party,SUMIFS(ledger!G:G,ledger!B:B,_xlpm.party,ledger!E:E,"<>*RD*",ledger!D:D,"Chamki")+SUMIFS(ledger!G:G, ledger!B:B, _xlpm.party, ledger!E:E, "<>*RD*", ledger!D:D, "Crinkle")))/1.0936)+_xlfn.IFNA(E144,0)} -> 362820.04 | W23: {=(_xlfn.BYROW(B75,_xlfn.LAMBDA(_xlpm.party,SUMIFS(ledger!G:G,ledger!B:B,_xlpm.party,ledger!E:E,"<>*RD*",ledger!D:D,"Silky")))/1.0936)+_xlfn.IFNA(F144,0)} -> 97421.361 | X23: {=(_xlfn.BYROW(B75,_xlfn.LAMBDA(_xlpm.party, (SUMIFS(ledger!J:J,ledger!B:B,_xlpm.party,ledger!E:E,"<>*RD*",ledger!D:D,"Chamki",ledger!C:C,"<>Closing CF")+ SUMIFS(ledger!J:J,ledger!B:B,_xlpm.party,ledger!E:E,"<>*RD*",ledger!D:D,"Crinkle",ledger!C:C,"<>Closing CF") )+_xlfn.IFNA(G144,0))))} -> 3628200.4 | Y23: {=_xlfn.BYROW(B75, _xlfn.LAMBDA(_xlpm.party, SUMIFS(ledger!J:J, ledger!B:B, _xlpm.party, ledger!E:E, "<>*RD*", ledger!D:D, "Silky", ledger!C:C, "<>Closing CF") )) + _xlfn.IFNA(H144, 0)} -> 1264498 | Z23: {=_xlfn.BYROW(B75, _xlfn.LAMBDA(_xlpm.party, SUMIFS(ledger!J:J, ledger!B:B, _xlpm.party, ledger!E:E, "<>*RD*", ledger!D:D, "Slub", ledger!C:C, "<>Closing CF") ))+ _xlfn.IFNA(I144, 0)} -> 0 | AA23: {=_xlfn.BYROW(B75, _xlfn.LAMBDA(_xlpm.party, SUMIFS(ledger!J:J, ledger!B:B, _xlpm.party, ledger!E:E, "<>*RD*", ledger!D:D, "Satin", ledger!C:C, "<>Closing CF") ))+ _xlfn.IFNA(J144, 0)} -> 0 | AB23: {=_xlfn.BYROW(B75, _xlfn.LAMBDA(_xlpm.party, SUMIFS(ledger!J:J, ledger!B:B, _xlpm.party, ledger!E:E, "<>*RD*", ledger!D:D, "Black-Chamki", ledger!C:C, "<>Closing CF") ))+ _xlfn.IFNA(K144, 0)} -> 0 | AC23: {=_xlfn.BYROW(B75, _xlfn.LAMBDA(_xlpm.party, SUMIFS(ledger!J:J, ledger!B:B, _xlpm.party, ledger!E:E, "<>*RD*", ledger!D:D, "Kataan", ledger!C:C, "<>Closing CF") ))+ _xlfn.IFNA(L144, 0)} -> 0 | AD23: {=_xlfn.BYROW(B75, _xlfn.LAMBDA(_xlpm.party, SUMIFS(ledger!J:J, ledger!B:B, _xlpm.party, ledger!E:E, "<>*RD*", ledger!D:D, "Munaar", ledger!C:C, "<>Closing CF") ))+ _xlfn.IFNA(M144, 0)} -> 0 | AE23: {=_xlfn.BYROW(B75, _xlfn.LAMBDA(_xlpm.party, SUMIFS(ledger!J:J, ledger!B:B, _xlpm.party, ledger!E:E, "<>*RD*", ledger!D:D, "Super Kataan", ledger!C:C, "<>Closing CF") ))+ _xlfn.IFNA(N144, 0)} -> 570908.01 | AF23: {=_xlfn.BYROW(B75, _xlfn.LAMBDA(_xlpm.party, SUMIFS(ledger!J:J, ledger!B:B, _xlpm.party, ledger!E:E, "<>*RD*", ledger!D:D, "Custom", ledger!C:C, "<>Closing CF") ))+ _xlfn.IFNA(O144, 0)} -> 0 | AG23: =X23+Y23+Z23+AA23+AB23+AC23+AD23+AF23+AE23 -> 5463606.4 | AH23: =(SUMIF(Table14[Party],S23,Table14[Credit]))+_xlfn.IFNA(Q144,0) -> 4967830 | AI23: =AG23-AH23 -> 495776.44 | AJ23: 10 | AK23: 13
I24: ibraheem behraam | S24: Salman Zaffar | T24: {=_xlfn.BYROW(B76,_xlfn.LAMBDA(_xlpm.party,SUMIFS(ledger!G:G,ledger!B:B,_xlpm.party,ledger!E:E,"<>*RD*")))+_xlfn.IFNA(C145,0)} -> 344332 | U24: {=_xlfn.BYROW(B76, _xlfn.LAMBDA(_xlpm.party, SUMIFS(ledger!G:G, ledger!B:B, _xlpm.party, ledger!E:E, "<>*RD*") / 1.0936 ))+_xlfn.IFNA(D145,0)} -> 314861.01 | V24: {=(_xlfn.BYROW(B76,_xlfn.LAMBDA(_xlpm.party,SUMIFS(ledger!G:G,ledger!B:B,_xlpm.party,ledger!E:E,"<>*RD*",ledger!D:D,"Chamki")+SUMIFS(ledger!G:G, ledger!B:B, _xlpm.party, ledger!E:E, "<>*RD*", ledger!D:D, "Crinkle")))/1.0936)+_xlfn.IFNA(E145,0)} -> 72939.832 | W24: {=(_xlfn.BYROW(B76,_xlfn.LAMBDA(_xlpm.party,SUMIFS(ledger!G:G,ledger!B:B,_xlpm.party,ledger!E:E,"<>*RD*",ledger!D:D,"Silky")))/1.0936)+_xlfn.IFNA(F145,0)} -> 31409.108 | X24: {=(_xlfn.BYROW(B76,_xlfn.LAMBDA(_xlpm.party, (SUMIFS(ledger!J:J,ledger!B:B,_xlpm.party,ledger!E:E,"<>*RD*",ledger!D:D,"Chamki",ledger!C:C,"<>Closing CF")+ SUMIFS(ledger!J:J,ledger!B:B,_xlpm.party,ledger!E:E,"<>*RD*",ledger!D:D,"Crinkle",ledger!C:C,"<>Closing CF") )+_xlfn.IFNA(G145,0))))} -> 729398.32 | Y24: {=_xlfn.BYROW(B76, _xlfn.LAMBDA(_xlpm.party, SUMIFS(ledger!J:J, ledger!B:B, _xlpm.party, ledger!E:E, "<>*RD*", ledger!D:D, "Silky", ledger!C:C, "<>Closing CF") )) + _xlfn.IFNA(H145, 0)} -> 408318.4 | Z24: {=_xlfn.BYROW(B76, _xlfn.LAMBDA(_xlpm.party, SUMIFS(ledger!J:J, ledger!B:B, _xlpm.party, ledger!E:E, "<>*RD*", ledger!D:D, "Slub", ledger!C:C, "<>Closing CF") ))+ _xlfn.IFNA(I145, 0)} -> 0 | AA24: {=_xlfn.BYROW(B76, _xlfn.LAMBDA(_xlpm.party, SUMIFS(ledger!J:J, ledger!B:B, _xlpm.party, ledger!E:E, "<>*RD*", ledger!D:D, "Satin", ledger!C:C, "<>Closing CF") ))+ _xlfn.IFNA(J145, 0)} -> 0 | AB24: {=_xlfn.BYROW(B76, _xlfn.LAMBDA(_xlpm.party, SUMIFS(ledger!J:J, ledger!B:B, _xlpm.party, ledger!E:E, "<>*RD*", ledger!D:D, "Black-Chamki", ledger!C:C, "<>Closing CF") ))+ _xlfn.IFNA(K145, 0)} -> 161653.26 | AC24: {=_xlfn.BYROW(B76, _xlfn.LAMBDA(_xlpm.party, SUMIFS(ledger!J:J, ledger!B:B, _xlpm.party, ledger!E:E, "<>*RD*", ledger!D:D, "Kataan", ledger!C:C, "<>Closing CF") ))+ _xlfn.IFNA(L145, 0)} -> 1970409.7 | AD24: {=_xlfn.BYROW(B76, _xlfn.LAMBDA(_xlpm.party, SUMIFS(ledger!J:J, ledger!B:B, _xlpm.party, ledger!E:E, "<>*RD*", ledger!D:D, "Munaar", ledger!C:C, "<>Closing CF") ))+ _xlfn.IFNA(M145, 0)} -> 0 | AE24: {=_xlfn.BYROW(B76, _xlfn.LAMBDA(_xlpm.party, SUMIFS(ledger!J:J, ledger!B:B, _xlpm.party, ledger!E:E, "<>*RD*", ledger!D:D, "Super Kataan", ledger!C:C, "<>Closing CF") ))+ _xlfn.IFNA(N145, 0)} -> 0 | AF24: {=_xlfn.BYROW(B76, _xlfn.LAMBDA(_xlpm.party, SUMIFS(ledger!J:J, ledger!B:B, _xlpm.party, ledger!E:E, "<>*RD*", ledger!D:D, "Custom", ledger!C:C, "<>Closing CF") ))+ _xlfn.IFNA(O145, 0)} -> 0 | AG24: =X24+Y24+Z24+AA24+AB24+AC24+AD24+AF24+AE24 -> 3269779.6 | AH24: =(SUMIF(Table14[Party],S24,Table14[Credit]))+_xlfn.IFNA(Q145,0) -> 3296025 | AI24: =AG24-AH24 -> -26245.373 | AJ24: 10 | AK24: 13
I25: Zia-ullah karachi | S25: Shahid Qasayi | T25: {=_xlfn.BYROW(B77,_xlfn.LAMBDA(_xlpm.party,SUMIFS(ledger!G:G,ledger!B:B,_xlpm.party,ledger!E:E,"<>*RD*")))+_xlfn.IFNA(C146,0)} -> 514433 | U25: {=_xlfn.BYROW(B77, _xlfn.LAMBDA(_xlpm.party, SUMIFS(ledger!G:G, ledger!B:B, _xlpm.party, ledger!E:E, "<>*RD*") / 1.0936 ))+_xlfn.IFNA(D146,0)} -> 470403.26 | V25: {=(_xlfn.BYROW(B77,_xlfn.LAMBDA(_xlpm.party,SUMIFS(ledger!G:G,ledger!B:B,_xlpm.party,ledger!E:E,"<>*RD*",ledger!D:D,"Chamki")+SUMIFS(ledger!G:G, ledger!B:B, _xlpm.party, ledger!E:E, "<>*RD*", ledger!D:D, "Crinkle")))/1.0936)+_xlfn.IFNA(E146,0)} -> 416798.65 | W25: {=(_xlfn.BYROW(B77,_xlfn.LAMBDA(_xlpm.party,SUMIFS(ledger!G:G,ledger!B:B,_xlpm.party,ledger!E:E,"<>*RD*",ledger!D:D,"Silky")))/1.0936)+_xlfn.IFNA(F146,0)} -> 4065.4718 | X25: {=(_xlfn.BYROW(B77,_xlfn.LAMBDA(_xlpm.party, (SUMIFS(ledger!J:J,ledger!B:B,_xlpm.party,ledger!E:E,"<>*RD*",ledger!D:D,"Chamki",ledger!C:C,"<>Closing CF")+ SUMIFS(ledger!J:J,ledger!B:B,_xlpm.party,ledger!E:E,"<>*RD*",ledger!D:D,"Crinkle",ledger!C:C,"<>Closing CF") )+_xlfn.IFNA(G146,0))))} -> 4167986.5 | Y25: {=_xlfn.BYROW(B77, _xlfn.LAMBDA(_xlpm.party, SUMIFS(ledger!J:J, ledger!B:B, _xlpm.party, ledger!E:E, "<>*RD*", ledger!D:D, "Silky", ledger!C:C, "<>Closing CF") )) + _xlfn.IFNA(H146, 0)} -> 52851.134 | Z25: {=_xlfn.BYROW(B77, _xlfn.LAMBDA(_xlpm.party, SUMIFS(ledger!J:J, ledger!B:B, _xlpm.party, ledger!E:E, "<>*RD*", ledger!D:D, "Slub", ledger!C:C, "<>Closing CF") ))+ _xlfn.IFNA(I146, 0)} -> 0 | AA25: {=_xlfn.BYROW(B77, _xlfn.LAMBDA(_xlpm.party, SUMIFS(ledger!J:J, ledger!B:B, _xlpm.party, ledger!E:E, "<>*RD*", ledger!D:D, "Satin", ledger!C:C, "<>Closing CF") ))+ _xlfn.IFNA(J146, 0)} -> 0 | AB25: {=_xlfn.BYROW(B77, _xlfn.LAMBDA(_xlpm.party, SUMIFS(ledger!J:J, ledger!B:B, _xlpm.party, ledger!E:E, "<>*RD*", ledger!D:D, "Black-Chamki", ledger!C:C, "<>Closing CF") ))+ _xlfn.IFNA(K146, 0)} -> 23767.374 | AC25: {=_xlfn.BYROW(B77, _xlfn.LAMBDA(_xlpm.party, SUMIFS(ledger!J:J, ledger!B:B, _xlpm.party, ledger!E:E, "<>*RD*", ledger!D:D, "Kataan", ledger!C:C, "<>Closing CF") ))+ _xlfn.IFNA(L146, 0)} -> 523143.75 | AD25: {=_xlfn.BYROW(B77, _xlfn.LAMBDA(_xlpm.party, SUMIFS(ledger!J:J, ledger!B:B, _xlpm.party, ledger!E:E, "<>*RD*", ledger!D:D, "Munaar", ledger!C:C, "<>Closing CF") ))+ _xlfn.IFNA(M146, 0)} -> 0 | AE25: {=_xlfn.BYROW(B77, _xlfn.LAMBDA(_xlpm.party, SUMIFS(ledger!J:J, ledger!B:B, _xlpm.party, ledger!E:E, "<>*RD*", ledger!D:D, "Super Kataan", ledger!C:C, "<>Closing CF") ))+ _xlfn.IFNA(N146, 0)} -> 0 | AF25: {=_xlfn.BYROW(B77, _xlfn.LAMBDA(_xlpm.party, SUMIFS(ledger!J:J, ledger!B:B, _xlpm.party, ledger!E:E, "<>*RD*", ledger!D:D, "Custom", ledger!C:C, "<>Closing CF") ))+ _xlfn.IFNA(O146, 0)} -> 0 | AG25: =X25+Y25+Z25+AA25+AB25+AC25+AD25+AF25+AE25 -> 4767748.7 | AH25: =(SUMIF(Table14[Party],S25,Table14[Credit]))+_xlfn.IFNA(Q146,0) -> 4752127 | AI25: =AG25-AH25 -> 15621.72 | AJ25: 10 | AK25: 13
I26: ZA | S26: Hameed corporation | T26: {=_xlfn.BYROW(B78,_xlfn.LAMBDA(_xlpm.party,SUMIFS(ledger!G:G,ledger!B:B,_xlpm.party,ledger!E:E,"<>*RD*")))+_xlfn.IFNA(C147,0)} -> 46404 | U26: {=_xlfn.BYROW(B78, _xlfn.LAMBDA(_xlpm.party, SUMIFS(ledger!G:G, ledger!B:B, _xlpm.party, ledger!E:E, "<>*RD*") / 1.0936 ))+_xlfn.IFNA(D147,0)} -> 42432.334 | V26: {=(_xlfn.BYROW(B78,_xlfn.LAMBDA(_xlpm.party,SUMIFS(ledger!G:G,ledger!B:B,_xlpm.party,ledger!E:E,"<>*RD*",ledger!D:D,"Chamki")+SUMIFS(ledger!G:G, ledger!B:B, _xlpm.party, ledger!E:E, "<>*RD*", ledger!D:D, "Crinkle")))/1.0936)+_xlfn.IFNA(E147,0)} -> 42432.334 | W26: {=(_xlfn.BYROW(B78,_xlfn.LAMBDA(_xlpm.party,SUMIFS(ledger!G:G,ledger!B:B,_xlpm.party,ledger!E:E,"<>*RD*",ledger!D:D,"Silky")))/1.0936)+_xlfn.IFNA(F147,0)} -> 0 | X26: {=(_xlfn.BYROW(B78,_xlfn.LAMBDA(_xlpm.party, (SUMIFS(ledger!J:J,ledger!B:B,_xlpm.party,ledger!E:E,"<>*RD*",ledger!D:D,"Chamki",ledger!C:C,"<>Closing CF")+ SUMIFS(ledger!J:J,ledger!B:B,_xlpm.party,ledger!E:E,"<>*RD*",ledger!D:D,"Crinkle",ledger!C:C,"<>Closing CF") )+_xlfn.IFNA(G147,0))))} -> 424323.34 | Y26: {=_xlfn.BYROW(B78, _xlfn.LAMBDA(_xlpm.party, SUMIFS(ledger!J:J, ledger!B:B, _xlpm.party, ledger!E:E, "<>*RD*", ledger!D:D, "Silky", ledger!C:C, "<>Closing CF") )) + _xlfn.IFNA(H147, 0)} -> 0 | Z26: {=_xlfn.BYROW(B78, _xlfn.LAMBDA(_xlpm.party, SUMIFS(ledger!J:J, ledger!B:B, _xlpm.party, ledger!E:E, "<>*RD*", ledger!D:D, "Slub", ledger!C:C, "<>Closing CF") ))+ _xlfn.IFNA(I147, 0)} -> 0 | AA26: {=_xlfn.BYROW(B78, _xlfn.LAMBDA(_xlpm.party, SUMIFS(ledger!J:J, ledger!B:B, _xlpm.party, ledger!E:E, "<>*RD*", ledger!D:D, "Satin", ledger!C:C, "<>Closing CF") ))+ _xlfn.IFNA(J147, 0)} -> 0 | AB26: {=_xlfn.BYROW(B78, _xlfn.LAMBDA(_xlpm.party, SUMIFS(ledger!J:J, ledger!B:B, _xlpm.party, ledger!E:E, "<>*RD*", ledger!D:D, "Black-Chamki", ledger!C:C, "<>Closing CF") ))+ _xlfn.IFNA(K147, 0)} -> 0 | AC26: {=_xlfn.BYROW(B78, _xlfn.LAMBDA(_xlpm.party, SUMIFS(ledger!J:J, ledger!B:B, _xlpm.party, ledger!E:E, "<>*RD*", ledger!D:D, "Kataan", ledger!C:C, "<>Closing CF") ))+ _xlfn.IFNA(L147, 0)} -> 0 | AD26: {=_xlfn.BYROW(B78, _xlfn.LAMBDA(_xlpm.party, SUMIFS(ledger!J:J, ledger!B:B, _xlpm.party, ledger!E:E, "<>*RD*", ledger!D:D, "Munaar", ledger!C:C, "<>Closing CF") ))+ _xlfn.IFNA(M147, 0)} -> 0 | AE26: {=_xlfn.BYROW(B78, _xlfn.LAMBDA(_xlpm.party, SUMIFS(ledger!J:J, ledger!B:B, _xlpm.party, ledger!E:E, "<>*RD*", ledger!D:D, "Super Kataan", ledger!C:C, "<>Closing CF") ))+ _xlfn.IFNA(N147, 0)} -> 0 | AF26: {=_xlfn.BYROW(B78, _xlfn.LAMBDA(_xlpm.party, SUMIFS(ledger!J:J, ledger!B:B, _xlpm.party, ledger!E:E, "<>*RD*", ledger!D:D, "Custom", ledger!C:C, "<>Closing CF") ))+ _xlfn.IFNA(O147, 0)} -> 0 | AG26: =X26+Y26+Z26+AA26+AB26+AC26+AD26+AF26+AE26 -> 424323.34 | AH26: =(SUMIF(Table14[Party],S26,Table14[Credit]))+_xlfn.IFNA(Q147,0) -> 424323 | AI26: =AG26-AH26 -> 0.33577176 | AJ26: 10 | AK26: 13
I27: Ahmad Javaid | S27: ibraheem behraam | T27: {=_xlfn.BYROW(B79,_xlfn.LAMBDA(_xlpm.party,SUMIFS(ledger!G:G,ledger!B:B,_xlpm.party,ledger!E:E,"<>*RD*")))+_xlfn.IFNA(C148,0)} -> 160320 | U27: {=_xlfn.BYROW(B79, _xlfn.LAMBDA(_xlpm.party, SUMIFS(ledger!G:G, ledger!B:B, _xlpm.party, ledger!E:E, "<>*RD*") / 1.0936 ))+_xlfn.IFNA(D148,0)} -> 146598.39 | V27: {=(_xlfn.BYROW(B79,_xlfn.LAMBDA(_xlpm.party,SUMIFS(ledger!G:G,ledger!B:B,_xlpm.party,ledger!E:E,"<>*RD*",ledger!D:D,"Chamki")+SUMIFS(ledger!G:G, ledger!B:B, _xlpm.party, ledger!E:E, "<>*RD*", ledger!D:D, "Crinkle")))/1.0936)+_xlfn.IFNA(E148,0)} -> 0 | W27: {=(_xlfn.BYROW(B79,_xlfn.LAMBDA(_xlpm.party,SUMIFS(ledger!G:G,ledger!B:B,_xlpm.party,ledger!E:E,"<>*RD*",ledger!D:D,"Silky")))/1.0936)+_xlfn.IFNA(F148,0)} -> 146598.39 | X27: {=(_xlfn.BYROW(B79,_xlfn.LAMBDA(_xlpm.party, (SUMIFS(ledger!J:J,ledger!B:B,_xlpm.party,ledger!E:E,"<>*RD*",ledger!D:D,"Chamki",ledger!C:C,"<>Closing CF")+ SUMIFS(ledger!J:J,ledger!B:B,_xlpm.party,ledger!E:E,"<>*RD*",ledger!D:D,"Crinkle",ledger!C:C,"<>Closing CF") )+_xlfn.IFNA(G148,0))))} -> 0 | Y27: {=_xlfn.BYROW(B79, _xlfn.LAMBDA(_xlpm.party, SUMIFS(ledger!J:J, ledger!B:B, _xlpm.party, ledger!E:E, "<>*RD*", ledger!D:D, "Silky", ledger!C:C, "<>Closing CF") )) + _xlfn.IFNA(H148, 0)} -> 1905779.1 | Z27: {=_xlfn.BYROW(B79, _xlfn.LAMBDA(_xlpm.party, SUMIFS(ledger!J:J, ledger!B:B, _xlpm.party, ledger!E:E, "<>*RD*", ledger!D:D, "Slub", ledger!C:C, "<>Closing CF") ))+ _xlfn.IFNA(I148, 0)} -> 0 | AA27: {=_xlfn.BYROW(B79, _xlfn.LAMBDA(_xlpm.party, SUMIFS(ledger!J:J, ledger!B:B, _xlpm.party, ledger!E:E, "<>*RD*", ledger!D:D, "Satin", ledger!C:C, "<>Closing CF") ))+ _xlfn.IFNA(J148, 0)} -> 0 | AB27: {=_xlfn.BYROW(B79, _xlfn.LAMBDA(_xlpm.party, SUMIFS(ledger!J:J, ledger!B:B, _xlpm.party, ledger!E:E, "<>*RD*", ledger!D:D, "Black-Chamki", ledger!C:C, "<>Closing CF") ))+ _xlfn.IFNA(K148, 0)} -> 0 | AC27: {=_xlfn.BYROW(B79, _xlfn.LAMBDA(_xlpm.party, SUMIFS(ledger!J:J, ledger!B:B, _xlpm.party, ledger!E:E, "<>*RD*", ledger!D:D, "Kataan", ledger!C:C, "<>Closing CF") ))+ _xlfn.IFNA(L148, 0)} -> 0 | AD27: {=_xlfn.BYROW(B79, _xlfn.LAMBDA(_xlpm.party, SUMIFS(ledger!J:J, ledger!B:B, _xlpm.party, ledger!E:E, "<>*RD*", ledger!D:D, "Munaar", ledger!C:C, "<>Closing CF") ))+ _xlfn.IFNA(M148, 0)} -> 0 | AE27: {=_xlfn.BYROW(B79, _xlfn.LAMBDA(_xlpm.party, SUMIFS(ledger!J:J, ledger!B:B, _xlpm.party, ledger!E:E, "<>*RD*", ledger!D:D, "Super Kataan", ledger!C:C, "<>Closing CF") ))+ _xlfn.IFNA(N148, 0)} -> 0 | AF27: {=_xlfn.BYROW(B79, _xlfn.LAMBDA(_xlpm.party, SUMIFS(ledger!J:J, ledger!B:B, _xlpm.party, ledger!E:E, "<>*RD*", ledger!D:D, "Custom", ledger!C:C, "<>Closing CF") ))+ _xlfn.IFNA(O148, 0)} -> 0 | AG27: =X27+Y27+Z27+AA27+AB27+AC27+AD27+AF27+AE27 -> 1905779.1 | AH27: =(SUMIF(Table14[Party],S27,Table14[Credit]))+_xlfn.IFNA(Q148,0) -> 1902400 | AI27: =AG27-AH27 -> 3379.0783 | AJ27: 10 | AK27: 13
S28: Zia-ullah karachi | T28: {=_xlfn.BYROW(B80,_xlfn.LAMBDA(_xlpm.party,SUMIFS(ledger!G:G,ledger!B:B,_xlpm.party,ledger!E:E,"<>*RD*")))+_xlfn.IFNA(C149,0)} -> 13622 | U28: {=_xlfn.BYROW(B80, _xlfn.LAMBDA(_xlpm.party, SUMIFS(ledger!G:G, ledger!B:B, _xlpm.party, ledger!E:E, "<>*RD*") / 1.0936 ))+_xlfn.IFNA(D149,0)} -> 12456.108 | V28: {=(_xlfn.BYROW(B80,_xlfn.LAMBDA(_xlpm.party,SUMIFS(ledger!G:G,ledger!B:B,_xlpm.party,ledger!E:E,"<>*RD*",ledger!D:D,"Chamki")+SUMIFS(ledger!G:G, ledger!B:B, _xlpm.party, ledger!E:E, "<>*RD*", ledger!D:D, "Crinkle")))/1.0936)+_xlfn.IFNA(E149,0)} -> 12456.108 | W28: {=(_xlfn.BYROW(B80,_xlfn.LAMBDA(_xlpm.party,SUMIFS(ledger!G:G,ledger!B:B,_xlpm.party,ledger!E:E,"<>*RD*",ledger!D:D,"Silky")))/1.0936)+_xlfn.IFNA(F149,0)} -> 0 | X28: {=(_xlfn.BYROW(B80,_xlfn.LAMBDA(_xlpm.party, (SUMIFS(ledger!J:J,ledger!B:B,_xlpm.party,ledger!E:E,"<>*RD*",ledger!D:D,"Chamki",ledger!C:C,"<>Closing CF")+ SUMIFS(ledger!J:J,ledger!B:B,_xlpm.party,ledger!E:E,"<>*RD*",ledger!D:D,"Crinkle",ledger!C:C,"<>Closing CF") )+_xlfn.IFNA(G149,0))))} -> 124561.08 | Y28: {=_xlfn.BYROW(B80, _xlfn.LAMBDA(_xlpm.party, SUMIFS(ledger!J:J, ledger!B:B, _xlpm.party, ledger!E:E, "<>*RD*", ledger!D:D, "Silky", ledger!C:C, "<>Closing CF") )) + _xlfn.IFNA(H149, 0)} -> 0 | Z28: {=_xlfn.BYROW(B80, _xlfn.LAMBDA(_xlpm.party, SUMIFS(ledger!J:J, ledger!B:B, _xlpm.party, ledger!E:E, "<>*RD*", ledger!D:D, "Slub", ledger!C:C, "<>Closing CF") ))+ _xlfn.IFNA(I149, 0)} -> 0 | AA28: {=_xlfn.BYROW(B80, _xlfn.LAMBDA(_xlpm.party, SUMIFS(ledger!J:J, ledger!B:B, _xlpm.party, ledger!E:E, "<>*RD*", ledger!D:D, "Satin", ledger!C:C, "<>Closing CF") ))+ _xlfn.IFNA(J149, 0)} -> 0 | AB28: {=_xlfn.BYROW(B80, _xlfn.LAMBDA(_xlpm.party, SUMIFS(ledger!J:J, ledger!B:B, _xlpm.party, ledger!E:E, "<>*RD*", ledger!D:D, "Black-Chamki", ledger!C:C, "<>Closing CF") ))+ _xlfn.IFNA(K149, 0)} -> 0 | AC28: {=_xlfn.BYROW(B80, _xlfn.LAMBDA(_xlpm.party, SUMIFS(ledger!J:J, ledger!B:B, _xlpm.party, ledger!E:E, "<>*RD*", ledger!D:D, "Kataan", ledger!C:C, "<>Closing CF") ))+ _xlfn.IFNA(L149, 0)} -> 0 | AD28: {=_xlfn.BYROW(B80, _xlfn.LAMBDA(_xlpm.party, SUMIFS(ledger!J:J, ledger!B:B, _xlpm.party, ledger!E:E, "<>*RD*", ledger!D:D, "Munaar", ledger!C:C, "<>Closing CF") ))+ _xlfn.IFNA(M149, 0)} -> 0 | AE28: {=_xlfn.BYROW(B80, _xlfn.LAMBDA(_xlpm.party, SUMIFS(ledger!J:J, ledger!B:B, _xlpm.party, ledger!E:E, "<>*RD*", ledger!D:D, "Super Kataan", ledger!C:C, "<>Closing CF") ))+ _xlfn.IFNA(N149, 0)} -> 0 | AF28: {=_xlfn.BYROW(B80, _xlfn.LAMBDA(_xlpm.party, SUMIFS(ledger!J:J, ledger!B:B, _xlpm.party, ledger!E:E, "<>*RD*", ledger!D:D, "Custom", ledger!C:C, "<>Closing CF") ))+ _xlfn.IFNA(O149, 0)} -> 0 | AG28: =X28+Y28+Z28+AA28+AB28+AC28+AD28+AF28+AE28 -> 124561.08 | AH28: =(SUMIF(Table14[Party],S28,Table14[Credit]))+_xlfn.IFNA(Q149,0) -> 124560 | AI28: =AG28-AH28 -> 1.0826628 | AJ28: 10 | AK28: 13
S29: ZA | T29: {=_xlfn.BYROW(B81,_xlfn.LAMBDA(_xlpm.party,SUMIFS(ledger!G:G,ledger!B:B,_xlpm.party,ledger!E:E,"<>*RD*")))+_xlfn.IFNA(C150,0)} -> 32399 | U29: {=_xlfn.BYROW(B81, _xlfn.LAMBDA(_xlpm.party, SUMIFS(ledger!G:G, ledger!B:B, _xlpm.party, ledger!E:E, "<>*RD*") / 1.0936 ))+_xlfn.IFNA(D150,0)} -> 29626.006 | V29: {=(_xlfn.BYROW(B81,_xlfn.LAMBDA(_xlpm.party,SUMIFS(ledger!G:G,ledger!B:B,_xlpm.party,ledger!E:E,"<>*RD*",ledger!D:D,"Chamki")+SUMIFS(ledger!G:G, ledger!B:B, _xlpm.party, ledger!E:E, "<>*RD*", ledger!D:D, "Crinkle")))/1.0936)+_xlfn.IFNA(E150,0)} -> 0 | W29: {=(_xlfn.BYROW(B81,_xlfn.LAMBDA(_xlpm.party,SUMIFS(ledger!G:G,ledger!B:B,_xlpm.party,ledger!E:E,"<>*RD*",ledger!D:D,"Silky")))/1.0936)+_xlfn.IFNA(F150,0)} -> 29626.006 | X29: {=(_xlfn.BYROW(B81,_xlfn.LAMBDA(_xlpm.party, (SUMIFS(ledger!J:J,ledger!B:B,_xlpm.party,ledger!E:E,"<>*RD*",ledger!D:D,"Chamki",ledger!C:C,"<>Closing CF")+ SUMIFS(ledger!J:J,ledger!B:B,_xlpm.party,ledger!E:E,"<>*RD*",ledger!D:D,"Crinkle",ledger!C:C,"<>Closing CF") )+_xlfn.IFNA(G150,0))))} -> 0 | Y29: {=_xlfn.BYROW(B81, _xlfn.LAMBDA(_xlpm.party, SUMIFS(ledger!J:J, ledger!B:B, _xlpm.party, ledger!E:E, "<>*RD*", ledger!D:D, "Silky", ledger!C:C, "<>Closing CF") )) + _xlfn.IFNA(H150, 0)} -> 385138.08 | Z29: {=_xlfn.BYROW(B81, _xlfn.LAMBDA(_xlpm.party, SUMIFS(ledger!J:J, ledger!B:B, _xlpm.party, ledger!E:E, "<>*RD*", ledger!D:D, "Slub", ledger!C:C, "<>Closing CF") ))+ _xlfn.IFNA(I150, 0)} -> 0 | AA29: {=_xlfn.BYROW(B81, _xlfn.LAMBDA(_xlpm.party, SUMIFS(ledger!J:J, ledger!B:B, _xlpm.party, ledger!E:E, "<>*RD*", ledger!D:D, "Satin", ledger!C:C, "<>Closing CF") ))+ _xlfn.IFNA(J150, 0)} -> 0 | AB29: {=_xlfn.BYROW(B81, _xlfn.LAMBDA(_xlpm.party, SUMIFS(ledger!J:J, ledger!B:B, _xlpm.party, ledger!E:E, "<>*RD*", ledger!D:D, "Black-Chamki", ledger!C:C, "<>Closing CF") ))+ _xlfn.IFNA(K150, 0)} -> 0 | AC29: {=_xlfn.BYROW(B81, _xlfn.LAMBDA(_xlpm.party, SUMIFS(ledger!J:J, ledger!B:B, _xlpm.party, ledger!E:E, "<>*RD*", ledger!D:D, "Kataan", ledger!C:C, "<>Closing CF") ))+ _xlfn.IFNA(L150, 0)} -> 0 | AD29: {=_xlfn.BYROW(B81, _xlfn.LAMBDA(_xlpm.party, SUMIFS(ledger!J:J, ledger!B:B, _xlpm.party, ledger!E:E, "<>*RD*", ledger!D:D, "Munaar", ledger!C:C, "<>Closing CF") ))+ _xlfn.IFNA(M150, 0)} -> 0 | AE29: {=_xlfn.BYROW(B81, _xlfn.LAMBDA(_xlpm.party, SUMIFS(ledger!J:J, ledger!B:B, _xlpm.party, ledger!E:E, "<>*RD*", ledger!D:D, "Super Kataan", ledger!C:C, "<>Closing CF") ))+ _xlfn.IFNA(N150, 0)} -> 0 | AF29: {=_xlfn.BYROW(B81, _xlfn.LAMBDA(_xlpm.party, SUMIFS(ledger!J:J, ledger!B:B, _xlpm.party, ledger!E:E, "<>*RD*", ledger!D:D, "Custom", ledger!C:C, "<>Closing CF") ))+ _xlfn.IFNA(O150, 0)} -> 0 | AG29: =X29+Y29+Z29+AA29+AB29+AC29+AD29+AF29+AE29 -> 385138.08 | AH29: =(SUMIF(Table14[Party],S29,Table14[Credit]))+_xlfn.IFNA(Q150,0) -> 385000 | AI29: =AG29-AH29 -> 138.07608 | AJ29: 10 | AK29: 13
S30: Ahmad Javaid | T30: {=_xlfn.BYROW(B82,_xlfn.LAMBDA(_xlpm.party,SUMIFS(ledger!G:G,ledger!B:B,_xlpm.party,ledger!E:E,"<>*RD*")))+_xlfn.IFNA(C151,0)} -> 12745 | U30: {=_xlfn.BYROW(B82, _xlfn.LAMBDA(_xlpm.party, SUMIFS(ledger!G:G, ledger!B:B, _xlpm.party, ledger!E:E, "<>*RD*") / 1.0936 ))+_xlfn.IFNA(D151,0)} -> 11654.17 | V30: {=(_xlfn.BYROW(B82,_xlfn.LAMBDA(_xlpm.party,SUMIFS(ledger!G:G,ledger!B:B,_xlpm.party,ledger!E:E,"<>*RD*",ledger!D:D,"Chamki")+SUMIFS(ledger!G:G, ledger!B:B, _xlpm.party, ledger!E:E, "<>*RD*", ledger!D:D, "Crinkle")))/1.0936)+_xlfn.IFNA(E151,0)} -> 0 | W30: {=(_xlfn.BYROW(B82,_xlfn.LAMBDA(_xlpm.party,SUMIFS(ledger!G:G,ledger!B:B,_xlpm.party,ledger!E:E,"<>*RD*",ledger!D:D,"Silky")))/1.0936)+_xlfn.IFNA(F151,0)} -> 0 | X30: {=(_xlfn.BYROW(B82,_xlfn.LAMBDA(_xlpm.party, (SUMIFS(ledger!J:J,ledger!B:B,_xlpm.party,ledger!E:E,"<>*RD*",ledger!D:D,"Chamki",ledger!C:C,"<>Closing CF")+ SUMIFS(ledger!J:J,ledger!B:B,_xlpm.party,ledger!E:E,"<>*RD*",ledger!D:D,"Crinkle",ledger!C:C,"<>Closing CF") )+_xlfn.IFNA(G151,0))))} -> 0 | Y30: {=_xlfn.BYROW(B82, _xlfn.LAMBDA(_xlpm.party, SUMIFS(ledger!J:J, ledger!B:B, _xlpm.party, ledger!E:E, "<>*RD*", ledger!D:D, "Silky", ledger!C:C, "<>Closing CF") )) + _xlfn.IFNA(H151, 0)} -> 0 | Z30: {=_xlfn.BYROW(B82, _xlfn.LAMBDA(_xlpm.party, SUMIFS(ledger!J:J, ledger!B:B, _xlpm.party, ledger!E:E, "<>*RD*", ledger!D:D, "Slub", ledger!C:C, "<>Closing CF") ))+ _xlfn.IFNA(I151, 0)} -> 0 | AA30: {=_xlfn.BYROW(B82, _xlfn.LAMBDA(_xlpm.party, SUMIFS(ledger!J:J, ledger!B:B, _xlpm.party, ledger!E:E, "<>*RD*", ledger!D:D, "Satin", ledger!C:C, "<>Closing CF") ))+ _xlfn.IFNA(J151, 0)} -> 0 | AB30: {=_xlfn.BYROW(B82, _xlfn.LAMBDA(_xlpm.party, SUMIFS(ledger!J:J, ledger!B:B, _xlpm.party, ledger!E:E, "<>*RD*", ledger!D:D, "Black-Chamki", ledger!C:C, "<>Closing CF") ))+ _xlfn.IFNA(K151, 0)} -> 0 | AC30: {=_xlfn.BYROW(B82, _xlfn.LAMBDA(_xlpm.party, SUMIFS(ledger!J:J, ledger!B:B, _xlpm.party, ledger!E:E, "<>*RD*", ledger!D:D, "Kataan", ledger!C:C, "<>Closing CF") ))+ _xlfn.IFNA(L151, 0)} -> 0 | AD30: {=_xlfn.BYROW(B82, _xlfn.LAMBDA(_xlpm.party, SUMIFS(ledger!J:J, ledger!B:B, _xlpm.party, ledger!E:E, "<>*RD*", ledger!D:D, "Munaar", ledger!C:C, "<>Closing CF") ))+ _xlfn.IFNA(M151, 0)} -> 151504.21 | AE30: {=_xlfn.BYROW(B82, _xlfn.LAMBDA(_xlpm.party, SUMIFS(ledger!J:J, ledger!B:B, _xlpm.party, ledger!E:E, "<>*RD*", ledger!D:D, "Super Kataan", ledger!C:C, "<>Closing CF") ))+ _xlfn.IFNA(N151, 0)} -> 0 | AF30: {=_xlfn.BYROW(B82, _xlfn.LAMBDA(_xlpm.party, SUMIFS(ledger!J:J, ledger!B:B, _xlpm.party, ledger!E:E, "<>*RD*", ledger!D:D, "Custom", ledger!C:C, "<>Closing CF") ))+ _xlfn.IFNA(O151, 0)} -> 0 | AG30: =X30+Y30+Z30+AA30+AB30+AC30+AD30+AF30+AE30 -> 151504.21 | AH30: =(SUMIF(Table14[Party],S30,Table14[Credit]))+_xlfn.IFNA(Q151,0) -> 130000 | AI30: =AG30-AH30 -> 21504.206 | AJ30: 10 | AK30: 13
S31: Shani Badshah | T31: {=_xlfn.BYROW(B83,_xlfn.LAMBDA(_xlpm.party,SUMIFS(ledger!G:G,ledger!B:B,_xlpm.party,ledger!E:E,"<>*RD*")))+_xlfn.IFNA(C152,0)} -> 312320 | U31: {=_xlfn.BYROW(B83, _xlfn.LAMBDA(_xlpm.party, SUMIFS(ledger!G:G, ledger!B:B, _xlpm.party, ledger!E:E, "<>*RD*") / 1.0936 ))+_xlfn.IFNA(D152,0)} -> 285588.88 | V31: {=(_xlfn.BYROW(B83,_xlfn.LAMBDA(_xlpm.party,SUMIFS(ledger!G:G,ledger!B:B,_xlpm.party,ledger!E:E,"<>*RD*",ledger!D:D,"Chamki")+SUMIFS(ledger!G:G, ledger!B:B, _xlpm.party, ledger!E:E, "<>*RD*", ledger!D:D, "Crinkle")))/1.0936)+_xlfn.IFNA(E152,0)} -> 198861.56 | W31: {=(_xlfn.BYROW(B83,_xlfn.LAMBDA(_xlpm.party,SUMIFS(ledger!G:G,ledger!B:B,_xlpm.party,ledger!E:E,"<>*RD*",ledger!D:D,"Silky")))/1.0936)+_xlfn.IFNA(F152,0)} -> 86727.323 | X31: {=(_xlfn.BYROW(B83,_xlfn.LAMBDA(_xlpm.party, (SUMIFS(ledger!J:J,ledger!B:B,_xlpm.party,ledger!E:E,"<>*RD*",ledger!D:D,"Chamki",ledger!C:C,"<>Closing CF")+ SUMIFS(ledger!J:J,ledger!B:B,_xlpm.party,ledger!E:E,"<>*RD*",ledger!D:D,"Crinkle",ledger!C:C,"<>Closing CF") )+_xlfn.IFNA(G152,0))))} -> 1988615.6 | Y31: {=_xlfn.BYROW(B83, _xlfn.LAMBDA(_xlpm.party, SUMIFS(ledger!J:J, ledger!B:B, _xlpm.party, ledger!E:E, "<>*RD*", ledger!D:D, "Silky", ledger!C:C, "<>Closing CF") )) + _xlfn.IFNA(H152, 0)} -> 1127455.2 | Z31: {=_xlfn.BYROW(B83, _xlfn.LAMBDA(_xlpm.party, SUMIFS(ledger!J:J, ledger!B:B, _xlpm.party, ledger!E:E, "<>*RD*", ledger!D:D, "Slub", ledger!C:C, "<>Closing CF") ))+ _xlfn.IFNA(I152, 0)} -> 0 | AA31: {=_xlfn.BYROW(B83, _xlfn.LAMBDA(_xlpm.party, SUMIFS(ledger!J:J, ledger!B:B, _xlpm.party, ledger!E:E, "<>*RD*", ledger!D:D, "Satin", ledger!C:C, "<>Closing CF") ))+ _xlfn.IFNA(J152, 0)} -> 0 | AB31: {=_xlfn.BYROW(B83, _xlfn.LAMBDA(_xlpm.party, SUMIFS(ledger!J:J, ledger!B:B, _xlpm.party, ledger!E:E, "<>*RD*", ledger!D:D, "Black-Chamki", ledger!C:C, "<>Closing CF") ))+ _xlfn.IFNA(K152, 0)} -> 0 | AC31: {=_xlfn.BYROW(B83, _xlfn.LAMBDA(_xlpm.party, SUMIFS(ledger!J:J, ledger!B:B, _xlpm.party, ledger!E:E, "<>*RD*", ledger!D:D, "Kataan", ledger!C:C, "<>Closing CF") ))+ _xlfn.IFNA(L152, 0)} -> 0 | AD31: {=_xlfn.BYROW(B83, _xlfn.LAMBDA(_xlpm.party, SUMIFS(ledger!J:J, ledger!B:B, _xlpm.party, ledger!E:E, "<>*RD*", ledger!D:D, "Munaar", ledger!C:C, "<>Closing CF") ))+ _xlfn.IFNA(M152, 0)} -> 0 | AE31: {=_xlfn.BYROW(B83, _xlfn.LAMBDA(_xlpm.party, SUMIFS(ledger!J:J, ledger!B:B, _xlpm.party, ledger!E:E, "<>*RD*", ledger!D:D, "Super Kataan", ledger!C:C, "<>Closing CF") ))+ _xlfn.IFNA(N152, 0)} -> 0 | AF31: {=_xlfn.BYROW(B83, _xlfn.LAMBDA(_xlpm.party, SUMIFS(ledger!J:J, ledger!B:B, _xlpm.party, ledger!E:E, "<>*RD*", ledger!D:D, "Custom", ledger!C:C, "<>Closing CF") ))+ _xlfn.IFNA(O152, 0)} -> 0 | AG31: =X31+Y31+Z31+AA31+AB31+AC31+AD31+AF31+AE31 -> 3116070.8 | AH31: =(SUMIF(Table14[Party],S31,Table14[Credit]))+_xlfn.IFNA(Q152,0) -> 3116071 | AI31: =AG31-AH31 -> -0.22457937 | AJ31: 10 | AK31: 13
S32: Rehman Ali | T32: {=_xlfn.BYROW(B84,_xlfn.LAMBDA(_xlpm.party,SUMIFS(ledger!G:G,ledger!B:B,_xlpm.party,ledger!E:E,"<>*RD*")))+_xlfn.IFNA(C153,0)} -> 50131 | U32: {=_xlfn.BYROW(B84, _xlfn.LAMBDA(_xlpm.party, SUMIFS(ledger!G:G, ledger!B:B, _xlpm.party, ledger!E:E, "<>*RD*") / 1.0936 ))+_xlfn.IFNA(D153,0)} -> 45840.344 | V32: {=(_xlfn.BYROW(B84,_xlfn.LAMBDA(_xlpm.party,SUMIFS(ledger!G:G,ledger!B:B,_xlpm.party,ledger!E:E,"<>*RD*",ledger!D:D,"Chamki")+SUMIFS(ledger!G:G, ledger!B:B, _xlpm.party, ledger!E:E, "<>*RD*", ledger!D:D, "Crinkle")))/1.0936)+_xlfn.IFNA(E153,0)} -> 0 | W32: {=(_xlfn.BYROW(B84,_xlfn.LAMBDA(_xlpm.party,SUMIFS(ledger!G:G,ledger!B:B,_xlpm.party,ledger!E:E,"<>*RD*",ledger!D:D,"Silky")))/1.0936)+_xlfn.IFNA(F153,0)} -> 45840.344 | X32: {=(_xlfn.BYROW(B84,_xlfn.LAMBDA(_xlpm.party, (SUMIFS(ledger!J:J,ledger!B:B,_xlpm.party,ledger!E:E,"<>*RD*",ledger!D:D,"Chamki",ledger!C:C,"<>Closing CF")+ SUMIFS(ledger!J:J,ledger!B:B,_xlpm.party,ledger!E:E,"<>*RD*",ledger!D:D,"Crinkle",ledger!C:C,"<>Closing CF") )+_xlfn.IFNA(G153,0))))} -> 0 | Y32: {=_xlfn.BYROW(B84, _xlfn.LAMBDA(_xlpm.party, SUMIFS(ledger!J:J, ledger!B:B, _xlpm.party, ledger!E:E, "<>*RD*", ledger!D:D, "Silky", ledger!C:C, "<>Closing CF") )) + _xlfn.IFNA(H153, 0)} -> 595924.47 | Z32: {=_xlfn.BYROW(B84, _xlfn.LAMBDA(_xlpm.party, SUMIFS(ledger!J:J, ledger!B:B, _xlpm.party, ledger!E:E, "<>*RD*", ledger!D:D, "Slub", ledger!C:C, "<>Closing CF") ))+ _xlfn.IFNA(I153, 0)} -> 0 | AA32: {=_xlfn.BYROW(B84, _xlfn.LAMBDA(_xlpm.party, SUMIFS(ledger!J:J, ledger!B:B, _xlpm.party, ledger!E:E, "<>*RD*", ledger!D:D, "Satin", ledger!C:C, "<>Closing CF") ))+ _xlfn.IFNA(J153, 0)} -> 0 | AB32: {=_xlfn.BYROW(B84, _xlfn.LAMBDA(_xlpm.party, SUMIFS(ledger!J:J, ledger!B:B, _xlpm.party, ledger!E:E, "<>*RD*", ledger!D:D, "Black-Chamki", ledger!C:C, "<>Closing CF") ))+ _xlfn.IFNA(K153, 0)} -> 0 | AC32: {=_xlfn.BYROW(B84, _xlfn.LAMBDA(_xlpm.party, SUMIFS(ledger!J:J, ledger!B:B, _xlpm.party, ledger!E:E, "<>*RD*", ledger!D:D, "Kataan", ledger!C:C, "<>Closing CF") ))+ _xlfn.IFNA(L153, 0)} -> 0 | AD32: {=_xlfn.BYROW(B84, _xlfn.LAMBDA(_xlpm.party, SUMIFS(ledger!J:J, ledger!B:B, _xlpm.party, ledger!E:E, "<>*RD*", ledger!D:D, "Munaar", ledger!C:C, "<>Closing CF") ))+ _xlfn.IFNA(M153, 0)} -> 0 | AE32: {=_xlfn.BYROW(B84, _xlfn.LAMBDA(_xlpm.party, SUMIFS(ledger!J:J, ledger!B:B, _xlpm.party, ledger!E:E, "<>*RD*", ledger!D:D, "Super Kataan", ledger!C:C, "<>Closing CF") ))+ _xlfn.IFNA(N153, 0)} -> 0 | AF32: {=_xlfn.BYROW(B84, _xlfn.LAMBDA(_xlpm.party, SUMIFS(ledger!J:J, ledger!B:B, _xlpm.party, ledger!E:E, "<>*RD*", ledger!D:D, "Custom", ledger!C:C, "<>Closing CF") ))+ _xlfn.IFNA(O153, 0)} -> 0 | AG32: =X32+Y32+Z32+AA32+AB32+AC32+AD32+AF32+AE32 -> 595924.47 | AH32: =(SUMIF(Table14[Party],S32,Table14[Credit]))+_xlfn.IFNA(Q153,0) -> 550000 | AI32: =AG32-AH32 -> 45924.47 | AJ32: 10 | AK32: 13
S33: Ahmad Shafique | T33: {=_xlfn.BYROW(B85,_xlfn.LAMBDA(_xlpm.party,SUMIFS(ledger!G:G,ledger!B:B,_xlpm.party,ledger!E:E,"<>*RD*")))+_xlfn.IFNA(C154,0)} -> 53541 | U33: {=_xlfn.BYROW(B85, _xlfn.LAMBDA(_xlpm.party, SUMIFS(ledger!G:G, ledger!B:B, _xlpm.party, ledger!E:E, "<>*RD*") / 1.0936 ))+_xlfn.IFNA(D154,0)} -> 48958.486 | V33: {=(_xlfn.BYROW(B85,_xlfn.LAMBDA(_xlpm.party,SUMIFS(ledger!G:G,ledger!B:B,_xlpm.party,ledger!E:E,"<>*RD*",ledger!D:D,"Chamki")+SUMIFS(ledger!G:G, ledger!B:B, _xlpm.party, ledger!E:E, "<>*RD*", ledger!D:D, "Crinkle")))/1.0936)+_xlfn.IFNA(E154,0)} -> 0 | W33: {=(_xlfn.BYROW(B85,_xlfn.LAMBDA(_xlpm.party,SUMIFS(ledger!G:G,ledger!B:B,_xlpm.party,ledger!E:E,"<>*RD*",ledger!D:D,"Silky")))/1.0936)+_xlfn.IFNA(F154,0)} -> 48958.486 | X33: {=(_xlfn.BYROW(B85,_xlfn.LAMBDA(_xlpm.party, (SUMIFS(ledger!J:J,ledger!B:B,_xlpm.party,ledger!E:E,"<>*RD*",ledger!D:D,"Chamki",ledger!C:C,"<>Closing CF")+ SUMIFS(ledger!J:J,ledger!B:B,_xlpm.party,ledger!E:E,"<>*RD*",ledger!D:D,"Crinkle",ledger!C:C,"<>Closing CF") )+_xlfn.IFNA(G154,0))))} -> 0 | Y33: {=_xlfn.BYROW(B85, _xlfn.LAMBDA(_xlpm.party, SUMIFS(ledger!J:J, ledger!B:B, _xlpm.party, ledger!E:E, "<>*RD*", ledger!D:D, "Silky", ledger!C:C, "<>Closing CF") )) + _xlfn.IFNA(H154, 0)} -> 636460.31 | Z33: {=_xlfn.BYROW(B85, _xlfn.LAMBDA(_xlpm.party, SUMIFS(ledger!J:J, ledger!B:B, _xlpm.party, ledger!E:E, "<>*RD*", ledger!D:D, "Slub", ledger!C:C, "<>Closing CF") ))+ _xlfn.IFNA(I154, 0)} -> 0 | AA33: {=_xlfn.BYROW(B85, _xlfn.LAMBDA(_xlpm.party, SUMIFS(ledger!J:J, ledger!B:B, _xlpm.party, ledger!E:E, "<>*RD*", ledger!D:D, "Satin", ledger!C:C, "<>Closing CF") ))+ _xlfn.IFNA(J154, 0)} -> 0 | AB33: {=_xlfn.BYROW(B85, _xlfn.LAMBDA(_xlpm.party, SUMIFS(ledger!J:J, ledger!B:B, _xlpm.party, ledger!E:E, "<>*RD*", ledger!D:D, "Black-Chamki", ledger!C:C, "<>Closing CF") ))+ _xlfn.IFNA(K154, 0)} -> 0 | AC33: {=_xlfn.BYROW(B85, _xlfn.LAMBDA(_xlpm.party, SUMIFS(ledger!J:J, ledger!B:B, _xlpm.party, ledger!E:E, "<>*RD*", ledger!D:D, "Kataan", ledger!C:C, "<>Closing CF") ))+ _xlfn.IFNA(L154, 0)} -> 0 | AD33: {=_xlfn.BYROW(B85, _xlfn.LAMBDA(_xlpm.party, SUMIFS(ledger!J:J, ledger!B:B, _xlpm.party, ledger!E:E, "<>*RD*", ledger!D:D, "Munaar", ledger!C:C, "<>Closing CF") ))+ _xlfn.IFNA(M154, 0)} -> 0 | AE33: {=_xlfn.BYROW(B85, _xlfn.LAMBDA(_xlpm.party, SUMIFS(ledger!J:J, ledger!B:B, _xlpm.party, ledger!E:E, "<>*RD*", ledger!D:D, "Super Kataan", ledger!C:C, "<>Closing CF") ))+ _xlfn.IFNA(N154, 0)} -> 0 | AF33: {=_xlfn.BYROW(B85, _xlfn.LAMBDA(_xlpm.party, SUMIFS(ledger!J:J, ledger!B:B, _xlpm.party, ledger!E:E, "<>*RD*", ledger!D:D, "Custom", ledger!C:C, "<>Closing CF") ))+ _xlfn.IFNA(O154, 0)} -> 0 | AG33: =X33+Y33+Z33+AA33+AB33+AC33+AD33+AF33+AE33 -> 636460.31 | AH33: =(SUMIF(Table14[Party],S33,Table14[Credit]))+_xlfn.IFNA(Q154,0) -> 636000 | AI33: =AG33-AH33 -> 460.31456 | AJ33: 10 | AK33: 13
S34: Hafiz Shawl | T34: {=_xlfn.BYROW(B86,_xlfn.LAMBDA(_xlpm.party,SUMIFS(ledger!G:G,ledger!B:B,_xlpm.party,ledger!E:E,"<>*RD*")))+_xlfn.IFNA(C155,0)} -> 33395 | U34: {=_xlfn.BYROW(B86, _xlfn.LAMBDA(_xlpm.party, SUMIFS(ledger!G:G, ledger!B:B, _xlpm.party, ledger!E:E, "<>*RD*") / 1.0936 ))+_xlfn.IFNA(D155,0)} -> 30536.759 | V34: {=(_xlfn.BYROW(B86,_xlfn.LAMBDA(_xlpm.party,SUMIFS(ledger!G:G,ledger!B:B,_xlpm.party,ledger!E:E,"<>*RD*",ledger!D:D,"Chamki")+SUMIFS(ledger!G:G, ledger!B:B, _xlpm.party, ledger!E:E, "<>*RD*", ledger!D:D, "Crinkle")))/1.0936)+_xlfn.IFNA(E155,0)} -> 0 | W34: {=(_xlfn.BYROW(B86,_xlfn.LAMBDA(_xlpm.party,SUMIFS(ledger!G:G,ledger!B:B,_xlpm.party,ledger!E:E,"<>*RD*",ledger!D:D,"Silky")))/1.0936)+_xlfn.IFNA(F155,0)} -> 1321.3241 | X34: {=(_xlfn.BYROW(B86,_xlfn.LAMBDA(_xlpm.party, (SUMIFS(ledger!J:J,ledger!B:B,_xlpm.party,ledger!E:E,"<>*RD*",ledger!D:D,"Chamki",ledger!C:C,"<>Closing CF")+ SUMIFS(ledger!J:J,ledger!B:B,_xlpm.party,ledger!E:E,"<>*RD*",ledger!D:D,"Crinkle",ledger!C:C,"<>Closing CF") )+_xlfn.IFNA(G155,0))))} -> 0 | Y34: {=_xlfn.BYROW(B86, _xlfn.LAMBDA(_xlpm.party, SUMIFS(ledger!J:J, ledger!B:B, _xlpm.party, ledger!E:E, "<>*RD*", ledger!D:D, "Silky", ledger!C:C, "<>Closing CF") )) + _xlfn.IFNA(H155, 0)} -> 15855.889 | Z34: {=_xlfn.BYROW(B86, _xlfn.LAMBDA(_xlpm.party, SUMIFS(ledger!J:J, ledger!B:B, _xlpm.party, ledger!E:E, "<>*RD*", ledger!D:D, "Slub", ledger!C:C, "<>Closing CF") ))+ _xlfn.IFNA(I155, 0)} -> 0 | AA34: {=_xlfn.BYROW(B86, _xlfn.LAMBDA(_xlpm.party, SUMIFS(ledger!J:J, ledger!B:B, _xlpm.party, ledger!E:E, "<>*RD*", ledger!D:D, "Satin", ledger!C:C, "<>Closing CF") ))+ _xlfn.IFNA(J155, 0)} -> 0 | AB34: {=_xlfn.BYROW(B86, _xlfn.LAMBDA(_xlpm.party, SUMIFS(ledger!J:J, ledger!B:B, _xlpm.party, ledger!E:E, "<>*RD*", ledger!D:D, "Black-Chamki", ledger!C:C, "<>Closing CF") ))+ _xlfn.IFNA(K155, 0)} -> 0 | AC34: {=_xlfn.BYROW(B86, _xlfn.LAMBDA(_xlpm.party, SUMIFS(ledger!J:J, ledger!B:B, _xlpm.party, ledger!E:E, "<>*RD*", ledger!D:D, "Kataan", ledger!C:C, "<>Closing CF") ))+ _xlfn.IFNA(L155, 0)} -> 0 | AD34: {=_xlfn.BYROW(B86, _xlfn.LAMBDA(_xlpm.party, SUMIFS(ledger!J:J, ledger!B:B, _xlpm.party, ledger!E:E, "<>*RD*", ledger!D:D, "Munaar", ledger!C:C, "<>Closing CF") ))+ _xlfn.IFNA(M155, 0)} -> 0 | AE34: {=_xlfn.BYROW(B86, _xlfn.LAMBDA(_xlpm.party, SUMIFS(ledger!J:J, ledger!B:B, _xlpm.party, ledger!E:E, "<>*RD*", ledger!D:D, "Super Kataan", ledger!C:C, "<>Closing CF") ))+ _xlfn.IFNA(N155, 0)} -> 0 | AF34: {=_xlfn.BYROW(B86, _xlfn.LAMBDA(_xlpm.party, SUMIFS(ledger!J:J, ledger!B:B, _xlpm.party, ledger!E:E, "<>*RD*", ledger!D:D, "Custom", ledger!C:C, "<>Closing CF") ))+ _xlfn.IFNA(O155, 0)} -> 584043.53 | AG34: =X34+Y34+Z34+AA34+AB34+AC34+AD34+AF34+AE34 -> 599899.41 | AH34: =(SUMIF(Table14[Party],S34,Table14[Credit]))+_xlfn.IFNA(Q155,0) -> 55855 | AI34: =AG34-AH34 -> 544044.41 | AJ34: 10 | AK34: 13
S35: Zahid Ejaz | T35: {=_xlfn.BYROW(B87,_xlfn.LAMBDA(_xlpm.party,SUMIFS(ledger!G:G,ledger!B:B,_xlpm.party,ledger!E:E,"<>*RD*")))+_xlfn.IFNA(C156,0)} -> 16060 | U35: {=_xlfn.BYROW(B87, _xlfn.LAMBDA(_xlpm.party, SUMIFS(ledger!G:G, ledger!B:B, _xlpm.party, ledger!E:E, "<>*RD*") / 1.0936 ))+_xlfn.IFNA(D156,0)} -> 14685.443 | V35: {=(_xlfn.BYROW(B87,_xlfn.LAMBDA(_xlpm.party,SUMIFS(ledger!G:G,ledger!B:B,_xlpm.party,ledger!E:E,"<>*RD*",ledger!D:D,"Chamki")+SUMIFS(ledger!G:G, ledger!B:B, _xlpm.party, ledger!E:E, "<>*RD*", ledger!D:D, "Crinkle")))/1.0936)+_xlfn.IFNA(E156,0)} -> 14685.443 | W35: {=(_xlfn.BYROW(B87,_xlfn.LAMBDA(_xlpm.party,SUMIFS(ledger!G:G,ledger!B:B,_xlpm.party,ledger!E:E,"<>*RD*",ledger!D:D,"Silky")))/1.0936)+_xlfn.IFNA(F156,0)} -> 0 | X35: {=(_xlfn.BYROW(B87,_xlfn.LAMBDA(_xlpm.party, (SUMIFS(ledger!J:J,ledger!B:B,_xlpm.party,ledger!E:E,"<>*RD*",ledger!D:D,"Chamki",ledger!C:C,"<>Closing CF")+ SUMIFS(ledger!J:J,ledger!B:B,_xlpm.party,ledger!E:E,"<>*RD*",ledger!D:D,"Crinkle",ledger!C:C,"<>Closing CF") )+_xlfn.IFNA(G156,0))))} -> 161539.87 | Y35: {=_xlfn.BYROW(B87, _xlfn.LAMBDA(_xlpm.party, SUMIFS(ledger!J:J, ledger!B:B, _xlpm.party, ledger!E:E, "<>*RD*", ledger!D:D, "Silky", ledger!C:C, "<>Closing CF") )) + _xlfn.IFNA(H156, 0)} -> 0 | Z35: {=_xlfn.BYROW(B87, _xlfn.LAMBDA(_xlpm.party, SUMIFS(ledger!J:J, ledger!B:B, _xlpm.party, ledger!E:E, "<>*RD*", ledger!D:D, "Slub", ledger!C:C, "<>Closing CF") ))+ _xlfn.IFNA(I156, 0)} -> 0 | AA35: {=_xlfn.BYROW(B87, _xlfn.LAMBDA(_xlpm.party, SUMIFS(ledger!J:J, ledger!B:B, _xlpm.party, ledger!E:E, "<>*RD*", ledger!D:D, "Satin", ledger!C:C, "<>Closing CF") ))+ _xlfn.IFNA(J156, 0)} -> 0 | AB35: {=_xlfn.BYROW(B87, _xlfn.LAMBDA(_xlpm.party, SUMIFS(ledger!J:J, ledger!B:B, _xlpm.party, ledger!E:E, "<>*RD*", ledger!D:D, "Black-Chamki", ledger!C:C, "<>Closing CF") ))+ _xlfn.IFNA(K156, 0)} -> 0 | AC35: {=_xlfn.BYROW(B87, _xlfn.LAMBDA(_xlpm.party, SUMIFS(ledger!J:J, ledger!B:B, _xlpm.party, ledger!E:E, "<>*RD*", ledger!D:D, "Kataan", ledger!C:C, "<>Closing CF") ))+ _xlfn.IFNA(L156, 0)} -> 0 | AD35: {=_xlfn.BYROW(B87, _xlfn.LAMBDA(_xlpm.party, SUMIFS(ledger!J:J, ledger!B:B, _xlpm.party, ledger!E:E, "<>*RD*", ledger!D:D, "Munaar", ledger!C:C, "<>Closing CF") ))+ _xlfn.IFNA(M156, 0)} -> 0 | AE35: {=_xlfn.BYROW(B87, _xlfn.LAMBDA(_xlpm.party, SUMIFS(ledger!J:J, ledger!B:B, _xlpm.party, ledger!E:E, "<>*RD*", ledger!D:D, "Super Kataan", ledger!C:C, "<>Closing CF") ))+ _xlfn.IFNA(N156, 0)} -> 0 | AF35: {=_xlfn.BYROW(B87, _xlfn.LAMBDA(_xlpm.party, SUMIFS(ledger!J:J, ledger!B:B, _xlpm.party, ledger!E:E, "<>*RD*", ledger!D:D, "Custom", ledger!C:C, "<>Closing CF") ))+ _xlfn.IFNA(O156, 0)} -> 0 | AG35: =X35+Y35+Z35+AA35+AB35+AC35+AD35+AF35+AE35 -> 161539.87 | AH35: =(SUMIF(Table14[Party],S35,Table14[Credit]))+_xlfn.IFNA(Q156,0) -> 169278 | AI35: =AG35-AH35 -> -7738.1317 | AJ35: 10 | AK35: 13
S36: Faizan Kamoki | T36: {=_xlfn.BYROW(B88,_xlfn.LAMBDA(_xlpm.party,SUMIFS(ledger!G:G,ledger!B:B,_xlpm.party,ledger!E:E,"<>*RD*")))+_xlfn.IFNA(C157,0)} -> 895614 | U36: {=_xlfn.BYROW(B88, _xlfn.LAMBDA(_xlpm.party, SUMIFS(ledger!G:G, ledger!B:B, _xlpm.party, ledger!E:E, "<>*RD*") / 1.0936 ))+_xlfn.IFNA(D157,0)} -> 818959.4 | V36: {=(_xlfn.BYROW(B88,_xlfn.LAMBDA(_xlpm.party,SUMIFS(ledger!G:G,ledger!B:B,_xlpm.party,ledger!E:E,"<>*RD*",ledger!D:D,"Chamki")+SUMIFS(ledger!G:G, ledger!B:B, _xlpm.party, ledger!E:E, "<>*RD*", ledger!D:D, "Crinkle")))/1.0936)+_xlfn.IFNA(E157,0)} -> 0 | W36: {=(_xlfn.BYROW(B88,_xlfn.LAMBDA(_xlpm.party,SUMIFS(ledger!G:G,ledger!B:B,_xlpm.party,ledger!E:E,"<>*RD*",ledger!D:D,"Silky")))/1.0936)+_xlfn.IFNA(F157,0)} -> 623105.34 | X36: {=(_xlfn.BYROW(B88,_xlfn.LAMBDA(_xlpm.party, (SUMIFS(ledger!J:J,ledger!B:B,_xlpm.party,ledger!E:E,"<>*RD*",ledger!D:D,"Chamki",ledger!C:C,"<>Closing CF")+ SUMIFS(ledger!J:J,ledger!B:B,_xlpm.party,ledger!E:E,"<>*RD*",ledger!D:D,"Crinkle",ledger!C:C,"<>Closing CF") )+_xlfn.IFNA(G157,0))))} -> 0 | Y36: {=_xlfn.BYROW(B88, _xlfn.LAMBDA(_xlpm.party, SUMIFS(ledger!J:J, ledger!B:B, _xlpm.party, ledger!E:E, "<>*RD*", ledger!D:D, "Silky", ledger!C:C, "<>Closing CF") )) + _xlfn.IFNA(H157, 0)} -> 8100369.4 | Z36: {=_xlfn.BYROW(B88, _xlfn.LAMBDA(_xlpm.party, SUMIFS(ledger!J:J, ledger!B:B, _xlpm.party, ledger!E:E, "<>*RD*", ledger!D:D, "Slub", ledger!C:C, "<>Closing CF") ))+ _xlfn.IFNA(I157, 0)} -> 0 | AA36: {=_xlfn.BYROW(B88, _xlfn.LAMBDA(_xlpm.party, SUMIFS(ledger!J:J, ledger!B:B, _xlpm.party, ledger!E:E, "<>*RD*", ledger!D:D, "Satin", ledger!C:C, "<>Closing CF") ))+ _xlfn.IFNA(J157, 0)} -> 0 | AB36: {=_xlfn.BYROW(B88, _xlfn.LAMBDA(_xlpm.party, SUMIFS(ledger!J:J, ledger!B:B, _xlpm.party, ledger!E:E, "<>*RD*", ledger!D:D, "Black-Chamki", ledger!C:C, "<>Closing CF") ))+ _xlfn.IFNA(K157, 0)} -> 0 | AC36: {=_xlfn.BYROW(B88, _xlfn.LAMBDA(_xlpm.party, SUMIFS(ledger!J:J, ledger!B:B, _xlpm.party, ledger!E:E, "<>*RD*", ledger!D:D, "Kataan", ledger!C:C, "<>Closing CF") ))+ _xlfn.IFNA(L157, 0)} -> 1894656.2 | AD36: {=_xlfn.BYROW(B88, _xlfn.LAMBDA(_xlpm.party, SUMIFS(ledger!J:J, ledger!B:B, _xlpm.party, ledger!E:E, "<>*RD*", ledger!D:D, "Munaar", ledger!C:C, "<>Closing CF") ))+ _xlfn.IFNA(M157, 0)} -> 0 | AE36: {=_xlfn.BYROW(B88, _xlfn.LAMBDA(_xlpm.party, SUMIFS(ledger!J:J, ledger!B:B, _xlpm.party, ledger!E:E, "<>*RD*", ledger!D:D, "Super Kataan", ledger!C:C, "<>Closing CF") ))+ _xlfn.IFNA(N157, 0)} -> 133035.84 | AF36: {=_xlfn.BYROW(B88, _xlfn.LAMBDA(_xlpm.party, SUMIFS(ledger!J:J, ledger!B:B, _xlpm.party, ledger!E:E, "<>*RD*", ledger!D:D, "Custom", ledger!C:C, "<>Closing CF") ))+ _xlfn.IFNA(O157, 0)} -> 272523.77 | AG36: =X36+Y36+Z36+AA36+AB36+AC36+AD36+AF36+AE36 -> 10400585 | AH36: =(SUMIF(Table14[Party],S36,Table14[Credit]))+_xlfn.IFNA(Q157,0) -> 10399441 | AI36: =AG36-AH36 -> 1143.7301
S37: KK fabrics | T37: {=_xlfn.BYROW(B89,_xlfn.LAMBDA(_xlpm.party,SUMIFS(ledger!G:G,ledger!B:B,_xlpm.party,ledger!E:E,"<>*RD*")))+_xlfn.IFNA(C158,0)} -> 59639 | U37: {=_xlfn.BYROW(B89, _xlfn.LAMBDA(_xlpm.party, SUMIFS(ledger!G:G, ledger!B:B, _xlpm.party, ledger!E:E, "<>*RD*") / 1.0936 ))+_xlfn.IFNA(D158,0)} -> 54534.565 | V37: {=(_xlfn.BYROW(B89,_xlfn.LAMBDA(_xlpm.party,SUMIFS(ledger!G:G,ledger!B:B,_xlpm.party,ledger!E:E,"<>*RD*",ledger!D:D,"Chamki")+SUMIFS(ledger!G:G, ledger!B:B, _xlpm.party, ledger!E:E, "<>*RD*", ledger!D:D, "Crinkle")))/1.0936)+_xlfn.IFNA(E158,0)} -> 54534.565 | W37: {=(_xlfn.BYROW(B89,_xlfn.LAMBDA(_xlpm.party,SUMIFS(ledger!G:G,ledger!B:B,_xlpm.party,ledger!E:E,"<>*RD*",ledger!D:D,"Silky")))/1.0936)+_xlfn.IFNA(F158,0)} -> 0 | X37: {=(_xlfn.BYROW(B89,_xlfn.LAMBDA(_xlpm.party, (SUMIFS(ledger!J:J,ledger!B:B,_xlpm.party,ledger!E:E,"<>*RD*",ledger!D:D,"Chamki",ledger!C:C,"<>Closing CF")+ SUMIFS(ledger!J:J,ledger!B:B,_xlpm.party,ledger!E:E,"<>*RD*",ledger!D:D,"Crinkle",ledger!C:C,"<>Closing CF") )+_xlfn.IFNA(G158,0))))} -> 545345.65 | Y37: {=_xlfn.BYROW(B89, _xlfn.LAMBDA(_xlpm.party, SUMIFS(ledger!J:J, ledger!B:B, _xlpm.party, ledger!E:E, "<>*RD*", ledger!D:D, "Silky", ledger!C:C, "<>Closing CF") )) + _xlfn.IFNA(H158, 0)} -> 0 | Z37: {=_xlfn.BYROW(B89, _xlfn.LAMBDA(_xlpm.party, SUMIFS(ledger!J:J, ledger!B:B, _xlpm.party, ledger!E:E, "<>*RD*", ledger!D:D, "Slub", ledger!C:C, "<>Closing CF") ))+ _xlfn.IFNA(I158, 0)} -> 0 | AA37: {=_xlfn.BYROW(B89, _xlfn.LAMBDA(_xlpm.party, SUMIFS(ledger!J:J, ledger!B:B, _xlpm.party, ledger!E:E, "<>*RD*", ledger!D:D, "Satin", ledger!C:C, "<>Closing CF") ))+ _xlfn.IFNA(J158, 0)} -> 0 | AB37: {=_xlfn.BYROW(B89, _xlfn.LAMBDA(_xlpm.party, SUMIFS(ledger!J:J, ledger!B:B, _xlpm.party, ledger!E:E, "<>*RD*", ledger!D:D, "Black-Chamki", ledger!C:C, "<>Closing CF") ))+ _xlfn.IFNA(K158, 0)} -> 0 | AC37: {=_xlfn.BYROW(B89, _xlfn.LAMBDA(_xlpm.party, SUMIFS(ledger!J:J, ledger!B:B, _xlpm.party, ledger!E:E, "<>*RD*", ledger!D:D, "Kataan", ledger!C:C, "<>Closing CF") ))+ _xlfn.IFNA(L158, 0)} -> 0 | AD37: {=_xlfn.BYROW(B89, _xlfn.LAMBDA(_xlpm.party, SUMIFS(ledger!J:J, ledger!B:B, _xlpm.party, ledger!E:E, "<>*RD*", ledger!D:D, "Munaar", ledger!C:C, "<>Closing CF") ))+ _xlfn.IFNA(M158, 0)} -> 0 | AE37: {=_xlfn.BYROW(B89, _xlfn.LAMBDA(_xlpm.party, SUMIFS(ledger!J:J, ledger!B:B, _xlpm.party, ledger!E:E, "<>*RD*", ledger!D:D, "Super Kataan", ledger!C:C, "<>Closing CF") ))+ _xlfn.IFNA(N158, 0)} -> 0 | AF37: {=_xlfn.BYROW(B89, _xlfn.LAMBDA(_xlpm.party, SUMIFS(ledger!J:J, ledger!B:B, _xlpm.party, ledger!E:E, "<>*RD*", ledger!D:D, "Custom", ledger!C:C, "<>Closing CF") ))+ _xlfn.IFNA(O158, 0)} -> 0 | AG37: =X37+Y37+Z37+AA37+AB37+AC37+AD37+AF37+AE37 -> 545345.65 | AH37: =(SUMIF(Table14[Party],S37,Table14[Credit]))+_xlfn.IFNA(Q158,0) -> 544000 | AI37: =AG37-AH37 -> 1345.6474
S38: Rauf Khan | T38: {=_xlfn.BYROW(B90,_xlfn.LAMBDA(_xlpm.party,SUMIFS(ledger!G:G,ledger!B:B,_xlpm.party,ledger!E:E,"<>*RD*")))+_xlfn.IFNA(C159,0)} -> 474322 | U38: {=_xlfn.BYROW(B90, _xlfn.LAMBDA(_xlpm.party, SUMIFS(ledger!G:G, ledger!B:B, _xlpm.party, ledger!E:E, "<>*RD*") / 1.0936 ))+_xlfn.IFNA(D159,0)} -> 433725.31 | V38: {=(_xlfn.BYROW(B90,_xlfn.LAMBDA(_xlpm.party,SUMIFS(ledger!G:G,ledger!B:B,_xlpm.party,ledger!E:E,"<>*RD*",ledger!D:D,"Chamki")+SUMIFS(ledger!G:G, ledger!B:B, _xlpm.party, ledger!E:E, "<>*RD*", ledger!D:D, "Crinkle")))/1.0936)+_xlfn.IFNA(E159,0)} -> 86493.233 | W38: {=(_xlfn.BYROW(B90,_xlfn.LAMBDA(_xlpm.party,SUMIFS(ledger!G:G,ledger!B:B,_xlpm.party,ledger!E:E,"<>*RD*",ledger!D:D,"Silky")))/1.0936)+_xlfn.IFNA(F159,0)} -> 243062.36 | X38: {=(_xlfn.BYROW(B90,_xlfn.LAMBDA(_xlpm.party, (SUMIFS(ledger!J:J,ledger!B:B,_xlpm.party,ledger!E:E,"<>*RD*",ledger!D:D,"Chamki",ledger!C:C,"<>Closing CF")+ SUMIFS(ledger!J:J,ledger!B:B,_xlpm.party,ledger!E:E,"<>*RD*",ledger!D:D,"Crinkle",ledger!C:C,"<>Closing CF") )+_xlfn.IFNA(G159,0))))} -> 864932.33 | Y38: {=_xlfn.BYROW(B90, _xlfn.LAMBDA(_xlpm.party, SUMIFS(ledger!J:J, ledger!B:B, _xlpm.party, ledger!E:E, "<>*RD*", ledger!D:D, "Silky", ledger!C:C, "<>Closing CF") )) + _xlfn.IFNA(H159, 0)} -> 2916748.4 | Z38: {=_xlfn.BYROW(B90, _xlfn.LAMBDA(_xlpm.party, SUMIFS(ledger!J:J, ledger!B:B, _xlpm.party, ledger!E:E, "<>*RD*", ledger!D:D, "Slub", ledger!C:C, "<>Closing CF") ))+ _xlfn.IFNA(I159, 0)} -> 0 | AA38: {=_xlfn.BYROW(B90, _xlfn.LAMBDA(_xlpm.party, SUMIFS(ledger!J:J, ledger!B:B, _xlpm.party, ledger!E:E, "<>*RD*", ledger!D:D, "Satin", ledger!C:C, "<>Closing CF") ))+ _xlfn.IFNA(J159, 0)} -> 1562545.7 | AB38: {=_xlfn.BYROW(B90, _xlfn.LAMBDA(_xlpm.party, SUMIFS(ledger!J:J, ledger!B:B, _xlpm.party, ledger!E:E, "<>*RD*", ledger!D:D, "Black-Chamki", ledger!C:C, "<>Closing CF") ))+ _xlfn.IFNA(K159, 0)} -> 0 | AC38: {=_xlfn.BYROW(B90, _xlfn.LAMBDA(_xlpm.party, SUMIFS(ledger!J:J, ledger!B:B, _xlpm.party, ledger!E:E, "<>*RD*", ledger!D:D, "Kataan", ledger!C:C, "<>Closing CF") ))+ _xlfn.IFNA(L159, 0)} -> 0 | AD38: {=_xlfn.BYROW(B90, _xlfn.LAMBDA(_xlpm.party, SUMIFS(ledger!J:J, ledger!B:B, _xlpm.party, ledger!E:E, "<>*RD*", ledger!D:D, "Munaar", ledger!C:C, "<>Closing CF") ))+ _xlfn.IFNA(M159, 0)} -> 0 | AE38: {=_xlfn.BYROW(B90, _xlfn.LAMBDA(_xlpm.party, SUMIFS(ledger!J:J, ledger!B:B, _xlpm.party, ledger!E:E, "<>*RD*", ledger!D:D, "Super Kataan", ledger!C:C, "<>Closing CF") ))+ _xlfn.IFNA(N159, 0)} -> 0 | AF38: {=_xlfn.BYROW(B90, _xlfn.LAMBDA(_xlpm.party, SUMIFS(ledger!J:J, ledger!B:B, _xlpm.party, ledger!E:E, "<>*RD*", ledger!D:D, "Custom", ledger!C:C, "<>Closing CF") ))+ _xlfn.IFNA(O159, 0)} -> 17000 | AG38: =X38+Y38+Z38+AA38+AB38+AC38+AD38+AF38+AE38 -> 5361226.4 | AH38: =(SUMIF(Table14[Party],S38,Table14[Credit]))+_xlfn.IFNA(Q159,0) -> 5146879 | AI38: =AG38-AH38 -> 214347.41
S39: Farhaan ali | T39: {=_xlfn.BYROW(B91,_xlfn.LAMBDA(_xlpm.party,SUMIFS(ledger!G:G,ledger!B:B,_xlpm.party,ledger!E:E,"<>*RD*")))+_xlfn.IFNA(C160,0)} -> 195693 | U39: {=_xlfn.BYROW(B91, _xlfn.LAMBDA(_xlpm.party, SUMIFS(ledger!G:G, ledger!B:B, _xlpm.party, ledger!E:E, "<>*RD*") / 1.0936 ))+_xlfn.IFNA(D160,0)} -> 178943.86 | V39: {=(_xlfn.BYROW(B91,_xlfn.LAMBDA(_xlpm.party,SUMIFS(ledger!G:G,ledger!B:B,_xlpm.party,ledger!E:E,"<>*RD*",ledger!D:D,"Chamki")+SUMIFS(ledger!G:G, ledger!B:B, _xlpm.party, ledger!E:E, "<>*RD*", ledger!D:D, "Crinkle")))/1.0936)+_xlfn.IFNA(E160,0)} -> 0 | W39: {=(_xlfn.BYROW(B91,_xlfn.LAMBDA(_xlpm.party,SUMIFS(ledger!G:G,ledger!B:B,_xlpm.party,ledger!E:E,"<>*RD*",ledger!D:D,"Silky")))/1.0936)+_xlfn.IFNA(F160,0)} -> 178943.86 | X39: {=(_xlfn.BYROW(B91,_xlfn.LAMBDA(_xlpm.party, (SUMIFS(ledger!J:J,ledger!B:B,_xlpm.party,ledger!E:E,"<>*RD*",ledger!D:D,"Chamki",ledger!C:C,"<>Closing CF")+ SUMIFS(ledger!J:J,ledger!B:B,_xlpm.party,ledger!E:E,"<>*RD*",ledger!D:D,"Crinkle",ledger!C:C,"<>Closing CF") )+_xlfn.IFNA(G160,0))))} -> 0 | Y39: {=_xlfn.BYROW(B91, _xlfn.LAMBDA(_xlpm.party, SUMIFS(ledger!J:J, ledger!B:B, _xlpm.party, ledger!E:E, "<>*RD*", ledger!D:D, "Silky", ledger!C:C, "<>Closing CF") )) + _xlfn.IFNA(H160, 0)} -> 2147326.3 | Z39: {=_xlfn.BYROW(B91, _xlfn.LAMBDA(_xlpm.party, SUMIFS(ledger!J:J, ledger!B:B, _xlpm.party, ledger!E:E, "<>*RD*", ledger!D:D, "Slub", ledger!C:C, "<>Closing CF") ))+ _xlfn.IFNA(I160, 0)} -> 0 | AA39: {=_xlfn.BYROW(B91, _xlfn.LAMBDA(_xlpm.party, SUMIFS(ledger!J:J, ledger!B:B, _xlpm.party, ledger!E:E, "<>*RD*", ledger!D:D, "Satin", ledger!C:C, "<>Closing CF") ))+ _xlfn.IFNA(J160, 0)} -> 0 | AB39: {=_xlfn.BYROW(B91, _xlfn.LAMBDA(_xlpm.party, SUMIFS(ledger!J:J, ledger!B:B, _xlpm.party, ledger!E:E, "<>*RD*", ledger!D:D, "Black-Chamki", ledger!C:C, "<>Closing CF") ))+ _xlfn.IFNA(K160, 0)} -> 0 | AC39: {=_xlfn.BYROW(B91, _xlfn.LAMBDA(_xlpm.party, SUMIFS(ledger!J:J, ledger!B:B, _xlpm.party, ledger!E:E, "<>*RD*", ledger!D:D, "Kataan", ledger!C:C, "<>Closing CF") ))+ _xlfn.IFNA(L160, 0)} -> 0 | AD39: {=_xlfn.BYROW(B91, _xlfn.LAMBDA(_xlpm.party, SUMIFS(ledger!J:J, ledger!B:B, _xlpm.party, ledger!E:E, "<>*RD*", ledger!D:D, "Munaar", ledger!C:C, "<>Closing CF") ))+ _xlfn.IFNA(M160, 0)} -> 0 | AE39: {=_xlfn.BYROW(B91, _xlfn.LAMBDA(_xlpm.party, SUMIFS(ledger!J:J, ledger!B:B, _xlpm.party, ledger!E:E, "<>*RD*", ledger!D:D, "Super Kataan", ledger!C:C, "<>Closing CF") ))+ _xlfn.IFNA(N160, 0)} -> 0 | AF39: {=_xlfn.BYROW(B91, _xlfn.LAMBDA(_xlpm.party, SUMIFS(ledger!J:J, ledger!B:B, _xlpm.party, ledger!E:E, "<>*RD*", ledger!D:D, "Custom", ledger!C:C, "<>Closing CF") ))+ _xlfn.IFNA(O160, 0)} -> 0 | AG39: =X39+Y39+Z39+AA39+AB39+AC39+AD39+AF39+AE39 -> 2147326.3 | AH39: =(SUMIF(Table14[Party],S39,Table14[Credit]))+_xlfn.IFNA(Q160,0) -> 2147000 | AI39: =AG39-AH39 -> 326.26189
S40: ACM salman zaffar | T40: {=_xlfn.BYROW(B92,_xlfn.LAMBDA(_xlpm.party,SUMIFS(ledger!G:G,ledger!B:B,_xlpm.party,ledger!E:E,"<>*RD*")))+_xlfn.IFNA(C161,0)} -> 94735 | U40: {=_xlfn.BYROW(B92, _xlfn.LAMBDA(_xlpm.party, SUMIFS(ledger!G:G, ledger!B:B, _xlpm.party, ledger!E:E, "<>*RD*") / 1.0936 ))+_xlfn.IFNA(D161,0)} -> 86626.737 | V40: {=(_xlfn.BYROW(B92,_xlfn.LAMBDA(_xlpm.party,SUMIFS(ledger!G:G,ledger!B:B,_xlpm.party,ledger!E:E,"<>*RD*",ledger!D:D,"Chamki")+SUMIFS(ledger!G:G, ledger!B:B, _xlpm.party, ledger!E:E, "<>*RD*", ledger!D:D, "Crinkle")))/1.0936)+_xlfn.IFNA(E161,0)} -> 84342.538 | W40: {=(_xlfn.BYROW(B92,_xlfn.LAMBDA(_xlpm.party,SUMIFS(ledger!G:G,ledger!B:B,_xlpm.party,ledger!E:E,"<>*RD*",ledger!D:D,"Silky")))/1.0936)+_xlfn.IFNA(F161,0)} -> 2284.199 | X40: {=(_xlfn.BYROW(B92,_xlfn.LAMBDA(_xlpm.party, (SUMIFS(ledger!J:J,ledger!B:B,_xlpm.party,ledger!E:E,"<>*RD*",ledger!D:D,"Chamki",ledger!C:C,"<>Closing CF")+ SUMIFS(ledger!J:J,ledger!B:B,_xlpm.party,ledger!E:E,"<>*RD*",ledger!D:D,"Crinkle",ledger!C:C,"<>Closing CF") )+_xlfn.IFNA(G161,0))))} -> 843425.38 | Y40: {=_xlfn.BYROW(B92, _xlfn.LAMBDA(_xlpm.party, SUMIFS(ledger!J:J, ledger!B:B, _xlpm.party, ledger!E:E, "<>*RD*", ledger!D:D, "Silky", ledger!C:C, "<>Closing CF") )) + _xlfn.IFNA(H161, 0)} -> 29694.587 | Z40: {=_xlfn.BYROW(B92, _xlfn.LAMBDA(_xlpm.party, SUMIFS(ledger!J:J, ledger!B:B, _xlpm.party, ledger!E:E, "<>*RD*", ledger!D:D, "Slub", ledger!C:C, "<>Closing CF") ))+ _xlfn.IFNA(I161, 0)} -> 0 | AA40: {=_xlfn.BYROW(B92, _xlfn.LAMBDA(_xlpm.party, SUMIFS(ledger!J:J, ledger!B:B, _xlpm.party, ledger!E:E, "<>*RD*", ledger!D:D, "Satin", ledger!C:C, "<>Closing CF") ))+ _xlfn.IFNA(J161, 0)} -> 0 | AB40: {=_xlfn.BYROW(B92, _xlfn.LAMBDA(_xlpm.party, SUMIFS(ledger!J:J, ledger!B:B, _xlpm.party, ledger!E:E, "<>*RD*", ledger!D:D, "Black-Chamki", ledger!C:C, "<>Closing CF") ))+ _xlfn.IFNA(K161, 0)} -> 0 | AC40: {=_xlfn.BYROW(B92, _xlfn.LAMBDA(_xlpm.party, SUMIFS(ledger!J:J, ledger!B:B, _xlpm.party, ledger!E:E, "<>*RD*", ledger!D:D, "Kataan", ledger!C:C, "<>Closing CF") ))+ _xlfn.IFNA(L161, 0)} -> 0 | AD40: {=_xlfn.BYROW(B92, _xlfn.LAMBDA(_xlpm.party, SUMIFS(ledger!J:J, ledger!B:B, _xlpm.party, ledger!E:E, "<>*RD*", ledger!D:D, "Munaar", ledger!C:C, "<>Closing CF") ))+ _xlfn.IFNA(M161, 0)} -> 0 | AE40: {=_xlfn.BYROW(B92, _xlfn.LAMBDA(_xlpm.party, SUMIFS(ledger!J:J, ledger!B:B, _xlpm.party, ledger!E:E, "<>*RD*", ledger!D:D, "Super Kataan", ledger!C:C, "<>Closing CF") ))+ _xlfn.IFNA(N161, 0)} -> 0 | AF40: {=_xlfn.BYROW(B92, _xlfn.LAMBDA(_xlpm.party, SUMIFS(ledger!J:J, ledger!B:B, _xlpm.party, ledger!E:E, "<>*RD*", ledger!D:D, "Custom", ledger!C:C, "<>Closing CF") ))+ _xlfn.IFNA(O161, 0)} -> 0 | AG40: =X40+Y40+Z40+AA40+AB40+AC40+AD40+AF40+AE40 -> 873119.97 | AH40: =(SUMIF(Table14[Party],S40,Table14[Credit]))+_xlfn.IFNA(Q161,0) -> 628000 | AI40: =AG40-AH40 -> 245119.97
S41: 0 | T41: {=_xlfn.BYROW(B93,_xlfn.LAMBDA(_xlpm.party,SUMIFS(ledger!G:G,ledger!B:B,_xlpm.party,ledger!E:E,"<>*RD*")))+_xlfn.IFNA(C162,0)} -> 0 | U41: {=_xlfn.BYROW(B93, _xlfn.LAMBDA(_xlpm.party, SUMIFS(ledger!G:G, ledger!B:B, _xlpm.party, ledger!E:E, "<>*RD*") / 1.0936 ))+_xlfn.IFNA(D162,0)} -> 0 | V41: {=(_xlfn.BYROW(B93,_xlfn.LAMBDA(_xlpm.party,SUMIFS(ledger!G:G,ledger!B:B,_xlpm.party,ledger!E:E,"<>*RD*",ledger!D:D,"Chamki")+SUMIFS(ledger!G:G, ledger!B:B, _xlpm.party, ledger!E:E, "<>*RD*", ledger!D:D, "Crinkle")))/1.0936)+_xlfn.IFNA(E162,0)} -> 0 | W41: {=(_xlfn.BYROW(B93,_xlfn.LAMBDA(_xlpm.party,SUMIFS(ledger!G:G,ledger!B:B,_xlpm.party,ledger!E:E,"<>*RD*",ledger!D:D,"Silky")))/1.0936)+_xlfn.IFNA(F162,0)} -> 0 | X41: {=(_xlfn.BYROW(B93,_xlfn.LAMBDA(_xlpm.party, (SUMIFS(ledger!J:J,ledger!B:B,_xlpm.party,ledger!E:E,"<>*RD*",ledger!D:D,"Chamki",ledger!C:C,"<>Closing CF")+ SUMIFS(ledger!J:J,ledger!B:B,_xlpm.party,ledger!E:E,"<>*RD*",ledger!D:D,"Crinkle",ledger!C:C,"<>Closing CF") )+_xlfn.IFNA(G162,0))))} -> 0 | Y41: {=_xlfn.BYROW(B93, _xlfn.LAMBDA(_xlpm.party, SUMIFS(ledger!J:J, ledger!B:B, _xlpm.party, ledger!E:E, "<>*RD*", ledger!D:D, "Silky", ledger!C:C, "<>Closing CF") )) + _xlfn.IFNA(H162, 0)} -> 0 | Z41: {=_xlfn.BYROW(B93, _xlfn.LAMBDA(_xlpm.party, SUMIFS(ledger!J:J, ledger!B:B, _xlpm.party, ledger!E:E, "<>*RD*", ledger!D:D, "Slub", ledger!C:C, "<>Closing CF") ))+ _xlfn.IFNA(I162, 0)} -> 0 | AA41: {=_xlfn.BYROW(B93, _xlfn.LAMBDA(_xlpm.party, SUMIFS(ledger!J:J, ledger!B:B, _xlpm.party, ledger!E:E, "<>*RD*", ledger!D:D, "Satin", ledger!C:C, "<>Closing CF") ))+ _xlfn.IFNA(J162, 0)} -> 0 | AB41: {=_xlfn.BYROW(B93, _xlfn.LAMBDA(_xlpm.party, SUMIFS(ledger!J:J, ledger!B:B, _xlpm.party, ledger!E:E, "<>*RD*", ledger!D:D, "Black-Chamki", ledger!C:C, "<>Closing CF") ))+ _xlfn.IFNA(K162, 0)} -> 0 | AC41: {=_xlfn.BYROW(B93, _xlfn.LAMBDA(_xlpm.party, SUMIFS(ledger!J:J, ledger!B:B, _xlpm.party, ledger!E:E, "<>*RD*", ledger!D:D, "Kataan", ledger!C:C, "<>Closing CF") ))+ _xlfn.IFNA(L162, 0)} -> 0 | AD41: {=_xlfn.BYROW(B93, _xlfn.LAMBDA(_xlpm.party, SUMIFS(ledger!J:J, ledger!B:B, _xlpm.party, ledger!E:E, "<>*RD*", ledger!D:D, "Munaar", ledger!C:C, "<>Closing CF") ))+ _xlfn.IFNA(M162, 0)} -> 0 | AE41: {=_xlfn.BYROW(B93, _xlfn.LAMBDA(_xlpm.party, SUMIFS(ledger!J:J, ledger!B:B, _xlpm.party, ledger!E:E, "<>*RD*", ledger!D:D, "Super Kataan", ledger!C:C, "<>Closing CF") ))+ _xlfn.IFNA(N162, 0)} -> 0 | AF41: {=_xlfn.BYROW(B93, _xlfn.LAMBDA(_xlpm.party, SUMIFS(ledger!J:J, ledger!B:B, _xlpm.party, ledger!E:E, "<>*RD*", ledger!D:D, "Custom", ledger!C:C, "<>Closing CF") ))+ _xlfn.IFNA(O162, 0)} -> 0 | AG41: =X41+Y41+Z41+AA41+AB41+AC41+AD41+AF41+AE41 -> 0 | AH41: =(SUMIF(Table14[Party],S41,Table14[Credit]))+_xlfn.IFNA(Q162,0) -> 0 | AI41: =AG41-AH41 -> 0
S42: Moeez badshah | T42: {=_xlfn.BYROW(B94,_xlfn.LAMBDA(_xlpm.party,SUMIFS(ledger!G:G,ledger!B:B,_xlpm.party,ledger!E:E,"<>*RD*")))+_xlfn.IFNA(C163,0)} -> 168047 | U42: {=_xlfn.BYROW(B94, _xlfn.LAMBDA(_xlpm.party, SUMIFS(ledger!G:G, ledger!B:B, _xlpm.party, ledger!E:E, "<>*RD*") / 1.0936 ))+_xlfn.IFNA(D163,0)} -> 153664.05 | V42: {=(_xlfn.BYROW(B94,_xlfn.LAMBDA(_xlpm.party,SUMIFS(ledger!G:G,ledger!B:B,_xlpm.party,ledger!E:E,"<>*RD*",ledger!D:D,"Chamki")+SUMIFS(ledger!G:G, ledger!B:B, _xlpm.party, ledger!E:E, "<>*RD*", ledger!D:D, "Crinkle")))/1.0936)+_xlfn.IFNA(E163,0)} -> 57385.699 | W42: {=(_xlfn.BYROW(B94,_xlfn.LAMBDA(_xlpm.party,SUMIFS(ledger!G:G,ledger!B:B,_xlpm.party,ledger!E:E,"<>*RD*",ledger!D:D,"Silky")))/1.0936)+_xlfn.IFNA(F163,0)} -> 96278.347 | X42: {=(_xlfn.BYROW(B94,_xlfn.LAMBDA(_xlpm.party, (SUMIFS(ledger!J:J,ledger!B:B,_xlpm.party,ledger!E:E,"<>*RD*",ledger!D:D,"Chamki",ledger!C:C,"<>Closing CF")+ SUMIFS(ledger!J:J,ledger!B:B,_xlpm.party,ledger!E:E,"<>*RD*",ledger!D:D,"Crinkle",ledger!C:C,"<>Closing CF") )+_xlfn.IFNA(G163,0))))} -> 573856.99 | Y42: {=_xlfn.BYROW(B94, _xlfn.LAMBDA(_xlpm.party, SUMIFS(ledger!J:J, ledger!B:B, _xlpm.party, ledger!E:E, "<>*RD*", ledger!D:D, "Silky", ledger!C:C, "<>Closing CF") )) + _xlfn.IFNA(H163, 0)} -> 1155340.2 | Z42: {=_xlfn.BYROW(B94, _xlfn.LAMBDA(_xlpm.party, SUMIFS(ledger!J:J, ledger!B:B, _xlpm.party, ledger!E:E, "<>*RD*", ledger!D:D, "Slub", ledger!C:C, "<>Closing CF") ))+ _xlfn.IFNA(I163, 0)} -> 0 | AA42: {=_xlfn.BYROW(B94, _xlfn.LAMBDA(_xlpm.party, SUMIFS(ledger!J:J, ledger!B:B, _xlpm.party, ledger!E:E, "<>*RD*", ledger!D:D, "Satin", ledger!C:C, "<>Closing CF") ))+ _xlfn.IFNA(J163, 0)} -> 0 | AB42: {=_xlfn.BYROW(B94, _xlfn.LAMBDA(_xlpm.party, SUMIFS(ledger!J:J, ledger!B:B, _xlpm.party, ledger!E:E, "<>*RD*", ledger!D:D, "Black-Chamki", ledger!C:C, "<>Closing CF") ))+ _xlfn.IFNA(K163, 0)} -> 0 | AC42: {=_xlfn.BYROW(B94, _xlfn.LAMBDA(_xlpm.party, SUMIFS(ledger!J:J, ledger!B:B, _xlpm.party, ledger!E:E, "<>*RD*", ledger!D:D, "Kataan", ledger!C:C, "<>Closing CF") ))+ _xlfn.IFNA(L163, 0)} -> 0 | AD42: {=_xlfn.BYROW(B94, _xlfn.LAMBDA(_xlpm.party, SUMIFS(ledger!J:J, ledger!B:B, _xlpm.party, ledger!E:E, "<>*RD*", ledger!D:D, "Munaar", ledger!C:C, "<>Closing CF") ))+ _xlfn.IFNA(M163, 0)} -> 0 | AE42: {=_xlfn.BYROW(B94, _xlfn.LAMBDA(_xlpm.party, SUMIFS(ledger!J:J, ledger!B:B, _xlpm.party, ledger!E:E, "<>*RD*", ledger!D:D, "Super Kataan", ledger!C:C, "<>Closing CF") ))+ _xlfn.IFNA(N163, 0)} -> 0 | AF42: {=_xlfn.BYROW(B94, _xlfn.LAMBDA(_xlpm.party, SUMIFS(ledger!J:J, ledger!B:B, _xlpm.party, ledger!E:E, "<>*RD*", ledger!D:D, "Custom", ledger!C:C, "<>Closing CF") ))+ _xlfn.IFNA(O163, 0)} -> 0 | AG42: =X42+Y42+Z42+AA42+AB42+AC42+AD42+AF42+AE42 -> 1729197.1 | AH42: =(SUMIF(Table14[Party],S42,Table14[Credit]))+_xlfn.IFNA(Q163,0) -> 1742500 | AI42: =AG42-AH42 -> -13302.853
S43: Bablu | T43: {=_xlfn.BYROW(B95,_xlfn.LAMBDA(_xlpm.party,SUMIFS(ledger!G:G,ledger!B:B,_xlpm.party,ledger!E:E,"<>*RD*")))+_xlfn.IFNA(C164,0)} -> 9579 | U43: {=_xlfn.BYROW(B95, _xlfn.LAMBDA(_xlpm.party, SUMIFS(ledger!G:G, ledger!B:B, _xlpm.party, ledger!E:E, "<>*RD*") / 1.0936 ))+_xlfn.IFNA(D164,0)} -> 8759.1441 | V43: {=(_xlfn.BYROW(B95,_xlfn.LAMBDA(_xlpm.party,SUMIFS(ledger!G:G,ledger!B:B,_xlpm.party,ledger!E:E,"<>*RD*",ledger!D:D,"Chamki")+SUMIFS(ledger!G:G, ledger!B:B, _xlpm.party, ledger!E:E, "<>*RD*", ledger!D:D, "Crinkle")))/1.0936)+_xlfn.IFNA(E164,0)} -> 0 | W43: {=(_xlfn.BYROW(B95,_xlfn.LAMBDA(_xlpm.party,SUMIFS(ledger!G:G,ledger!B:B,_xlpm.party,ledger!E:E,"<>*RD*",ledger!D:D,"Silky")))/1.0936)+_xlfn.IFNA(F164,0)} -> 8759.1441 | X43: {=(_xlfn.BYROW(B95,_xlfn.LAMBDA(_xlpm.party, (SUMIFS(ledger!J:J,ledger!B:B,_xlpm.party,ledger!E:E,"<>*RD*",ledger!D:D,"Chamki",ledger!C:C,"<>Closing CF")+ SUMIFS(ledger!J:J,ledger!B:B,_xlpm.party,ledger!E:E,"<>*RD*",ledger!D:D,"Crinkle",ledger!C:C,"<>Closing CF") )+_xlfn.IFNA(G164,0))))} -> 0 | Y43: {=_xlfn.BYROW(B95, _xlfn.LAMBDA(_xlpm.party, SUMIFS(ledger!J:J, ledger!B:B, _xlpm.party, ledger!E:E, "<>*RD*", ledger!D:D, "Silky", ledger!C:C, "<>Closing CF") )) + _xlfn.IFNA(H164, 0)} -> 105109.73 | Z43: {=_xlfn.BYROW(B95, _xlfn.LAMBDA(_xlpm.party, SUMIFS(ledger!J:J, ledger!B:B, _xlpm.party, ledger!E:E, "<>*RD*", ledger!D:D, "Slub", ledger!C:C, "<>Closing CF") ))+ _xlfn.IFNA(I164, 0)} -> 0 | AA43: {=_xlfn.BYROW(B95, _xlfn.LAMBDA(_xlpm.party, SUMIFS(ledger!J:J, ledger!B:B, _xlpm.party, ledger!E:E, "<>*RD*", ledger!D:D, "Satin", ledger!C:C, "<>Closing CF") ))+ _xlfn.IFNA(J164, 0)} -> 0 | AB43: {=_xlfn.BYROW(B95, _xlfn.LAMBDA(_xlpm.party, SUMIFS(ledger!J:J, ledger!B:B, _xlpm.party, ledger!E:E, "<>*RD*", ledger!D:D, "Black-Chamki", ledger!C:C, "<>Closing CF") ))+ _xlfn.IFNA(K164, 0)} -> 0 | AC43: {=_xlfn.BYROW(B95, _xlfn.LAMBDA(_xlpm.party, SUMIFS(ledger!J:J, ledger!B:B, _xlpm.party, ledger!E:E, "<>*RD*", ledger!D:D, "Kataan", ledger!C:C, "<>Closing CF") ))+ _xlfn.IFNA(L164, 0)} -> 0 | AD43: {=_xlfn.BYROW(B95, _xlfn.LAMBDA(_xlpm.party, SUMIFS(ledger!J:J, ledger!B:B, _xlpm.party, ledger!E:E, "<>*RD*", ledger!D:D, "Munaar", ledger!C:C, "<>Closing CF") ))+ _xlfn.IFNA(M164, 0)} -> 0 | AE43: {=_xlfn.BYROW(B95, _xlfn.LAMBDA(_xlpm.party, SUMIFS(ledger!J:J, ledger!B:B, _xlpm.party, ledger!E:E, "<>*RD*", ledger!D:D, "Super Kataan", ledger!C:C, "<>Closing CF") ))+ _xlfn.IFNA(N164, 0)} -> 0 | AF43: {=_xlfn.BYROW(B95, _xlfn.LAMBDA(_xlpm.party, SUMIFS(ledger!J:J, ledger!B:B, _xlpm.party, ledger!E:E, "<>*RD*", ledger!D:D, "Custom", ledger!C:C, "<>Closing CF") ))+ _xlfn.IFNA(O164, 0)} -> 0 | AG43: =X43+Y43+Z43+AA43+AB43+AC43+AD43+AF43+AE43 -> 105109.73 | AH43: =(SUMIF(Table14[Party],S43,Table14[Credit]))+_xlfn.IFNA(Q164,0) -> 100000 | AI43: =AG43-AH43 -> 5109.7293
S44: Sheikh Naveed | T44: {=_xlfn.BYROW(B96,_xlfn.LAMBDA(_xlpm.party,SUMIFS(ledger!G:G,ledger!B:B,_xlpm.party,ledger!E:E,"<>*RD*")))+_xlfn.IFNA(C165,0)} -> 23123 | U44: {=_xlfn.BYROW(B96, _xlfn.LAMBDA(_xlpm.party, SUMIFS(ledger!G:G, ledger!B:B, _xlpm.party, ledger!E:E, "<>*RD*") / 1.0936 ))+_xlfn.IFNA(D165,0)} -> 21143.928 | V44: {=(_xlfn.BYROW(B96,_xlfn.LAMBDA(_xlpm.party,SUMIFS(ledger!G:G,ledger!B:B,_xlpm.party,ledger!E:E,"<>*RD*",ledger!D:D,"Chamki")+SUMIFS(ledger!G:G, ledger!B:B, _xlpm.party, ledger!E:E, "<>*RD*", ledger!D:D, "Crinkle")))/1.0936)+_xlfn.IFNA(E165,0)} -> 21143.928 | W44: {=(_xlfn.BYROW(B96,_xlfn.LAMBDA(_xlpm.party,SUMIFS(ledger!G:G,ledger!B:B,_xlpm.party,ledger!E:E,"<>*RD*",ledger!D:D,"Silky")))/1.0936)+_xlfn.IFNA(F165,0)} -> 0 | X44: {=(_xlfn.BYROW(B96,_xlfn.LAMBDA(_xlpm.party, (SUMIFS(ledger!J:J,ledger!B:B,_xlpm.party,ledger!E:E,"<>*RD*",ledger!D:D,"Chamki",ledger!C:C,"<>Closing CF")+ SUMIFS(ledger!J:J,ledger!B:B,_xlpm.party,ledger!E:E,"<>*RD*",ledger!D:D,"Crinkle",ledger!C:C,"<>Closing CF") )+_xlfn.IFNA(G165,0))))} -> 211439.28 | Y44: {=_xlfn.BYROW(B96, _xlfn.LAMBDA(_xlpm.party, SUMIFS(ledger!J:J, ledger!B:B, _xlpm.party, ledger!E:E, "<>*RD*", ledger!D:D, "Silky", ledger!C:C, "<>Closing CF") )) + _xlfn.IFNA(H165, 0)} -> 0 | Z44: {=_xlfn.BYROW(B96, _xlfn.LAMBDA(_xlpm.party, SUMIFS(ledger!J:J, ledger!B:B, _xlpm.party, ledger!E:E, "<>*RD*", ledger!D:D, "Slub", ledger!C:C, "<>Closing CF") ))+ _xlfn.IFNA(I165, 0)} -> 0 | AA44: {=_xlfn.BYROW(B96, _xlfn.LAMBDA(_xlpm.party, SUMIFS(ledger!J:J, ledger!B:B, _xlpm.party, ledger!E:E, "<>*RD*", ledger!D:D, "Satin", ledger!C:C, "<>Closing CF") ))+ _xlfn.IFNA(J165, 0)} -> 0 | AB44: {=_xlfn.BYROW(B96, _xlfn.LAMBDA(_xlpm.party, SUMIFS(ledger!J:J, ledger!B:B, _xlpm.party, ledger!E:E, "<>*RD*", ledger!D:D, "Black-Chamki", ledger!C:C, "<>Closing CF") ))+ _xlfn.IFNA(K165, 0)} -> 0 | AC44: {=_xlfn.BYROW(B96, _xlfn.LAMBDA(_xlpm.party, SUMIFS(ledger!J:J, ledger!B:B, _xlpm.party, ledger!E:E, "<>*RD*", ledger!D:D, "Kataan", ledger!C:C, "<>Closing CF") ))+ _xlfn.IFNA(L165, 0)} -> 0 | AD44: {=_xlfn.BYROW(B96, _xlfn.LAMBDA(_xlpm.party, SUMIFS(ledger!J:J, ledger!B:B, _xlpm.party, ledger!E:E, "<>*RD*", ledger!D:D, "Munaar", ledger!C:C, "<>Closing CF") ))+ _xlfn.IFNA(M165, 0)} -> 0 | AE44: {=_xlfn.BYROW(B96, _xlfn.LAMBDA(_xlpm.party, SUMIFS(ledger!J:J, ledger!B:B, _xlpm.party, ledger!E:E, "<>*RD*", ledger!D:D, "Super Kataan", ledger!C:C, "<>Closing CF") ))+ _xlfn.IFNA(N165, 0)} -> 0 | AF44: {=_xlfn.BYROW(B96, _xlfn.LAMBDA(_xlpm.party, SUMIFS(ledger!J:J, ledger!B:B, _xlpm.party, ledger!E:E, "<>*RD*", ledger!D:D, "Custom", ledger!C:C, "<>Closing CF") ))+ _xlfn.IFNA(O165, 0)} -> 0 | AG44: =X44+Y44+Z44+AA44+AB44+AC44+AD44+AF44+AE44 -> 211439.28 | AH44: =(SUMIF(Table14[Party],S44,Table14[Credit]))+_xlfn.IFNA(Q165,0) -> 204900 | AI44: =AG44-AH44 -> 6539.2831
S45: malik salman | T45: {=_xlfn.BYROW(B97,_xlfn.LAMBDA(_xlpm.party,SUMIFS(ledger!G:G,ledger!B:B,_xlpm.party,ledger!E:E,"<>*RD*")))+_xlfn.IFNA(C166,0)} -> 14194 | U45: {=_xlfn.BYROW(B97, _xlfn.LAMBDA(_xlpm.party, SUMIFS(ledger!G:G, ledger!B:B, _xlpm.party, ledger!E:E, "<>*RD*") / 1.0936 ))+_xlfn.IFNA(D166,0)} -> 12979.151 | V45: {=(_xlfn.BYROW(B97,_xlfn.LAMBDA(_xlpm.party,SUMIFS(ledger!G:G,ledger!B:B,_xlpm.party,ledger!E:E,"<>*RD*",ledger!D:D,"Chamki")+SUMIFS(ledger!G:G, ledger!B:B, _xlpm.party, ledger!E:E, "<>*RD*", ledger!D:D, "Crinkle")))/1.0936)+_xlfn.IFNA(E166,0)} -> 0 | W45: {=(_xlfn.BYROW(B97,_xlfn.LAMBDA(_xlpm.party,SUMIFS(ledger!G:G,ledger!B:B,_xlpm.party,ledger!E:E,"<>*RD*",ledger!D:D,"Silky")))/1.0936)+_xlfn.IFNA(F166,0)} -> 0 | X45: {=(_xlfn.BYROW(B97,_xlfn.LAMBDA(_xlpm.party, (SUMIFS(ledger!J:J,ledger!B:B,_xlpm.party,ledger!E:E,"<>*RD*",ledger!D:D,"Chamki",ledger!C:C,"<>Closing CF")+ SUMIFS(ledger!J:J,ledger!B:B,_xlpm.party,ledger!E:E,"<>*RD*",ledger!D:D,"Crinkle",ledger!C:C,"<>Closing CF") )+_xlfn.IFNA(G166,0))))} -> 0 | Y45: {=_xlfn.BYROW(B97, _xlfn.LAMBDA(_xlpm.party, SUMIFS(ledger!J:J, ledger!B:B, _xlpm.party, ledger!E:E, "<>*RD*", ledger!D:D, "Silky", ledger!C:C, "<>Closing CF") )) + _xlfn.IFNA(H166, 0)} -> 0 | Z45: {=_xlfn.BYROW(B97, _xlfn.LAMBDA(_xlpm.party, SUMIFS(ledger!J:J, ledger!B:B, _xlpm.party, ledger!E:E, "<>*RD*", ledger!D:D, "Slub", ledger!C:C, "<>Closing CF") ))+ _xlfn.IFNA(I166, 0)} -> 0 | AA45: {=_xlfn.BYROW(B97, _xlfn.LAMBDA(_xlpm.party, SUMIFS(ledger!J:J, ledger!B:B, _xlpm.party, ledger!E:E, "<>*RD*", ledger!D:D, "Satin", ledger!C:C, "<>Closing CF") ))+ _xlfn.IFNA(J166, 0)} -> 0 | AB45: {=_xlfn.BYROW(B97, _xlfn.LAMBDA(_xlpm.party, SUMIFS(ledger!J:J, ledger!B:B, _xlpm.party, ledger!E:E, "<>*RD*", ledger!D:D, "Black-Chamki", ledger!C:C, "<>Closing CF") ))+ _xlfn.IFNA(K166, 0)} -> 0 | AC45: {=_xlfn.BYROW(B97, _xlfn.LAMBDA(_xlpm.party, SUMIFS(ledger!J:J, ledger!B:B, _xlpm.party, ledger!E:E, "<>*RD*", ledger!D:D, "Kataan", ledger!C:C, "<>Closing CF") ))+ _xlfn.IFNA(L166, 0)} -> 0 | AD45: {=_xlfn.BYROW(B97, _xlfn.LAMBDA(_xlpm.party, SUMIFS(ledger!J:J, ledger!B:B, _xlpm.party, ledger!E:E, "<>*RD*", ledger!D:D, "Munaar", ledger!C:C, "<>Closing CF") ))+ _xlfn.IFNA(M166, 0)} -> 0 | AE45: {=_xlfn.BYROW(B97, _xlfn.LAMBDA(_xlpm.party, SUMIFS(ledger!J:J, ledger!B:B, _xlpm.party, ledger!E:E, "<>*RD*", ledger!D:D, "Super Kataan", ledger!C:C, "<>Closing CF") ))+ _xlfn.IFNA(N166, 0)} -> 194687.27 | AF45: {=_xlfn.BYROW(B97, _xlfn.LAMBDA(_xlpm.party, SUMIFS(ledger!J:J, ledger!B:B, _xlpm.party, ledger!E:E, "<>*RD*", ledger!D:D, "Custom", ledger!C:C, "<>Closing CF") ))+ _xlfn.IFNA(O166, 0)} -> 0 | AG45: =X45+Y45+Z45+AA45+AB45+AC45+AD45+AF45+AE45 -> 194687.27 | AH45: =(SUMIF(Table14[Party],S45,Table14[Credit]))+_xlfn.IFNA(Q166,0) -> 194000 | AI45: =AG45-AH45 -> 687.2714
S46: Rehan Butt | T46: {=_xlfn.BYROW(B98,_xlfn.LAMBDA(_xlpm.party,SUMIFS(ledger!G:G,ledger!B:B,_xlpm.party,ledger!E:E,"<>*RD*")))+_xlfn.IFNA(C167,0)} -> 53438 | U46: {=_xlfn.BYROW(B98, _xlfn.LAMBDA(_xlpm.party, SUMIFS(ledger!G:G, ledger!B:B, _xlpm.party, ledger!E:E, "<>*RD*") / 1.0936 ))+_xlfn.IFNA(D167,0)} -> 48864.301 | V46: {=(_xlfn.BYROW(B98,_xlfn.LAMBDA(_xlpm.party,SUMIFS(ledger!G:G,ledger!B:B,_xlpm.party,ledger!E:E,"<>*RD*",ledger!D:D,"Chamki")+SUMIFS(ledger!G:G, ledger!B:B, _xlpm.party, ledger!E:E, "<>*RD*", ledger!D:D, "Crinkle")))/1.0936)+_xlfn.IFNA(E167,0)} -> 48864.301 | W46: {=(_xlfn.BYROW(B98,_xlfn.LAMBDA(_xlpm.party,SUMIFS(ledger!G:G,ledger!B:B,_xlpm.party,ledger!E:E,"<>*RD*",ledger!D:D,"Silky")))/1.0936)+_xlfn.IFNA(F167,0)} -> 0 | X46: {=(_xlfn.BYROW(B98,_xlfn.LAMBDA(_xlpm.party, (SUMIFS(ledger!J:J,ledger!B:B,_xlpm.party,ledger!E:E,"<>*RD*",ledger!D:D,"Chamki",ledger!C:C,"<>Closing CF")+ SUMIFS(ledger!J:J,ledger!B:B,_xlpm.party,ledger!E:E,"<>*RD*",ledger!D:D,"Crinkle",ledger!C:C,"<>Closing CF") )+_xlfn.IFNA(G167,0))))} -> 488643.01 | Y46: {=_xlfn.BYROW(B98, _xlfn.LAMBDA(_xlpm.party, SUMIFS(ledger!J:J, ledger!B:B, _xlpm.party, ledger!E:E, "<>*RD*", ledger!D:D, "Silky", ledger!C:C, "<>Closing CF") )) + _xlfn.IFNA(H167, 0)} -> 0 | Z46: {=_xlfn.BYROW(B98, _xlfn.LAMBDA(_xlpm.party, SUMIFS(ledger!J:J, ledger!B:B, _xlpm.party, ledger!E:E, "<>*RD*", ledger!D:D, "Slub", ledger!C:C, "<>Closing CF") ))+ _xlfn.IFNA(I167, 0)} -> 0 | AA46: {=_xlfn.BYROW(B98, _xlfn.LAMBDA(_xlpm.party, SUMIFS(ledger!J:J, ledger!B:B, _xlpm.party, ledger!E:E, "<>*RD*", ledger!D:D, "Satin", ledger!C:C, "<>Closing CF") ))+ _xlfn.IFNA(J167, 0)} -> 0 | AB46: {=_xlfn.BYROW(B98, _xlfn.LAMBDA(_xlpm.party, SUMIFS(ledger!J:J, ledger!B:B, _xlpm.party, ledger!E:E, "<>*RD*", ledger!D:D, "Black-Chamki", ledger!C:C, "<>Closing CF") ))+ _xlfn.IFNA(K167, 0)} -> 0 | AC46: {=_xlfn.BYROW(B98, _xlfn.LAMBDA(_xlpm.party, SUMIFS(ledger!J:J, ledger!B:B, _xlpm.party, ledger!E:E, "<>*RD*", ledger!D:D, "Kataan", ledger!C:C, "<>Closing CF") ))+ _xlfn.IFNA(L167, 0)} -> 0 | AD46: {=_xlfn.BYROW(B98, _xlfn.LAMBDA(_xlpm.party, SUMIFS(ledger!J:J, ledger!B:B, _xlpm.party, ledger!E:E, "<>*RD*", ledger!D:D, "Munaar", ledger!C:C, "<>Closing CF") ))+ _xlfn.IFNA(M167, 0)} -> 0 | AE46: {=_xlfn.BYROW(B98, _xlfn.LAMBDA(_xlpm.party, SUMIFS(ledger!J:J, ledger!B:B, _xlpm.party, ledger!E:E, "<>*RD*", ledger!D:D, "Super Kataan", ledger!C:C, "<>Closing CF") ))+ _xlfn.IFNA(N167, 0)} -> 0 | AF46: {=_xlfn.BYROW(B98, _xlfn.LAMBDA(_xlpm.party, SUMIFS(ledger!J:J, ledger!B:B, _xlpm.party, ledger!E:E, "<>*RD*", ledger!D:D, "Custom", ledger!C:C, "<>Closing CF") ))+ _xlfn.IFNA(O167, 0)} -> 0 | AG46: =X46+Y46+Z46+AA46+AB46+AC46+AD46+AF46+AE46 -> 488643.01 | AH46: =(SUMIF(Table14[Party],S46,Table14[Credit]))+_xlfn.IFNA(Q167,0) -> 488600 | AI46: =AG46-AH46 -> 43.013899
S47: Usama Nadeem | T47: {=_xlfn.BYROW(B99,_xlfn.LAMBDA(_xlpm.party,SUMIFS(ledger!G:G,ledger!B:B,_xlpm.party,ledger!E:E,"<>*RD*")))+_xlfn.IFNA(C168,0)} -> 53747 | U47: {=_xlfn.BYROW(B99, _xlfn.LAMBDA(_xlpm.party, SUMIFS(ledger!G:G, ledger!B:B, _xlpm.party, ledger!E:E, "<>*RD*") / 1.0936 ))+_xlfn.IFNA(D168,0)} -> 49146.854 | V47: {=(_xlfn.BYROW(B99,_xlfn.LAMBDA(_xlpm.party,SUMIFS(ledger!G:G,ledger!B:B,_xlpm.party,ledger!E:E,"<>*RD*",ledger!D:D,"Chamki")+SUMIFS(ledger!G:G, ledger!B:B, _xlpm.party, ledger!E:E, "<>*RD*", ledger!D:D, "Crinkle")))/1.0936)+_xlfn.IFNA(E168,0)} -> 49146.854 | W47: {=(_xlfn.BYROW(B99,_xlfn.LAMBDA(_xlpm.party,SUMIFS(ledger!G:G,ledger!B:B,_xlpm.party,ledger!E:E,"<>*RD*",ledger!D:D,"Silky")))/1.0936)+_xlfn.IFNA(F168,0)} -> 0 | X47: {=(_xlfn.BYROW(B99,_xlfn.LAMBDA(_xlpm.party, (SUMIFS(ledger!J:J,ledger!B:B,_xlpm.party,ledger!E:E,"<>*RD*",ledger!D:D,"Chamki",ledger!C:C,"<>Closing CF")+ SUMIFS(ledger!J:J,ledger!B:B,_xlpm.party,ledger!E:E,"<>*RD*",ledger!D:D,"Crinkle",ledger!C:C,"<>Closing CF") )+_xlfn.IFNA(G168,0))))} -> 491468.54 | Y47: {=_xlfn.BYROW(B99, _xlfn.LAMBDA(_xlpm.party, SUMIFS(ledger!J:J, ledger!B:B, _xlpm.party, ledger!E:E, "<>*RD*", ledger!D:D, "Silky", ledger!C:C, "<>Closing CF") )) + _xlfn.IFNA(H168, 0)} -> 0 | Z47: {=_xlfn.BYROW(B99, _xlfn.LAMBDA(_xlpm.party, SUMIFS(ledger!J:J, ledger!B:B, _xlpm.party, ledger!E:E, "<>*RD*", ledger!D:D, "Slub", ledger!C:C, "<>Closing CF") ))+ _xlfn.IFNA(I168, 0)} -> 0 | AA47: {=_xlfn.BYROW(B99, _xlfn.LAMBDA(_xlpm.party, SUMIFS(ledger!J:J, ledger!B:B, _xlpm.party, ledger!E:E, "<>*RD*", ledger!D:D, "Satin", ledger!C:C, "<>Closing CF") ))+ _xlfn.IFNA(J168, 0)} -> 0 | AB47: {=_xlfn.BYROW(B99, _xlfn.LAMBDA(_xlpm.party, SUMIFS(ledger!J:J, ledger!B:B, _xlpm.party, ledger!E:E, "<>*RD*", ledger!D:D, "Black-Chamki", ledger!C:C, "<>Closing CF") ))+ _xlfn.IFNA(K168, 0)} -> 0 | AC47: {=_xlfn.BYROW(B99, _xlfn.LAMBDA(_xlpm.party, SUMIFS(ledger!J:J, ledger!B:B, _xlpm.party, ledger!E:E, "<>*RD*", ledger!D:D, "Kataan", ledger!C:C, "<>Closing CF") ))+ _xlfn.IFNA(L168, 0)} -> 0 | AD47: {=_xlfn.BYROW(B99, _xlfn.LAMBDA(_xlpm.party, SUMIFS(ledger!J:J, ledger!B:B, _xlpm.party, ledger!E:E, "<>*RD*", ledger!D:D, "Munaar", ledger!C:C, "<>Closing CF") ))+ _xlfn.IFNA(M168, 0)} -> 0 | AE47: {=_xlfn.BYROW(B99, _xlfn.LAMBDA(_xlpm.party, SUMIFS(ledger!J:J, ledger!B:B, _xlpm.party, ledger!E:E, "<>*RD*", ledger!D:D, "Super Kataan", ledger!C:C, "<>Closing CF") ))+ _xlfn.IFNA(N168, 0)} -> 0 | AF47: {=_xlfn.BYROW(B99, _xlfn.LAMBDA(_xlpm.party, SUMIFS(ledger!J:J, ledger!B:B, _xlpm.party, ledger!E:E, "<>*RD*", ledger!D:D, "Custom", ledger!C:C, "<>Closing CF") ))+ _xlfn.IFNA(O168, 0)} -> 0 | AG47: =X47+Y47+Z47+AA47+AB47+AC47+AD47+AF47+AE47 -> 491468.54 | AH47: =(SUMIF(Table14[Party],S47,Table14[Credit]))+_xlfn.IFNA(Q168,0) -> 300000 | AI47: =AG47-AH47 -> 191468.54
S48: Abdul Wahid | T48: {=_xlfn.BYROW(B100,_xlfn.LAMBDA(_xlpm.party,SUMIFS(ledger!G:G,ledger!B:B,_xlpm.party,ledger!E:E,"<>*RD*")))+_xlfn.IFNA(C169,0)} -> 35292 | U48: {=_xlfn.BYROW(B100, _xlfn.LAMBDA(_xlpm.party, SUMIFS(ledger!G:G, ledger!B:B, _xlpm.party, ledger!E:E, "<>*RD*") / 1.0936 ))+_xlfn.IFNA(D169,0)} -> 32271.397 | V48: {=(_xlfn.BYROW(B100,_xlfn.LAMBDA(_xlpm.party,SUMIFS(ledger!G:G,ledger!B:B,_xlpm.party,ledger!E:E,"<>*RD*",ledger!D:D,"Chamki")+SUMIFS(ledger!G:G, ledger!B:B, _xlpm.party, ledger!E:E, "<>*RD*", ledger!D:D, "Crinkle")))/1.0936)+_xlfn.IFNA(E169,0)} -> 0 | W48: {=(_xlfn.BYROW(B100,_xlfn.LAMBDA(_xlpm.party,SUMIFS(ledger!G:G,ledger!B:B,_xlpm.party,ledger!E:E,"<>*RD*",ledger!D:D,"Silky")))/1.0936)+_xlfn.IFNA(F169,0)} -> 32271.397 | X48: {=(_xlfn.BYROW(B100,_xlfn.LAMBDA(_xlpm.party, (SUMIFS(ledger!J:J,ledger!B:B,_xlpm.party,ledger!E:E,"<>*RD*",ledger!D:D,"Chamki",ledger!C:C,"<>Closing CF")+ SUMIFS(ledger!J:J,ledger!B:B,_xlpm.party,ledger!E:E,"<>*RD*",ledger!D:D,"Crinkle",ledger!C:C,"<>Closing CF") )+_xlfn.IFNA(G169,0))))} -> 0 | Y48: {=_xlfn.BYROW(B100, _xlfn.LAMBDA(_xlpm.party, SUMIFS(ledger!J:J, ledger!B:B, _xlpm.party, ledger!E:E, "<>*RD*", ledger!D:D, "Silky", ledger!C:C, "<>Closing CF") )) + _xlfn.IFNA(H169, 0)} -> 387256.77 | Z48: {=_xlfn.BYROW(B100, _xlfn.LAMBDA(_xlpm.party, SUMIFS(ledger!J:J, ledger!B:B, _xlpm.party, ledger!E:E, "<>*RD*", ledger!D:D, "Slub", ledger!C:C, "<>Closing CF") ))+ _xlfn.IFNA(I169, 0)} -> 0 | AA48: {=_xlfn.BYROW(B100, _xlfn.LAMBDA(_xlpm.party, SUMIFS(ledger!J:J, ledger!B:B, _xlpm.party, ledger!E:E, "<>*RD*", ledger!D:D, "Satin", ledger!C:C, "<>Closing CF") ))+ _xlfn.IFNA(J169, 0)} -> 0 | AB48: {=_xlfn.BYROW(B100, _xlfn.LAMBDA(_xlpm.party, SUMIFS(ledger!J:J, ledger!B:B, _xlpm.party, ledger!E:E, "<>*RD*", ledger!D:D, "Black-Chamki", ledger!C:C, "<>Closing CF") ))+ _xlfn.IFNA(K169, 0)} -> 0 | AC48: {=_xlfn.BYROW(B100, _xlfn.LAMBDA(_xlpm.party, SUMIFS(ledger!J:J, ledger!B:B, _xlpm.party, ledger!E:E, "<>*RD*", ledger!D:D, "Kataan", ledger!C:C, "<>Closing CF") ))+ _xlfn.IFNA(L169, 0)} -> 0 | AD48: {=_xlfn.BYROW(B100, _xlfn.LAMBDA(_xlpm.party, SUMIFS(ledger!J:J, ledger!B:B, _xlpm.party, ledger!E:E, "<>*RD*", ledger!D:D, "Munaar", ledger!C:C, "<>Closing CF") ))+ _xlfn.IFNA(M169, 0)} -> 0 | AE48: {=_xlfn.BYROW(B100, _xlfn.LAMBDA(_xlpm.party, SUMIFS(ledger!J:J, ledger!B:B, _xlpm.party, ledger!E:E, "<>*RD*", ledger!D:D, "Super Kataan", ledger!C:C, "<>Closing CF") ))+ _xlfn.IFNA(N169, 0)} -> 0 | AF48: {=_xlfn.BYROW(B100, _xlfn.LAMBDA(_xlpm.party, SUMIFS(ledger!J:J, ledger!B:B, _xlpm.party, ledger!E:E, "<>*RD*", ledger!D:D, "Custom", ledger!C:C, "<>Closing CF") ))+ _xlfn.IFNA(O169, 0)} -> 0 | AG48: =X48+Y48+Z48+AA48+AB48+AC48+AD48+AF48+AE48 -> 387256.77 | AH48: =(SUMIF(Table14[Party],S48,Table14[Credit]))+_xlfn.IFNA(Q169,0) -> 387256 | AI48: =AG48-AH48 -> 0.76664228
S49: mesum | T49: {=_xlfn.BYROW(B101,_xlfn.LAMBDA(_xlpm.party,SUMIFS(ledger!G:G,ledger!B:B,_xlpm.party,ledger!E:E,"<>*RD*")))+_xlfn.IFNA(C170,0)} -> 140184 | U49: {=_xlfn.BYROW(B101, _xlfn.LAMBDA(_xlpm.party, SUMIFS(ledger!G:G, ledger!B:B, _xlpm.party, ledger!E:E, "<>*RD*") / 1.0936 ))+_xlfn.IFNA(D170,0)} -> 128185.81 | V49: {=(_xlfn.BYROW(B101,_xlfn.LAMBDA(_xlpm.party,SUMIFS(ledger!G:G,ledger!B:B,_xlpm.party,ledger!E:E,"<>*RD*",ledger!D:D,"Chamki")+SUMIFS(ledger!G:G, ledger!B:B, _xlpm.party, ledger!E:E, "<>*RD*", ledger!D:D, "Crinkle")))/1.0936)+_xlfn.IFNA(E170,0)} -> 0 | W49: {=(_xlfn.BYROW(B101,_xlfn.LAMBDA(_xlpm.party,SUMIFS(ledger!G:G,ledger!B:B,_xlpm.party,ledger!E:E,"<>*RD*",ledger!D:D,"Silky")))/1.0936)+_xlfn.IFNA(F170,0)} -> 128185.81 | X49: {=(_xlfn.BYROW(B101,_xlfn.LAMBDA(_xlpm.party, (SUMIFS(ledger!J:J,ledger!B:B,_xlpm.party,ledger!E:E,"<>*RD*",ledger!D:D,"Chamki",ledger!C:C,"<>Closing CF")+ SUMIFS(ledger!J:J,ledger!B:B,_xlpm.party,ledger!E:E,"<>*RD*",ledger!D:D,"Crinkle",ledger!C:C,"<>Closing CF") )+_xlfn.IFNA(G170,0))))} -> 0 | Y49: {=_xlfn.BYROW(B101, _xlfn.LAMBDA(_xlpm.party, SUMIFS(ledger!J:J, ledger!B:B, _xlpm.party, ledger!E:E, "<>*RD*", ledger!D:D, "Silky", ledger!C:C, "<>Closing CF") )) + _xlfn.IFNA(H170, 0)} -> 1666415.5 | Z49: {=_xlfn.BYROW(B101, _xlfn.LAMBDA(_xlpm.party, SUMIFS(ledger!J:J, ledger!B:B, _xlpm.party, ledger!E:E, "<>*RD*", ledger!D:D, "Slub", ledger!C:C, "<>Closing CF") ))+ _xlfn.IFNA(I170, 0)} -> 0 | AA49: {=_xlfn.BYROW(B101, _xlfn.LAMBDA(_xlpm.party, SUMIFS(ledger!J:J, ledger!B:B, _xlpm.party, ledger!E:E, "<>*RD*", ledger!D:D, "Satin", ledger!C:C, "<>Closing CF") ))+ _xlfn.IFNA(J170, 0)} -> 0 | AB49: {=_xlfn.BYROW(B101, _xlfn.LAMBDA(_xlpm.party, SUMIFS(ledger!J:J, ledger!B:B, _xlpm.party, ledger!E:E, "<>*RD*", ledger!D:D, "Black-Chamki", ledger!C:C, "<>Closing CF") ))+ _xlfn.IFNA(K170, 0)} -> 0 | AC49: {=_xlfn.BYROW(B101, _xlfn.LAMBDA(_xlpm.party, SUMIFS(ledger!J:J, ledger!B:B, _xlpm.party, ledger!E:E, "<>*RD*", ledger!D:D, "Kataan", ledger!C:C, "<>Closing CF") ))+ _xlfn.IFNA(L170, 0)} -> 0 | AD49: {=_xlfn.BYROW(B101, _xlfn.LAMBDA(_xlpm.party, SUMIFS(ledger!J:J, ledger!B:B, _xlpm.party, ledger!E:E, "<>*RD*", ledger!D:D, "Munaar", ledger!C:C, "<>Closing CF") ))+ _xlfn.IFNA(M170, 0)} -> 0 | AE49: {=_xlfn.BYROW(B101, _xlfn.LAMBDA(_xlpm.party, SUMIFS(ledger!J:J, ledger!B:B, _xlpm.party, ledger!E:E, "<>*RD*", ledger!D:D, "Super Kataan", ledger!C:C, "<>Closing CF") ))+ _xlfn.IFNA(N170, 0)} -> 0 | AF49: {=_xlfn.BYROW(B101, _xlfn.LAMBDA(_xlpm.party, SUMIFS(ledger!J:J, ledger!B:B, _xlpm.party, ledger!E:E, "<>*RD*", ledger!D:D, "Custom", ledger!C:C, "<>Closing CF") ))+ _xlfn.IFNA(O170, 0)} -> 0 | AG49: =X49+Y49+Z49+AA49+AB49+AC49+AD49+AF49+AE49 -> 1666415.5 | AH49: =(SUMIF(Table14[Party],S49,Table14[Credit]))+_xlfn.IFNA(Q170,0) -> 1666331 | AI49: =AG49-AH49 -> 84.508413
S50: Qasim Latif | T50: {=_xlfn.BYROW(B102,_xlfn.LAMBDA(_xlpm.party,SUMIFS(ledger!G:G,ledger!B:B,_xlpm.party,ledger!E:E,"<>*RD*")))+_xlfn.IFNA(C171,0)} -> 8229 | U50: {=_xlfn.BYROW(B102, _xlfn.LAMBDA(_xlpm.party, SUMIFS(ledger!G:G, ledger!B:B, _xlpm.party, ledger!E:E, "<>*RD*") / 1.0936 ))+_xlfn.IFNA(D171,0)} -> 7524.6891 | V50: {=(_xlfn.BYROW(B102,_xlfn.LAMBDA(_xlpm.party,SUMIFS(ledger!G:G,ledger!B:B,_xlpm.party,ledger!E:E,"<>*RD*",ledger!D:D,"Chamki")+SUMIFS(ledger!G:G, ledger!B:B, _xlpm.party, ledger!E:E, "<>*RD*", ledger!D:D, "Crinkle")))/1.0936)+_xlfn.IFNA(E171,0)} -> 0 | W50: {=(_xlfn.BYROW(B102,_xlfn.LAMBDA(_xlpm.party,SUMIFS(ledger!G:G,ledger!B:B,_xlpm.party,ledger!E:E,"<>*RD*",ledger!D:D,"Silky")))/1.0936)+_xlfn.IFNA(F171,0)} -> 0 | X50: {=(_xlfn.BYROW(B102,_xlfn.LAMBDA(_xlpm.party, (SUMIFS(ledger!J:J,ledger!B:B,_xlpm.party,ledger!E:E,"<>*RD*",ledger!D:D,"Chamki",ledger!C:C,"<>Closing CF")+ SUMIFS(ledger!J:J,ledger!B:B,_xlpm.party,ledger!E:E,"<>*RD*",ledger!D:D,"Crinkle",ledger!C:C,"<>Closing CF") )+_xlfn.IFNA(G171,0))))} -> 0 | Y50: {=_xlfn.BYROW(B102, _xlfn.LAMBDA(_xlpm.party, SUMIFS(ledger!J:J, ledger!B:B, _xlpm.party, ledger!E:E, "<>*RD*", ledger!D:D, "Silky", ledger!C:C, "<>Closing CF") )) + _xlfn.IFNA(H171, 0)} -> 0 | Z50: {=_xlfn.BYROW(B102, _xlfn.LAMBDA(_xlpm.party, SUMIFS(ledger!J:J, ledger!B:B, _xlpm.party, ledger!E:E, "<>*RD*", ledger!D:D, "Slub", ledger!C:C, "<>Closing CF") ))+ _xlfn.IFNA(I171, 0)} -> 0 | AA50: {=_xlfn.BYROW(B102, _xlfn.LAMBDA(_xlpm.party, SUMIFS(ledger!J:J, ledger!B:B, _xlpm.party, ledger!E:E, "<>*RD*", ledger!D:D, "Satin", ledger!C:C, "<>Closing CF") ))+ _xlfn.IFNA(J171, 0)} -> 0 | AB50: {=_xlfn.BYROW(B102, _xlfn.LAMBDA(_xlpm.party, SUMIFS(ledger!J:J, ledger!B:B, _xlpm.party, ledger!E:E, "<>*RD*", ledger!D:D, "Black-Chamki", ledger!C:C, "<>Closing CF") ))+ _xlfn.IFNA(K171, 0)} -> 0 | AC50: {=_xlfn.BYROW(B102, _xlfn.LAMBDA(_xlpm.party, SUMIFS(ledger!J:J, ledger!B:B, _xlpm.party, ledger!E:E, "<>*RD*", ledger!D:D, "Kataan", ledger!C:C, "<>Closing CF") ))+ _xlfn.IFNA(L171, 0)} -> 0 | AD50: {=_xlfn.BYROW(B102, _xlfn.LAMBDA(_xlpm.party, SUMIFS(ledger!J:J, ledger!B:B, _xlpm.party, ledger!E:E, "<>*RD*", ledger!D:D, "Munaar", ledger!C:C, "<>Closing CF") ))+ _xlfn.IFNA(M171, 0)} -> 0 | AE50: {=_xlfn.BYROW(B102, _xlfn.LAMBDA(_xlpm.party, SUMIFS(ledger!J:J, ledger!B:B, _xlpm.party, ledger!E:E, "<>*RD*", ledger!D:D, "Super Kataan", ledger!C:C, "<>Closing CF") ))+ _xlfn.IFNA(N171, 0)} -> 0 | AF50: {=_xlfn.BYROW(B102, _xlfn.LAMBDA(_xlpm.party, SUMIFS(ledger!J:J, ledger!B:B, _xlpm.party, ledger!E:E, "<>*RD*", ledger!D:D, "Custom", ledger!C:C, "<>Closing CF") ))+ _xlfn.IFNA(O171, 0)} -> 106977 | AG50: =X50+Y50+Z50+AA50+AB50+AC50+AD50+AF50+AE50 -> 106977 | AH50: =(SUMIF(Table14[Party],S50,Table14[Credit]))+_xlfn.IFNA(Q171,0) -> 106900 | AI50: =AG50-AH50 -> 77
S51: G star | T51: {=_xlfn.BYROW(B103,_xlfn.LAMBDA(_xlpm.party,SUMIFS(ledger!G:G,ledger!B:B,_xlpm.party,ledger!E:E,"<>*RD*")))+_xlfn.IFNA(C172,0)} -> 165317 | U51: {=_xlfn.BYROW(B103, _xlfn.LAMBDA(_xlpm.party, SUMIFS(ledger!G:G, ledger!B:B, _xlpm.party, ledger!E:E, "<>*RD*") / 1.0936 ))+_xlfn.IFNA(D172,0)} -> 151167.7 | V51: {=(_xlfn.BYROW(B103,_xlfn.LAMBDA(_xlpm.party,SUMIFS(ledger!G:G,ledger!B:B,_xlpm.party,ledger!E:E,"<>*RD*",ledger!D:D,"Chamki")+SUMIFS(ledger!G:G, ledger!B:B, _xlpm.party, ledger!E:E, "<>*RD*", ledger!D:D, "Crinkle")))/1.0936)+_xlfn.IFNA(E172,0)} -> 151167.7 | W51: {=(_xlfn.BYROW(B103,_xlfn.LAMBDA(_xlpm.party,SUMIFS(ledger!G:G,ledger!B:B,_xlpm.party,ledger!E:E,"<>*RD*",ledger!D:D,"Silky")))/1.0936)+_xlfn.IFNA(F172,0)} -> 0 | X51: {=(_xlfn.BYROW(B103,_xlfn.LAMBDA(_xlpm.party, (SUMIFS(ledger!J:J,ledger!B:B,_xlpm.party,ledger!E:E,"<>*RD*",ledger!D:D,"Chamki",ledger!C:C,"<>Closing CF")+ SUMIFS(ledger!J:J,ledger!B:B,_xlpm.party,ledger!E:E,"<>*RD*",ledger!D:D,"Crinkle",ledger!C:C,"<>Closing CF") )+_xlfn.IFNA(G172,0))))} -> 1511677 | Y51: {=_xlfn.BYROW(B103, _xlfn.LAMBDA(_xlpm.party, SUMIFS(ledger!J:J, ledger!B:B, _xlpm.party, ledger!E:E, "<>*RD*", ledger!D:D, "Silky", ledger!C:C, "<>Closing CF") )) + _xlfn.IFNA(H172, 0)} -> 0 | Z51: {=_xlfn.BYROW(B103, _xlfn.LAMBDA(_xlpm.party, SUMIFS(ledger!J:J, ledger!B:B, _xlpm.party, ledger!E:E, "<>*RD*", ledger!D:D, "Slub", ledger!C:C, "<>Closing CF") ))+ _xlfn.IFNA(I172, 0)} -> 0 | AA51: {=_xlfn.BYROW(B103, _xlfn.LAMBDA(_xlpm.party, SUMIFS(ledger!J:J, ledger!B:B, _xlpm.party, ledger!E:E, "<>*RD*", ledger!D:D, "Satin", ledger!C:C, "<>Closing CF") ))+ _xlfn.IFNA(J172, 0)} -> 0 | AB51: {=_xlfn.BYROW(B103, _xlfn.LAMBDA(_xlpm.party, SUMIFS(ledger!J:J, ledger!B:B, _xlpm.party, ledger!E:E, "<>*RD*", ledger!D:D, "Black-Chamki", ledger!C:C, "<>Closing CF") ))+ _xlfn.IFNA(K172, 0)} -> 0 | AC51: {=_xlfn.BYROW(B103, _xlfn.LAMBDA(_xlpm.party, SUMIFS(ledger!J:J, ledger!B:B, _xlpm.party, ledger!E:E, "<>*RD*", ledger!D:D, "Kataan", ledger!C:C, "<>Closing CF") ))+ _xlfn.IFNA(L172, 0)} -> 0 | AD51: {=_xlfn.BYROW(B103, _xlfn.LAMBDA(_xlpm.party, SUMIFS(ledger!J:J, ledger!B:B, _xlpm.party, ledger!E:E, "<>*RD*", ledger!D:D, "Munaar", ledger!C:C, "<>Closing CF") ))+ _xlfn.IFNA(M172, 0)} -> 0 | AE51: {=_xlfn.BYROW(B103, _xlfn.LAMBDA(_xlpm.party, SUMIFS(ledger!J:J, ledger!B:B, _xlpm.party, ledger!E:E, "<>*RD*", ledger!D:D, "Super Kataan", ledger!C:C, "<>Closing CF") ))+ _xlfn.IFNA(N172, 0)} -> 0 | AF51: {=_xlfn.BYROW(B103, _xlfn.LAMBDA(_xlpm.party, SUMIFS(ledger!J:J, ledger!B:B, _xlpm.party, ledger!E:E, "<>*RD*", ledger!D:D, "Custom", ledger!C:C, "<>Closing CF") ))+ _xlfn.IFNA(O172, 0)} -> 0 | AG51: =X51+Y51+Z51+AA51+AB51+AC51+AD51+AF51+AE51 -> 1511677 | AH51: =(SUMIF(Table14[Party],S51,Table14[Credit]))+_xlfn.IFNA(Q172,0) -> 1450000 | AI51: =AG51-AH51 -> 61677.03
S52: Raza Khan | T52: {=_xlfn.BYROW(B104,_xlfn.LAMBDA(_xlpm.party,SUMIFS(ledger!G:G,ledger!B:B,_xlpm.party,ledger!E:E,"<>*RD*")))+_xlfn.IFNA(C173,0)} -> 28033 | U52: {=_xlfn.BYROW(B104, _xlfn.LAMBDA(_xlpm.party, SUMIFS(ledger!G:G, ledger!B:B, _xlpm.party, ledger!E:E, "<>*RD*") / 1.0936 ))+_xlfn.IFNA(D173,0)} -> 25633.687 | V52: {=(_xlfn.BYROW(B104,_xlfn.LAMBDA(_xlpm.party,SUMIFS(ledger!G:G,ledger!B:B,_xlpm.party,ledger!E:E,"<>*RD*",ledger!D:D,"Chamki")+SUMIFS(ledger!G:G, ledger!B:B, _xlpm.party, ledger!E:E, "<>*RD*", ledger!D:D, "Crinkle")))/1.0936)+_xlfn.IFNA(E173,0)} -> 0 | W52: {=(_xlfn.BYROW(B104,_xlfn.LAMBDA(_xlpm.party,SUMIFS(ledger!G:G,ledger!B:B,_xlpm.party,ledger!E:E,"<>*RD*",ledger!D:D,"Silky")))/1.0936)+_xlfn.IFNA(F173,0)} -> 25633.687 | X52: {=(_xlfn.BYROW(B104,_xlfn.LAMBDA(_xlpm.party, (SUMIFS(ledger!J:J,ledger!B:B,_xlpm.party,ledger!E:E,"<>*RD*",ledger!D:D,"Chamki",ledger!C:C,"<>Closing CF")+ SUMIFS(ledger!J:J,ledger!B:B,_xlpm.party,ledger!E:E,"<>*RD*",ledger!D:D,"Crinkle",ledger!C:C,"<>Closing CF") )+_xlfn.IFNA(G173,0))))} -> 0 | Y52: {=_xlfn.BYROW(B104, _xlfn.LAMBDA(_xlpm.party, SUMIFS(ledger!J:J, ledger!B:B, _xlpm.party, ledger!E:E, "<>*RD*", ledger!D:D, "Silky", ledger!C:C, "<>Closing CF") )) + _xlfn.IFNA(H173, 0)} -> 307604.24 | Z52: {=_xlfn.BYROW(B104, _xlfn.LAMBDA(_xlpm.party, SUMIFS(ledger!J:J, ledger!B:B, _xlpm.party, ledger!E:E, "<>*RD*", ledger!D:D, "Slub", ledger!C:C, "<>Closing CF") ))+ _xlfn.IFNA(I173, 0)} -> 0 | AA52: {=_xlfn.BYROW(B104, _xlfn.LAMBDA(_xlpm.party, SUMIFS(ledger!J:J, ledger!B:B, _xlpm.party, ledger!E:E, "<>*RD*", ledger!D:D, "Satin", ledger!C:C, "<>Closing CF") ))+ _xlfn.IFNA(J173, 0)} -> 0 | AB52: {=_xlfn.BYROW(B104, _xlfn.LAMBDA(_xlpm.party, SUMIFS(ledger!J:J, ledger!B:B, _xlpm.party, ledger!E:E, "<>*RD*", ledger!D:D, "Black-Chamki", ledger!C:C, "<>Closing CF") ))+ _xlfn.IFNA(K173, 0)} -> 0 | AC52: {=_xlfn.BYROW(B104, _xlfn.LAMBDA(_xlpm.party, SUMIFS(ledger!J:J, ledger!B:B, _xlpm.party, ledger!E:E, "<>*RD*", ledger!D:D, "Kataan", ledger!C:C, "<>Closing CF") ))+ _xlfn.IFNA(L173, 0)} -> 0 | AD52: {=_xlfn.BYROW(B104, _xlfn.LAMBDA(_xlpm.party, SUMIFS(ledger!J:J, ledger!B:B, _xlpm.party, ledger!E:E, "<>*RD*", ledger!D:D, "Munaar", ledger!C:C, "<>Closing CF") ))+ _xlfn.IFNA(M173, 0)} -> 0 | AE52: {=_xlfn.BYROW(B104, _xlfn.LAMBDA(_xlpm.party, SUMIFS(ledger!J:J, ledger!B:B, _xlpm.party, ledger!E:E, "<>*RD*", ledger!D:D, "Super Kataan", ledger!C:C, "<>Closing CF") ))+ _xlfn.IFNA(N173, 0)} -> 0 | AF52: {=_xlfn.BYROW(B104, _xlfn.LAMBDA(_xlpm.party, SUMIFS(ledger!J:J, ledger!B:B, _xlpm.party, ledger!E:E, "<>*RD*", ledger!D:D, "Custom", ledger!C:C, "<>Closing CF") ))+ _xlfn.IFNA(O173, 0)} -> 0 | AG52: =X52+Y52+Z52+AA52+AB52+AC52+AD52+AF52+AE52 -> 307604.24 | AH52: =(SUMIF(Table14[Party],S52,Table14[Credit]))+_xlfn.IFNA(Q173,0) -> 307584 | AI52: =AG52-AH52 -> 20.242868
S53: waqas karachi | T53: {=_xlfn.BYROW(B125,_xlfn.LAMBDA(_xlpm.party,SUMIFS(ledger!G:G,ledger!B:B,_xlpm.party,ledger!E:E,"<>*RD*")))+_xlfn.IFNA(C174,0)} -> 0 | U53: {=_xlfn.BYROW(B125, _xlfn.LAMBDA(_xlpm.party, SUMIFS(ledger!G:G, ledger!B:B, _xlpm.party, ledger!E:E, "<>*RD*") / 1.0936 ))+_xlfn.IFNA(D174,0)} -> 0 | V53: {=(_xlfn.BYROW(B125,_xlfn.LAMBDA(_xlpm.party,SUMIFS(ledger!G:G,ledger!B:B,_xlpm.party,ledger!E:E,"<>*RD*",ledger!D:D,"Chamki")+SUMIFS(ledger!G:G, ledger!B:B, _xlpm.party, ledger!E:E, "<>*RD*", ledger!D:D, "Crinkle")))/1.0936)+_xlfn.IFNA(E174,0)} -> 0 | W53: {=(_xlfn.BYROW(B125,_xlfn.LAMBDA(_xlpm.party,SUMIFS(ledger!G:G,ledger!B:B,_xlpm.party,ledger!E:E,"<>*RD*",ledger!D:D,"Silky")))/1.0936)+_xlfn.IFNA(F174,0)} -> 0 | X53: {=(_xlfn.BYROW(B125,_xlfn.LAMBDA(_xlpm.party, (SUMIFS(ledger!J:J,ledger!B:B,_xlpm.party,ledger!E:E,"<>*RD*",ledger!D:D,"Chamki",ledger!C:C,"<>Closing CF")+ SUMIFS(ledger!J:J,ledger!B:B,_xlpm.party,ledger!E:E,"<>*RD*",ledger!D:D,"Crinkle",ledger!C:C,"<>Closing CF") )+_xlfn.IFNA(G174,0))))} -> 0 | Y53: {=_xlfn.BYROW(B125, _xlfn.LAMBDA(_xlpm.party, SUMIFS(ledger!J:J, ledger!B:B, _xlpm.party, ledger!E:E, "<>*RD*", ledger!D:D, "Silky", ledger!C:C, "<>Closing CF") )) + _xlfn.IFNA(H174, 0)} -> 0 | Z53: {=_xlfn.BYROW(B125, _xlfn.LAMBDA(_xlpm.party, SUMIFS(ledger!J:J, ledger!B:B, _xlpm.party, ledger!E:E, "<>*RD*", ledger!D:D, "Slub", ledger!C:C, "<>Closing CF") ))+ _xlfn.IFNA(I174, 0)} -> 0 | AA53: {=_xlfn.BYROW(B125, _xlfn.LAMBDA(_xlpm.party, SUMIFS(ledger!J:J, ledger!B:B, _xlpm.party, ledger!E:E, "<>*RD*", ledger!D:D, "Satin", ledger!C:C, "<>Closing CF") ))+ _xlfn.IFNA(J174, 0)} -> 0 | AB53: {=_xlfn.BYROW(B125, _xlfn.LAMBDA(_xlpm.party, SUMIFS(ledger!J:J, ledger!B:B, _xlpm.party, ledger!E:E, "<>*RD*", ledger!D:D, "Black-Chamki", ledger!C:C, "<>Closing CF") ))+ _xlfn.IFNA(K174, 0)} -> 0 | AC53: {=_xlfn.BYROW(B125, _xlfn.LAMBDA(_xlpm.party, SUMIFS(ledger!J:J, ledger!B:B, _xlpm.party, ledger!E:E, "<>*RD*", ledger!D:D, "Kataan", ledger!C:C, "<>Closing CF") ))+ _xlfn.IFNA(L174, 0)} -> 0 | AD53: {=_xlfn.BYROW(B125, _xlfn.LAMBDA(_xlpm.party, SUMIFS(ledger!J:J, ledger!B:B, _xlpm.party, ledger!E:E, "<>*RD*", ledger!D:D, "Munaar", ledger!C:C, "<>Closing CF") ))+ _xlfn.IFNA(M174, 0)} -> 0 | AE53: {=_xlfn.BYROW(B125, _xlfn.LAMBDA(_xlpm.party, SUMIFS(ledger!J:J, ledger!B:B, _xlpm.party, ledger!E:E, "<>*RD*", ledger!D:D, "Super Kataan", ledger!C:C, "<>Closing CF") ))+ _xlfn.IFNA(N174, 0)} -> 0 | AF53: {=_xlfn.BYROW(B125, _xlfn.LAMBDA(_xlpm.party, SUMIFS(ledger!J:J, ledger!B:B, _xlpm.party, ledger!E:E, "<>*RD*", ledger!D:D, "Custom", ledger!C:C, "<>Closing CF") ))+ _xlfn.IFNA(O174, 0)} -> 0 | AG53: =X53+Y53+Z53+AA53+AB53+AC53+AD53+AF53+AE53 -> 0 | AH53: =(SUMIF(Table14[Party],S53,Table14[Credit]))+_xlfn.IFNA(Q174,0) -> 0 | AI53: =AG53-AH53 -> 0
B55: Billing September
C56: Gaz | D56: Total Metres | E56: Total Chamki | F56: Total Super Silky | G56: Billing (Chamki/Crinkle) | H56: Billing (Super Chamki) | I56: Billing (Slub) | J56: Billing (Satin) | K56: Billing (Black-chamki) | L56: Billing (Kataan) | M56: Billing (Munaar) | N56: Billing (Super Kataan) | O56: Billing Custom | P56: Adjusted Bill | Q56: Amount Paid | R56: Balance | S56: Rate (Chamki) | T56: Rate (Super Silky)
A57: Parties: | B57: {=_xlfn.UNIQUE(Table1[Party Name])} -> BSC | C57: {=_xlfn.BYROW(_xlfn.ANCHORARRAY(B57),_xlfn.LAMBDA(_xlpm.party,SUMIFS(ledger!G:G,ledger!B:B,_xlpm.party,ledger!E:E,"<>*RD*")))} -> 1439048 | D57: {=_xlfn.BYROW(_xlfn.ANCHORARRAY(B57), _xlfn.LAMBDA(_xlpm.party, SUMIFS(ledger!G:G, ledger!B:B, _xlpm.party, ledger!E:E, "<>*RD*") / 1.0936 ))} -> 1315881.5 | E57: {=(_xlfn.BYROW(_xlfn.ANCHORARRAY(B57),_xlfn.LAMBDA(_xlpm.party,SUMIFS(ledger!G:G,ledger!B:B,_xlpm.party,ledger!E:E,"<>*RD*",ledger!D:D,"Chamki")+SUMIFS(ledger!G:G, ledger!B:B, _xlpm.party, ledger!E:E, "<>*RD*", ledger!D:D, "Crinkle")))/1.0936)} -> 830739.76 | F57: {=(_xlfn.BYROW(_xlfn.ANCHORARRAY(B57),_xlfn.LAMBDA(_xlpm.party,SUMIFS(ledger!G:G,ledger!B:B,_xlpm.party,ledger!E:E,"<>*RD*",ledger!D:D,"Silky")))/1.0936)} -> 483641.19 | G57: {=(_xlfn.BYROW(B57,_xlfn.LAMBDA(_xlpm.party, (SUMIFS(ledger!J:J,ledger!B:B,_xlpm.party,ledger!E:E,"<>*RD*",ledger!D:D,"chamki",ledger!C:C,"<>Closing CF")+ SUMIFS(ledger!J:J,ledger!B:B,_xlpm.party,ledger!E:E,"<>*RD*",ledger!D:D,"Crinkle",ledger!C:C,"<>Closing CF") ))))} -> 8307397.6 | H57: {=_xlfn.BYROW(B57, _xlfn.LAMBDA(_xlpm.party, SUMIFS(ledger!J:J, ledger!B:B, _xlpm.party, ledger!E:E, "<>*RD*", ledger!D:D, "Silky", ledger!C:C, "<>Closing CF") ))} -> 6023850.6 | I57: {=_xlfn.BYROW(B57, _xlfn.LAMBDA(_xlpm.party, SUMIFS(ledger!J:J, ledger!B:B, _xlpm.party, ledger!E:E, "<>*RD*", ledger!D:D, "Slub", ledger!C:C, "<>Closing CF") ))} -> 0 | J57: {=_xlfn.BYROW(B57, _xlfn.LAMBDA(_xlpm.party, SUMIFS(ledger!J:J, ledger!B:B, _xlpm.party, ledger!E:E, "<>*RD*", ledger!D:D, "Satin", ledger!C:C, "<>Closing CF") ))} -> 0 | K57: {=_xlfn.BYROW(B57, _xlfn.LAMBDA(_xlpm.party, SUMIFS(ledger!J:J, ledger!B:B, _xlpm.party, ledger!E:E, "<>*RD*", ledger!D:D, "Black-chamki", ledger!C:C, "<>Closing CF") ))} -> 0 | L57: {=_xlfn.BYROW(B57, _xlfn.LAMBDA(_xlpm.party, SUMIFS(ledger!J:J, ledger!B:B, _xlpm.party, ledger!E:E, "<>*RD*", ledger!D:D, "Kataan", ledger!C:C, "<>Closing CF") ))} -> 0 | M57: {=_xlfn.BYROW(B57, _xlfn.LAMBDA(_xlpm.party, SUMIFS(ledger!J:J, ledger!B:B, _xlpm.party, ledger!E:E, "<>*RD*", ledger!D:D, "Munaar", ledger!C:C, "<>Closing CF") ))} -> 0 | N57: {=_xlfn.BYROW(B57, _xlfn.LAMBDA(_xlpm.party, SUMIFS(ledger!J:J, ledger!B:B, _xlpm.party, ledger!E:E, "<>*RD*", ledger!D:D, "Super kataan", ledger!C:C, "<>Closing CF") ))} -> 0 | O57: {=_xlfn.BYROW(B57, _xlfn.LAMBDA(_xlpm.party, SUMIFS(ledger!J:J, ledger!B:B, _xlpm.party, ledger!E:E, "<>*RD*", ledger!D:D, "Custom", ledger!C:C, "<>Closing CF") ))} -> 18006.584 | P57: =SUM(G57:O57) -> 14349255 | Q57: =(SUMIF(Table14[Party],B57,Table14[Credit])) -> 0 | R57: =P57-Q57 -> 14349255 | S57: 10 | T57: 12 | W57: Row Labels | X57: Sum of Tiyaar | Y57: Sum of Total
B58: Ejaz Sahab | C58: 54161 | D58: 49525.421 | E58: 0 | F58: 49525.421 | G58: {=(_xlfn.BYROW(B58,_xlfn.LAMBDA(_xlpm.party, (SUMIFS(ledger!J:J,ledger!B:B,_xlpm.party,ledger!E:E,"<>*RD*",ledger!D:D,"Chamki",ledger!C:C,"<>Closing CF")+ SUMIFS(ledger!J:J,ledger!B:B,_xlpm.party,ledger!E:E,"<>*RD*",ledger!D:D,"Crinkle",ledger!C:C,"<>Closing CF") ))))} -> 0 | H58: {=_xlfn.BYROW(B58, _xlfn.LAMBDA(_xlpm.party, SUMIFS(ledger!J:J, ledger!B:B, _xlpm.party, ledger!E:E, "<>*RD*", ledger!D:D, "Silky", ledger!C:C, "<>Closing CF") ))} -> 643830.47 | I58: {=_xlfn.BYROW(B58, _xlfn.LAMBDA(_xlpm.party, SUMIFS(ledger!J:J, ledger!B:B, _xlpm.party, ledger!E:E, "<>*RD*", ledger!D:D, "Slub", ledger!C:C, "<>Closing CF") ))} -> 0 | J58: {=_xlfn.BYROW(B58, _xlfn.LAMBDA(_xlpm.party, SUMIFS(ledger!J:J, ledger!B:B, _xlpm.party, ledger!E:E, "<>*RD*", ledger!D:D, "Satin", ledger!C:C, "<>Closing CF") ))} -> 0 | K58: {=_xlfn.BYROW(B58, _xlfn.LAMBDA(_xlpm.party, SUMIFS(ledger!J:J, ledger!B:B, _xlpm.party, ledger!E:E, "<>*RD*", ledger!D:D, "Black-chamki", ledger!C:C, "<>Closing CF") ))} -> 0 | L58: {=_xlfn.BYROW(B58, _xlfn.LAMBDA(_xlpm.party, SUMIFS(ledger!J:J, ledger!B:B, _xlpm.party, ledger!E:E, "<>*RD*", ledger!D:D, "Kataan", ledger!C:C, "<>Closing CF") ))} -> 0 | M58: {=_xlfn.BYROW(B58, _xlfn.LAMBDA(_xlpm.party, SUMIFS(ledger!J:J, ledger!B:B, _xlpm.party, ledger!E:E, "<>*RD*", ledger!D:D, "Munaar", ledger!C:C, "<>Closing CF") ))} -> 0 | N58: {=_xlfn.BYROW(B58, _xlfn.LAMBDA(_xlpm.party, SUMIFS(ledger!J:J, ledger!B:B, _xlpm.party, ledger!E:E, "<>*RD*", ledger!D:D, "Super kataan", ledger!C:C, "<>Closing CF") ))} -> 0 | O58: {=_xlfn.BYROW(B58, _xlfn.LAMBDA(_xlpm.party, SUMIFS(ledger!J:J, ledger!B:B, _xlpm.party, ledger!E:E, "<>*RD*", ledger!D:D, "Custom", ledger!C:C, "<>Closing CF") ))} -> 0 | P58: =SUM(G58:O58) -> 643830.47 | Q58: =(SUMIF(Table14[Party],B58,Table14[Credit])) -> 160635 | R58: =P58-Q58 -> 483195.47 | S58: 10 | T58: 12 | W58: BSC | X58: 1297884.1 | Y58: 12319874
B59: Arshad | C59: 85199 | D59: 77906.913 | E59: 77906.913 | F59: 0 | G59: {=(_xlfn.BYROW(B59,_xlfn.LAMBDA(_xlpm.party, (SUMIFS(ledger!J:J,ledger!B:B,_xlpm.party,ledger!E:E,"<>*RD*",ledger!D:D,"Chamki",ledger!C:C,"<>Closing CF")+ SUMIFS(ledger!J:J,ledger!B:B,_xlpm.party,ledger!E:E,"<>*RD*",ledger!D:D,"Crinkle",ledger!C:C,"<>Closing CF") ))))} -> 779069.13 | H59: {=_xlfn.BYROW(B59, _xlfn.LAMBDA(_xlpm.party, SUMIFS(ledger!J:J, ledger!B:B, _xlpm.party, ledger!E:E, "<>*RD*", ledger!D:D, "Silky", ledger!C:C, "<>Closing CF") ))} -> 0 | I59: {=_xlfn.BYROW(B59, _xlfn.LAMBDA(_xlpm.party, SUMIFS(ledger!J:J, ledger!B:B, _xlpm.party, ledger!E:E, "<>*RD*", ledger!D:D, "Slub", ledger!C:C, "<>Closing CF") ))} -> 0 | J59: {=_xlfn.BYROW(B59, _xlfn.LAMBDA(_xlpm.party, SUMIFS(ledger!J:J, ledger!B:B, _xlpm.party, ledger!E:E, "<>*RD*", ledger!D:D, "Satin", ledger!C:C, "<>Closing CF") ))} -> 0 | K59: {=_xlfn.BYROW(B59, _xlfn.LAMBDA(_xlpm.party, SUMIFS(ledger!J:J, ledger!B:B, _xlpm.party, ledger!E:E, "<>*RD*", ledger!D:D, "Black-chamki", ledger!C:C, "<>Closing CF") ))} -> 0 | L59: {=_xlfn.BYROW(B59, _xlfn.LAMBDA(_xlpm.party, SUMIFS(ledger!J:J, ledger!B:B, _xlpm.party, ledger!E:E, "<>*RD*", ledger!D:D, "Kataan", ledger!C:C, "<>Closing CF") ))} -> 0 | M59: {=_xlfn.BYROW(B59, _xlfn.LAMBDA(_xlpm.party, SUMIFS(ledger!J:J, ledger!B:B, _xlpm.party, ledger!E:E, "<>*RD*", ledger!D:D, "Munaar", ledger!C:C, "<>Closing CF") ))} -> 0 | N59: {=_xlfn.BYROW(B59, _xlfn.LAMBDA(_xlpm.party, SUMIFS(ledger!J:J, ledger!B:B, _xlpm.party, ledger!E:E, "<>*RD*", ledger!D:D, "Super kataan", ledger!C:C, "<>Closing CF") ))} -> 0 | O59: {=_xlfn.BYROW(B59, _xlfn.LAMBDA(_xlpm.party, SUMIFS(ledger!J:J, ledger!B:B, _xlpm.party, ledger!E:E, "<>*RD*", ledger!D:D, "Custom", ledger!C:C, "<>Closing CF") ))} -> 0 | P59: =SUM(G59:O59) -> 779069.13 | Q59: =(SUMIF(Table14[Party],B59,Table14[Credit])) -> 635085 | R59: =P59-Q59 -> 143984.13 | S59: 10 | T59: 12 | W59: Ejaz Sahab | X59: 49525.421 | Y59: 594305.05
B60: Shehzad Kamoki | C60: 0 | D60: 0 | E60: 0 | F60: 0 | G60: {=(_xlfn.BYROW(B60,_xlfn.LAMBDA(_xlpm.party, (SUMIFS(ledger!J:J,ledger!B:B,_xlpm.party,ledger!E:E,"<>*RD*",ledger!D:D,"Chamki",ledger!C:C,"<>Closing CF")+ SUMIFS(ledger!J:J,ledger!B:B,_xlpm.party,ledger!E:E,"<>*RD*",ledger!D:D,"Crinkle",ledger!C:C,"<>Closing CF") ))))} -> 0 | H60: {=_xlfn.BYROW(B60, _xlfn.LAMBDA(_xlpm.party, SUMIFS(ledger!J:J, ledger!B:B, _xlpm.party, ledger!E:E, "<>*RD*", ledger!D:D, "Silky", ledger!C:C, "<>Closing CF") ))} -> 0 | I60: {=_xlfn.BYROW(B60, _xlfn.LAMBDA(_xlpm.party, SUMIFS(ledger!J:J, ledger!B:B, _xlpm.party, ledger!E:E, "<>*RD*", ledger!D:D, "Slub", ledger!C:C, "<>Closing CF") ))} -> 0 | J60: {=_xlfn.BYROW(B60, _xlfn.LAMBDA(_xlpm.party, SUMIFS(ledger!J:J, ledger!B:B, _xlpm.party, ledger!E:E, "<>*RD*", ledger!D:D, "Satin", ledger!C:C, "<>Closing CF") ))} -> 0 | K60: {=_xlfn.BYROW(B60, _xlfn.LAMBDA(_xlpm.party, SUMIFS(ledger!J:J, ledger!B:B, _xlpm.party, ledger!E:E, "<>*RD*", ledger!D:D, "Black-chamki", ledger!C:C, "<>Closing CF") ))} -> 0 | L60: {=_xlfn.BYROW(B60, _xlfn.LAMBDA(_xlpm.party, SUMIFS(ledger!J:J, ledger!B:B, _xlpm.party, ledger!E:E, "<>*RD*", ledger!D:D, "Kataan", ledger!C:C, "<>Closing CF") ))} -> 0 | M60: {=_xlfn.BYROW(B60, _xlfn.LAMBDA(_xlpm.party, SUMIFS(ledger!J:J, ledger!B:B, _xlpm.party, ledger!E:E, "<>*RD*", ledger!D:D, "Munaar", ledger!C:C, "<>Closing CF") ))} -> 0 | N60: {=_xlfn.BYROW(B60, _xlfn.LAMBDA(_xlpm.party, SUMIFS(ledger!J:J, ledger!B:B, _xlpm.party, ledger!E:E, "<>*RD*", ledger!D:D, "Super kataan", ledger!C:C, "<>Closing CF") ))} -> 0 | O60: {=_xlfn.BYROW(B60, _xlfn.LAMBDA(_xlpm.party, SUMIFS(ledger!J:J, ledger!B:B, _xlpm.party, ledger!E:E, "<>*RD*", ledger!D:D, "Custom", ledger!C:C, "<>Closing CF") ))} -> 0 | P60: =SUM(G60:O60) -> 0 | Q60: =(SUMIF(Table14[Party],B60,Table14[Credit])) -> 0 | R60: =P60-Q60 -> 0 | S60: 10.5 | T60: 13 | W60: Arshad | X60: 77906.913 | Y60: 779069.13
B61: Sufi Nawaz Sahab | C61: 175864 | D61: 160812 | E61: 0 | F61: 99855.523 | G61: {=(_xlfn.BYROW(B61,_xlfn.LAMBDA(_xlpm.party, (SUMIFS(ledger!J:J,ledger!B:B,_xlpm.party,ledger!E:E,"<>*RD*",ledger!D:D,"Chamki",ledger!C:C,"<>Closing CF")+ SUMIFS(ledger!J:J,ledger!B:B,_xlpm.party,ledger!E:E,"<>*RD*",ledger!D:D,"Crinkle",ledger!C:C,"<>Closing CF") ))))} -> 0 | H61: {=_xlfn.BYROW(B61, _xlfn.LAMBDA(_xlpm.party, SUMIFS(ledger!J:J, ledger!B:B, _xlpm.party, ledger!E:E, "<>*RD*", ledger!D:D, "Silky", ledger!C:C, "<>Closing CF") ))} -> 1098410.8 | I61: {=_xlfn.BYROW(B61, _xlfn.LAMBDA(_xlpm.party, SUMIFS(ledger!J:J, ledger!B:B, _xlpm.party, ledger!E:E, "<>*RD*", ledger!D:D, "Slub", ledger!C:C, "<>Closing CF") ))} -> 0 | J61: {=_xlfn.BYROW(B61, _xlfn.LAMBDA(_xlpm.party, SUMIFS(ledger!J:J, ledger!B:B, _xlpm.party, ledger!E:E, "<>*RD*", ledger!D:D, "Satin", ledger!C:C, "<>Closing CF") ))} -> 0 | K61: {=_xlfn.BYROW(B61, _xlfn.LAMBDA(_xlpm.party, SUMIFS(ledger!J:J, ledger!B:B, _xlpm.party, ledger!E:E, "<>*RD*", ledger!D:D, "Black-chamki", ledger!C:C, "<>Closing CF") ))} -> 0 | L61: {=_xlfn.BYROW(B61, _xlfn.LAMBDA(_xlpm.party, SUMIFS(ledger!J:J, ledger!B:B, _xlpm.party, ledger!E:E, "<>*RD*", ledger!D:D, "Kataan", ledger!C:C, "<>Closing CF") ))} -> 0 | M61: {=_xlfn.BYROW(B61, _xlfn.LAMBDA(_xlpm.party, SUMIFS(ledger!J:J, ledger!B:B, _xlpm.party, ledger!E:E, "<>*RD*", ledger!D:D, "Munaar", ledger!C:C, "<>Closing CF") ))} -> 0 | N61: {=_xlfn.BYROW(B61, _xlfn.LAMBDA(_xlpm.party, SUMIFS(ledger!J:J, ledger!B:B, _xlpm.party, ledger!E:E, "<>*RD*", ledger!D:D, "Super kataan", ledger!C:C, "<>Closing CF") ))} -> 914347.11 | O61: {=_xlfn.BYROW(B61, _xlfn.LAMBDA(_xlpm.party, SUMIFS(ledger!J:J, ledger!B:B, _xlpm.party, ledger!E:E, "<>*RD*", ledger!D:D, "Custom", ledger!C:C, "<>Closing CF") ))} -> 0 | P61: =SUM(G61:O61) -> 2012757.9 | Q61: =(SUMIF(Table14[Party],B61,Table14[Credit])) -> 700000 | R61: =P61-Q61 -> 1312757.9 | S61: 10 | T61: 12 | W61: Shehzad Kamoki | X61: 0 | Y61: 0
B62: Sajad Khan | C62: 0 | D62: 0 | E62: 0 | F62: 0 | G62: {=(_xlfn.BYROW(B62,_xlfn.LAMBDA(_xlpm.party, (SUMIFS(ledger!J:J,ledger!B:B,_xlpm.party,ledger!E:E,"<>*RD*",ledger!D:D,"Chamki",ledger!C:C,"<>Closing CF")+ SUMIFS(ledger!J:J,ledger!B:B,_xlpm.party,ledger!E:E,"<>*RD*",ledger!D:D,"Crinkle",ledger!C:C,"<>Closing CF") ))))} -> 0 | H62: {=_xlfn.BYROW(B62, _xlfn.LAMBDA(_xlpm.party, SUMIFS(ledger!J:J, ledger!B:B, _xlpm.party, ledger!E:E, "<>*RD*", ledger!D:D, "Silky", ledger!C:C, "<>Closing CF") ))} -> 0 | I62: {=_xlfn.BYROW(B62, _xlfn.LAMBDA(_xlpm.party, SUMIFS(ledger!J:J, ledger!B:B, _xlpm.party, ledger!E:E, "<>*RD*", ledger!D:D, "Slub", ledger!C:C, "<>Closing CF") ))} -> 0 | J62: {=_xlfn.BYROW(B62, _xlfn.LAMBDA(_xlpm.party, SUMIFS(ledger!J:J, ledger!B:B, _xlpm.party, ledger!E:E, "<>*RD*", ledger!D:D, "Satin", ledger!C:C, "<>Closing CF") ))} -> 0 | K62: {=_xlfn.BYROW(B62, _xlfn.LAMBDA(_xlpm.party, SUMIFS(ledger!J:J, ledger!B:B, _xlpm.party, ledger!E:E, "<>*RD*", ledger!D:D, "Black-chamki", ledger!C:C, "<>Closing CF") ))} -> 0 | L62: {=_xlfn.BYROW(B62, _xlfn.LAMBDA(_xlpm.party, SUMIFS(ledger!J:J, ledger!B:B, _xlpm.party, ledger!E:E, "<>*RD*", ledger!D:D, "Kataan", ledger!C:C, "<>Closing CF") ))} -> 0 | M62: {=_xlfn.BYROW(B62, _xlfn.LAMBDA(_xlpm.party, SUMIFS(ledger!J:J, ledger!B:B, _xlpm.party, ledger!E:E, "<>*RD*", ledger!D:D, "Munaar", ledger!C:C, "<>Closing CF") ))} -> 0 | N62: {=_xlfn.BYROW(B62, _xlfn.LAMBDA(_xlpm.party, SUMIFS(ledger!J:J, ledger!B:B, _xlpm.party, ledger!E:E, "<>*RD*", ledger!D:D, "Super kataan", ledger!C:C, "<>Closing CF") ))} -> 0 | O62: {=_xlfn.BYROW(B62, _xlfn.LAMBDA(_xlpm.party, SUMIFS(ledger!J:J, ledger!B:B, _xlpm.party, ledger!E:E, "<>*RD*", ledger!D:D, "Custom", ledger!C:C, "<>Closing CF") ))} -> 0 | P62: =SUM(G62:O62) -> 0 | Q62: =(SUMIF(Table14[Party],B62,Table14[Credit])) -> 164000 | R62: =P62-Q62 -> -164000 | S62: 10 | T62: 12 | W62: Sufi Nawaz Sahab | X62: 160812 | Y62: 1198266.3
B63: Raaz Fabrics | C63: 80391 | D63: 73510.424 | E63: 73510.424 | F63: 0 | G63: {=(_xlfn.BYROW(B63,_xlfn.LAMBDA(_xlpm.party, (SUMIFS(ledger!J:J,ledger!B:B,_xlpm.party,ledger!E:E,"<>*RD*",ledger!D:D,"Chamki",ledger!C:C,"<>Closing CF")+ SUMIFS(ledger!J:J,ledger!B:B,_xlpm.party,ledger!E:E,"<>*RD*",ledger!D:D,"Crinkle",ledger!C:C,"<>Closing CF") ))))} -> 735104.24 | H63: {=_xlfn.BYROW(B63, _xlfn.LAMBDA(_xlpm.party, SUMIFS(ledger!J:J, ledger!B:B, _xlpm.party, ledger!E:E, "<>*RD*", ledger!D:D, "Silky", ledger!C:C, "<>Closing CF") ))} -> 0 | I63: {=_xlfn.BYROW(B63, _xlfn.LAMBDA(_xlpm.party, SUMIFS(ledger!J:J, ledger!B:B, _xlpm.party, ledger!E:E, "<>*RD*", ledger!D:D, "Slub", ledger!C:C, "<>Closing CF") ))} -> 0 | J63: {=_xlfn.BYROW(B63, _xlfn.LAMBDA(_xlpm.party, SUMIFS(ledger!J:J, ledger!B:B, _xlpm.party, ledger!E:E, "<>*RD*", ledger!D:D, "Satin", ledger!C:C, "<>Closing CF") ))} -> 0 | K63: {=_xlfn.BYROW(B63, _xlfn.LAMBDA(_xlpm.party, SUMIFS(ledger!J:J, ledger!B:B, _xlpm.party, ledger!E:E, "<>*RD*", ledger!D:D, "Black-chamki", ledger!C:C, "<>Closing CF") ))} -> 0 | L63: {=_xlfn.BYROW(B63, _xlfn.LAMBDA(_xlpm.party, SUMIFS(ledger!J:J, ledger!B:B, _xlpm.party, ledger!E:E, "<>*RD*", ledger!D:D, "Kataan", ledger!C:C, "<>Closing CF") ))} -> 0 | M63: {=_xlfn.BYROW(B63, _xlfn.LAMBDA(_xlpm.party, SUMIFS(ledger!J:J, ledger!B:B, _xlpm.party, ledger!E:E, "<>*RD*", ledger!D:D, "Munaar", ledger!C:C, "<>Closing CF") ))} -> 0 | N63: {=_xlfn.BYROW(B63, _xlfn.LAMBDA(_xlpm.party, SUMIFS(ledger!J:J, ledger!B:B, _xlpm.party, ledger!E:E, "<>*RD*", ledger!D:D, "Super kataan", ledger!C:C, "<>Closing CF") ))} -> 0 | O63: {=_xlfn.BYROW(B63, _xlfn.LAMBDA(_xlpm.party, SUMIFS(ledger!J:J, ledger!B:B, _xlpm.party, ledger!E:E, "<>*RD*", ledger!D:D, "Custom", ledger!C:C, "<>Closing CF") ))} -> 0 | P63: =SUM(G63:O63) -> 735104.24 | Q63: =(SUMIF(Table14[Party],B63,Table14[Credit])) -> 450000 | R63: =P63-Q63 -> 285104.24 | S63: 10 | T63: 12 | W63: Sajad Khan | X63: 0 | Y63: 0
B64: Azam | C64: 0 | D64: 0 | E64: 0 | F64: 0 | G64: {=(_xlfn.BYROW(B64,_xlfn.LAMBDA(_xlpm.party, (SUMIFS(ledger!J:J,ledger!B:B,_xlpm.party,ledger!E:E,"<>*RD*",ledger!D:D,"Chamki",ledger!C:C,"<>Closing CF")+ SUMIFS(ledger!J:J,ledger!B:B,_xlpm.party,ledger!E:E,"<>*RD*",ledger!D:D,"Crinkle",ledger!C:C,"<>Closing CF") ))))} -> 0 | H64: {=_xlfn.BYROW(B64, _xlfn.LAMBDA(_xlpm.party, SUMIFS(ledger!J:J, ledger!B:B, _xlpm.party, ledger!E:E, "<>*RD*", ledger!D:D, "Silky", ledger!C:C, "<>Closing CF") ))} -> 0 | I64: {=_xlfn.BYROW(B64, _xlfn.LAMBDA(_xlpm.party, SUMIFS(ledger!J:J, ledger!B:B, _xlpm.party, ledger!E:E, "<>*RD*", ledger!D:D, "Slub", ledger!C:C, "<>Closing CF") ))} -> 0 | J64: {=_xlfn.BYROW(B64, _xlfn.LAMBDA(_xlpm.party, SUMIFS(ledger!J:J, ledger!B:B, _xlpm.party, ledger!E:E, "<>*RD*", ledger!D:D, "Satin", ledger!C:C, "<>Closing CF") ))} -> 0 | K64: {=_xlfn.BYROW(B64, _xlfn.LAMBDA(_xlpm.party, SUMIFS(ledger!J:J, ledger!B:B, _xlpm.party, ledger!E:E, "<>*RD*", ledger!D:D, "Black-chamki", ledger!C:C, "<>Closing CF") ))} -> 0 | L64: {=_xlfn.BYROW(B64, _xlfn.LAMBDA(_xlpm.party, SUMIFS(ledger!J:J, ledger!B:B, _xlpm.party, ledger!E:E, "<>*RD*", ledger!D:D, "Kataan", ledger!C:C, "<>Closing CF") ))} -> 0 | M64: {=_xlfn.BYROW(B64, _xlfn.LAMBDA(_xlpm.party, SUMIFS(ledger!J:J, ledger!B:B, _xlpm.party, ledger!E:E, "<>*RD*", ledger!D:D, "Munaar", ledger!C:C, "<>Closing CF") ))} -> 0 | N64: {=_xlfn.BYROW(B64, _xlfn.LAMBDA(_xlpm.party, SUMIFS(ledger!J:J, ledger!B:B, _xlpm.party, ledger!E:E, "<>*RD*", ledger!D:D, "Super kataan", ledger!C:C, "<>Closing CF") ))} -> 0 | O64: {=_xlfn.BYROW(B64, _xlfn.LAMBDA(_xlpm.party, SUMIFS(ledger!J:J, ledger!B:B, _xlpm.party, ledger!E:E, "<>*RD*", ledger!D:D, "Custom", ledger!C:C, "<>Closing CF") ))} -> 0 | P64: =SUM(G64:O64) -> 0 | Q64: =(SUMIF(Table14[Party],B64,Table14[Credit])) -> 0 | R64: =P64-Q64 -> 0 | S64: 10 | T64: 12 | W64: Raaz Fabrics | X64: 73510.424 | Y64: 735104.24
B65: Ubaidullah | C65: 163207 | D65: 149238.3 | E65: 0 | F65: 149238.3 | G65: {=(_xlfn.BYROW(B65,_xlfn.LAMBDA(_xlpm.party, (SUMIFS(ledger!J:J,ledger!B:B,_xlpm.party,ledger!E:E,"<>*RD*",ledger!D:D,"Chamki",ledger!C:C,"<>Closing CF")+ SUMIFS(ledger!J:J,ledger!B:B,_xlpm.party,ledger!E:E,"<>*RD*",ledger!D:D,"Crinkle",ledger!C:C,"<>Closing CF") ))))} -> 0 | H65: {=_xlfn.BYROW(B65, _xlfn.LAMBDA(_xlpm.party, SUMIFS(ledger!J:J, ledger!B:B, _xlpm.party, ledger!E:E, "<>*RD*", ledger!D:D, "Silky", ledger!C:C, "<>Closing CF") ))} -> 1741799.6 | I65: {=_xlfn.BYROW(B65, _xlfn.LAMBDA(_xlpm.party, SUMIFS(ledger!J:J, ledger!B:B, _xlpm.party, ledger!E:E, "<>*RD*", ledger!D:D, "Slub", ledger!C:C, "<>Closing CF") ))} -> 0 | J65: {=_xlfn.BYROW(B65, _xlfn.LAMBDA(_xlpm.party, SUMIFS(ledger!J:J, ledger!B:B, _xlpm.party, ledger!E:E, "<>*RD*", ledger!D:D, "Satin", ledger!C:C, "<>Closing CF") ))} -> 0 | K65: {=_xlfn.BYROW(B65, _xlfn.LAMBDA(_xlpm.party, SUMIFS(ledger!J:J, ledger!B:B, _xlpm.party, ledger!E:E, "<>*RD*", ledger!D:D, "Black-chamki", ledger!C:C, "<>Closing CF") ))} -> 0 | L65: {=_xlfn.BYROW(B65, _xlfn.LAMBDA(_xlpm.party, SUMIFS(ledger!J:J, ledger!B:B, _xlpm.party, ledger!E:E, "<>*RD*", ledger!D:D, "Kataan", ledger!C:C, "<>Closing CF") ))} -> 0 | M65: {=_xlfn.BYROW(B65, _xlfn.LAMBDA(_xlpm.party, SUMIFS(ledger!J:J, ledger!B:B, _xlpm.party, ledger!E:E, "<>*RD*", ledger!D:D, "Munaar", ledger!C:C, "<>Closing CF") ))} -> 0 | N65: {=_xlfn.BYROW(B65, _xlfn.LAMBDA(_xlpm.party, SUMIFS(ledger!J:J, ledger!B:B, _xlpm.party, ledger!E:E, "<>*RD*", ledger!D:D, "Super kataan", ledger!C:C, "<>Closing CF") ))} -> 0 | O65: {=_xlfn.BYROW(B65, _xlfn.LAMBDA(_xlpm.party, SUMIFS(ledger!J:J, ledger!B:B, _xlpm.party, ledger!E:E, "<>*RD*", ledger!D:D, "Custom", ledger!C:C, "<>Closing CF") ))} -> 0 | P65: =SUM(G65:O65) -> 1741799.6 | Q65: =(SUMIF(Table14[Party],B65,Table14[Credit])) -> 1741459 | R65: =P65-Q65 -> 340.56108 | S65: 10 | T65: 12 | W65: Azam | X65: 0 | Y65: 0
B66: Ashraf Zia | C66: 0 | D66: 0 | E66: 0 | F66: 0 | G66: {=(_xlfn.BYROW(B66,_xlfn.LAMBDA(_xlpm.party, (SUMIFS(ledger!J:J,ledger!B:B,_xlpm.party,ledger!E:E,"<>*RD*",ledger!D:D,"Chamki",ledger!C:C,"<>Closing CF")+ SUMIFS(ledger!J:J,ledger!B:B,_xlpm.party,ledger!E:E,"<>*RD*",ledger!D:D,"Crinkle",ledger!C:C,"<>Closing CF") ))))} -> 0 | H66: {=_xlfn.BYROW(B66, _xlfn.LAMBDA(_xlpm.party, SUMIFS(ledger!J:J, ledger!B:B, _xlpm.party, ledger!E:E, "<>*RD*", ledger!D:D, "Silky", ledger!C:C, "<>Closing CF") ))} -> 0 | I66: {=_xlfn.BYROW(B66, _xlfn.LAMBDA(_xlpm.party, SUMIFS(ledger!J:J, ledger!B:B, _xlpm.party, ledger!E:E, "<>*RD*", ledger!D:D, "Slub", ledger!C:C, "<>Closing CF") ))} -> 0 | J66: {=_xlfn.BYROW(B66, _xlfn.LAMBDA(_xlpm.party, SUMIFS(ledger!J:J, ledger!B:B, _xlpm.party, ledger!E:E, "<>*RD*", ledger!D:D, "Satin", ledger!C:C, "<>Closing CF") ))} -> 0 | K66: {=_xlfn.BYROW(B66, _xlfn.LAMBDA(_xlpm.party, SUMIFS(ledger!J:J, ledger!B:B, _xlpm.party, ledger!E:E, "<>*RD*", ledger!D:D, "Black-chamki", ledger!C:C, "<>Closing CF") ))} -> 0 | L66: {=_xlfn.BYROW(B66, _xlfn.LAMBDA(_xlpm.party, SUMIFS(ledger!J:J, ledger!B:B, _xlpm.party, ledger!E:E, "<>*RD*", ledger!D:D, "Kataan", ledger!C:C, "<>Closing CF") ))} -> 0 | M66: {=_xlfn.BYROW(B66, _xlfn.LAMBDA(_xlpm.party, SUMIFS(ledger!J:J, ledger!B:B, _xlpm.party, ledger!E:E, "<>*RD*", ledger!D:D, "Munaar", ledger!C:C, "<>Closing CF") ))} -> 0 | N66: {=_xlfn.BYROW(B66, _xlfn.LAMBDA(_xlpm.party, SUMIFS(ledger!J:J, ledger!B:B, _xlpm.party, ledger!E:E, "<>*RD*", ledger!D:D, "Super kataan", ledger!C:C, "<>Closing CF") ))} -> 0 | O66: {=_xlfn.BYROW(B66, _xlfn.LAMBDA(_xlpm.party, SUMIFS(ledger!J:J, ledger!B:B, _xlpm.party, ledger!E:E, "<>*RD*", ledger!D:D, "Custom", ledger!C:C, "<>Closing CF") ))} -> 0 | P66: =SUM(G66:O66) -> 0 | Q66: =(SUMIF(Table14[Party],B66,Table14[Credit])) -> 0 | R66: =P66-Q66 -> 0 | S66: 12 | T66: 12 | W66: Ubaidullah | X66: 149238.3 | Y66: 1790859.5
B67: Hafiz Qureshi | C67: 171825 | D67: 157118.69 | E67: 52614.301 | F67: 57155.267 | G67: {=(_xlfn.BYROW(B67,_xlfn.LAMBDA(_xlpm.party, (SUMIFS(ledger!J:J,ledger!B:B,_xlpm.party,ledger!E:E,"<>*RD*",ledger!D:D,"Chamki",ledger!C:C,"<>Closing CF")+ SUMIFS(ledger!J:J,ledger!B:B,_xlpm.party,ledger!E:E,"<>*RD*",ledger!D:D,"Crinkle",ledger!C:C,"<>Closing CF") ))))} -> 526143.01 | H67: {=_xlfn.BYROW(B67, _xlfn.LAMBDA(_xlpm.party, SUMIFS(ledger!J:J, ledger!B:B, _xlpm.party, ledger!E:E, "<>*RD*", ledger!D:D, "Silky", ledger!C:C, "<>Closing CF") ))} -> 743018.47 | I67: {=_xlfn.BYROW(B67, _xlfn.LAMBDA(_xlpm.party, SUMIFS(ledger!J:J, ledger!B:B, _xlpm.party, ledger!E:E, "<>*RD*", ledger!D:D, "Slub", ledger!C:C, "<>Closing CF") ))} -> 0 | J67: {=_xlfn.BYROW(B67, _xlfn.LAMBDA(_xlpm.party, SUMIFS(ledger!J:J, ledger!B:B, _xlpm.party, ledger!E:E, "<>*RD*", ledger!D:D, "Satin", ledger!C:C, "<>Closing CF") ))} -> 0 | K67: {=_xlfn.BYROW(B67, _xlfn.LAMBDA(_xlpm.party, SUMIFS(ledger!J:J, ledger!B:B, _xlpm.party, ledger!E:E, "<>*RD*", ledger!D:D, "Black-chamki", ledger!C:C, "<>Closing CF") ))} -> 0 | L67: {=_xlfn.BYROW(B67, _xlfn.LAMBDA(_xlpm.party, SUMIFS(ledger!J:J, ledger!B:B, _xlpm.party, ledger!E:E, "<>*RD*", ledger!D:D, "Kataan", ledger!C:C, "<>Closing CF") ))} -> 520840.34 | M67: {=_xlfn.BYROW(B67, _xlfn.LAMBDA(_xlpm.party, SUMIFS(ledger!J:J, ledger!B:B, _xlpm.party, ledger!E:E, "<>*RD*", ledger!D:D, "Munaar", ledger!C:C, "<>Closing CF") ))} -> 0 | N67: {=_xlfn.BYROW(B67, _xlfn.LAMBDA(_xlpm.party, SUMIFS(ledger!J:J, ledger!B:B, _xlpm.party, ledger!E:E, "<>*RD*", ledger!D:D, "Super kataan", ledger!C:C, "<>Closing CF") ))} -> 0 | O67: {=_xlfn.BYROW(B67, _xlfn.LAMBDA(_xlpm.party, SUMIFS(ledger!J:J, ledger!B:B, _xlpm.party, ledger!E:E, "<>*RD*", ledger!D:D, "Custom", ledger!C:C, "<>Closing CF") ))} -> 0 | P67: =SUM(G67:O67) -> 1790001.8 | Q67: =(SUMIF(Table14[Party],B67,Table14[Credit])) -> 1296044 | R67: =P67-Q67 -> 493957.83 | S67: 10 | T67: 12 | W67: Ashraf Zia | X67: 0 | Y67: 0
B68: Badshah Fabrics | C68: 0 | D68: 0 | E68: 0 | F68: 0 | G68: {=(_xlfn.BYROW(B68,_xlfn.LAMBDA(_xlpm.party, (SUMIFS(ledger!J:J,ledger!B:B,_xlpm.party,ledger!E:E,"<>*RD*",ledger!D:D,"Chamki",ledger!C:C,"<>Closing CF")+ SUMIFS(ledger!J:J,ledger!B:B,_xlpm.party,ledger!E:E,"<>*RD*",ledger!D:D,"Crinkle",ledger!C:C,"<>Closing CF") ))))} -> 0 | H68: {=_xlfn.BYROW(B68, _xlfn.LAMBDA(_xlpm.party, SUMIFS(ledger!J:J, ledger!B:B, _xlpm.party, ledger!E:E, "<>*RD*", ledger!D:D, "Silky", ledger!C:C, "<>Closing CF") ))} -> 0 | I68: {=_xlfn.BYROW(B68, _xlfn.LAMBDA(_xlpm.party, SUMIFS(ledger!J:J, ledger!B:B, _xlpm.party, ledger!E:E, "<>*RD*", ledger!D:D, "Slub", ledger!C:C, "<>Closing CF") ))} -> 0 | J68: {=_xlfn.BYROW(B68, _xlfn.LAMBDA(_xlpm.party, SUMIFS(ledger!J:J, ledger!B:B, _xlpm.party, ledger!E:E, "<>*RD*", ledger!D:D, "Satin", ledger!C:C, "<>Closing CF") ))} -> 0 | K68: {=_xlfn.BYROW(B68, _xlfn.LAMBDA(_xlpm.party, SUMIFS(ledger!J:J, ledger!B:B, _xlpm.party, ledger!E:E, "<>*RD*", ledger!D:D, "Black-chamki", ledger!C:C, "<>Closing CF") ))} -> 0 | L68: {=_xlfn.BYROW(B68, _xlfn.LAMBDA(_xlpm.party, SUMIFS(ledger!J:J, ledger!B:B, _xlpm.party, ledger!E:E, "<>*RD*", ledger!D:D, "Kataan", ledger!C:C, "<>Closing CF") ))} -> 0 | M68: {=_xlfn.BYROW(B68, _xlfn.LAMBDA(_xlpm.party, SUMIFS(ledger!J:J, ledger!B:B, _xlpm.party, ledger!E:E, "<>*RD*", ledger!D:D, "Munaar", ledger!C:C, "<>Closing CF") ))} -> 0 | N68: {=_xlfn.BYROW(B68, _xlfn.LAMBDA(_xlpm.party, SUMIFS(ledger!J:J, ledger!B:B, _xlpm.party, ledger!E:E, "<>*RD*", ledger!D:D, "Super kataan", ledger!C:C, "<>Closing CF") ))} -> 0 | O68: {=_xlfn.BYROW(B68, _xlfn.LAMBDA(_xlpm.party, SUMIFS(ledger!J:J, ledger!B:B, _xlpm.party, ledger!E:E, "<>*RD*", ledger!D:D, "Custom", ledger!C:C, "<>Closing CF") ))} -> 0 | P68: =SUM(G68:O68) -> 0 | Q68: =(SUMIF(Table14[Party],B68,Table14[Credit])) -> 0 | R68: =P68-Q68 -> 0 | S68: 10 | T68: 12 | W68: Hafiz Qureshi | X68: 157118.69 | Y68: 1212006.2
B69: Gauhar Kashif | C69: 0 | D69: 0 | E69: 0 | F69: 0 | G69: {=(_xlfn.BYROW(B69,_xlfn.LAMBDA(_xlpm.party, (SUMIFS(ledger!J:J,ledger!B:B,_xlpm.party,ledger!E:E,"<>*RD*",ledger!D:D,"Chamki",ledger!C:C,"<>Closing CF")+ SUMIFS(ledger!J:J,ledger!B:B,_xlpm.party,ledger!E:E,"<>*RD*",ledger!D:D,"Crinkle",ledger!C:C,"<>Closing CF") ))))} -> 0 | H69: {=_xlfn.BYROW(B69, _xlfn.LAMBDA(_xlpm.party, SUMIFS(ledger!J:J, ledger!B:B, _xlpm.party, ledger!E:E, "<>*RD*", ledger!D:D, "Silky", ledger!C:C, "<>Closing CF") ))} -> 0 | I69: {=_xlfn.BYROW(B69, _xlfn.LAMBDA(_xlpm.party, SUMIFS(ledger!J:J, ledger!B:B, _xlpm.party, ledger!E:E, "<>*RD*", ledger!D:D, "Slub", ledger!C:C, "<>Closing CF") ))} -> 0 | J69: {=_xlfn.BYROW(B69, _xlfn.LAMBDA(_xlpm.party, SUMIFS(ledger!J:J, ledger!B:B, _xlpm.party, ledger!E:E, "<>*RD*", ledger!D:D, "Satin", ledger!C:C, "<>Closing CF") ))} -> 0 | K69: {=_xlfn.BYROW(B69, _xlfn.LAMBDA(_xlpm.party, SUMIFS(ledger!J:J, ledger!B:B, _xlpm.party, ledger!E:E, "<>*RD*", ledger!D:D, "Black-chamki", ledger!C:C, "<>Closing CF") ))} -> 0 | L69: {=_xlfn.BYROW(B69, _xlfn.LAMBDA(_xlpm.party, SUMIFS(ledger!J:J, ledger!B:B, _xlpm.party, ledger!E:E, "<>*RD*", ledger!D:D, "Kataan", ledger!C:C, "<>Closing CF") ))} -> 0 | M69: {=_xlfn.BYROW(B69, _xlfn.LAMBDA(_xlpm.party, SUMIFS(ledger!J:J, ledger!B:B, _xlpm.party, ledger!E:E, "<>*RD*", ledger!D:D, "Munaar", ledger!C:C, "<>Closing CF") ))} -> 0 | N69: {=_xlfn.BYROW(B69, _xlfn.LAMBDA(_xlpm.party, SUMIFS(ledger!J:J, ledger!B:B, _xlpm.party, ledger!E:E, "<>*RD*", ledger!D:D, "Super kataan", ledger!C:C, "<>Closing CF") ))} -> 0 | O69: {=_xlfn.BYROW(B69, _xlfn.LAMBDA(_xlpm.party, SUMIFS(ledger!J:J, ledger!B:B, _xlpm.party, ledger!E:E, "<>*RD*", ledger!D:D, "Custom", ledger!C:C, "<>Closing CF") ))} -> 0 | P69: =SUM(G69:O69) -> 0 | Q69: =(SUMIF(Table14[Party],B69,Table14[Credit])) -> 0 | R69: =P69-Q69 -> 0 | S69: 10 | T69: 12 | W69: Badshah Fabrics | X69: 0 | Y69: 0
... B75: Amjad sohail | C75: 43788 | D75: 40040.234 | E75: 0 | F75: 1979.7001 | G75: {=(_xlfn.BYROW(B75,_xlfn.LAMBDA(_xlpm.party, (SUMIFS(ledger!J:J,ledger!B:B,_xlpm.party,ledger!E:E,"<>*RD*",ledger!D:D,"Chamki",ledger!C:C,"<>Closing CF")+ SUMIFS(ledger!J:J,ledger!B:B,_xlpm.party,ledger!E:E,"<>*RD*",ledger!D:D,"Crinkle",ledger!C:C,"<>Closing CF") ))))} -> 0 | H75: {=_xlfn.BYROW(B75, _xlfn.LAMBDA(_xlpm.party, SUMIFS(ledger!J:J, ledger!B:B, _xlpm.party, ledger!E:E, "<>*RD*", ledger!D:D, "Silky", ledger!C:C, "<>Closing CF") ))} -> 23756.401 | I75: {=_xlfn.BYROW(B75, _xlfn.LAMBDA(_xlpm.party, SUMIFS(ledger!J:J, ledger!B:B, _xlpm.party, ledger!E:E, "<>*RD*", ledger!D:D, "Slub", ledger!C:C, "<>Closing CF") ))} -> 0 | J75: {=_xlfn.BYROW(B75, _xlfn.LAMBDA(_xlpm.party, SUMIFS(ledger!J:J, ledger!B:B, _xlpm.party, ledger!E:E, "<>*RD*", ledger!D:D, "Satin", ledger!C:C, "<>Closing CF") ))} -> 0 | K75: {=_xlfn.BYROW(B75, _xlfn.LAMBDA(_xlpm.party, SUMIFS(ledger!J:J, ledger!B:B, _xlpm.party, ledger!E:E, "<>*RD*", ledger!D:D, "Black-chamki", ledger!C:C, "<>Closing CF") ))} -> 0 | L75: {=_xlfn.BYROW(B75, _xlfn.LAMBDA(_xlpm.party, SUMIFS(ledger!J:J, ledger!B:B, _xlpm.party, ledger!E:E, "<>*RD*", ledger!D:D, "Kataan", ledger!C:C, "<>Closing CF") ))} -> 0 | M75: {=_xlfn.BYROW(B75, _xlfn.LAMBDA(_xlpm.party, SUMIFS(ledger!J:J, ledger!B:B, _xlpm.party, ledger!E:E, "<>*RD*", ledger!D:D, "Munaar", ledger!C:C, "<>Closing CF") ))} -> 0 | N75: {=_xlfn.BYROW(B75, _xlfn.LAMBDA(_xlpm.party, SUMIFS(ledger!J:J, ledger!B:B, _xlpm.party, ledger!E:E, "<>*RD*", ledger!D:D, "Super kataan", ledger!C:C, "<>Closing CF") ))} -> 570908.01 | O75: {=_xlfn.BYROW(B75, _xlfn.LAMBDA(_xlpm.party, SUMIFS(ledger!J:J, ledger!B:B, _xlpm.party, ledger!E:E, "<>*RD*", ledger!D:D, "Custom", ledger!C:C, "<>Closing CF") ))} -> 0 | P75: =SUM(G75:O75) -> 594664.41 | Q75: =(SUMIF(Table14[Party],B75,Table14[Credit])) -> 550000 | R75: =P75-Q75 -> 44664.411 | S75: 10 | T75: 12 | W75: Grand Total | X75: 1965995.8 | Y75: 18629484
B76: Salman Zaffar | C76: 0 | D76: 0 | E76: 0 | F76: 0 | G76: {=(_xlfn.BYROW(B76,_xlfn.LAMBDA(_xlpm.party, (SUMIFS(ledger!J:J,ledger!B:B,_xlpm.party,ledger!E:E,"<>*RD*",ledger!D:D,"Chamki",ledger!C:C,"<>Closing CF")+ SUMIFS(ledger!J:J,ledger!B:B,_xlpm.party,ledger!E:E,"<>*RD*",ledger!D:D,"Crinkle",ledger!C:C,"<>Closing CF") ))))} -> 0 | H76: {=_xlfn.BYROW(B76, _xlfn.LAMBDA(_xlpm.party, SUMIFS(ledger!J:J, ledger!B:B, _xlpm.party, ledger!E:E, "<>*RD*", ledger!D:D, "Silky", ledger!C:C, "<>Closing CF") ))} -> 0 | I76: {=_xlfn.BYROW(B76, _xlfn.LAMBDA(_xlpm.party, SUMIFS(ledger!J:J, ledger!B:B, _xlpm.party, ledger!E:E, "<>*RD*", ledger!D:D, "Slub", ledger!C:C, "<>Closing CF") ))} -> 0 | J76: {=_xlfn.BYROW(B76, _xlfn.LAMBDA(_xlpm.party, SUMIFS(ledger!J:J, ledger!B:B, _xlpm.party, ledger!E:E, "<>*RD*", ledger!D:D, "Satin", ledger!C:C, "<>Closing CF") ))} -> 0 | K76: {=_xlfn.BYROW(B76, _xlfn.LAMBDA(_xlpm.party, SUMIFS(ledger!J:J, ledger!B:B, _xlpm.party, ledger!E:E, "<>*RD*", ledger!D:D, "Black-chamki", ledger!C:C, "<>Closing CF") ))} -> 0 | L76: {=_xlfn.BYROW(B76, _xlfn.LAMBDA(_xlpm.party, SUMIFS(ledger!J:J, ledger!B:B, _xlpm.party, ledger!E:E, "<>*RD*", ledger!D:D, "Kataan", ledger!C:C, "<>Closing CF") ))} -> 0 | M76: {=_xlfn.BYROW(B76, _xlfn.LAMBDA(_xlpm.party, SUMIFS(ledger!J:J, ledger!B:B, _xlpm.party, ledger!E:E, "<>*RD*", ledger!D:D, "Munaar", ledger!C:C, "<>Closing CF") ))} -> 0 | N76: {=_xlfn.BYROW(B76, _xlfn.LAMBDA(_xlpm.party, SUMIFS(ledger!J:J, ledger!B:B, _xlpm.party, ledger!E:E, "<>*RD*", ledger!D:D, "Super kataan", ledger!C:C, "<>Closing CF") ))} -> 0 | O76: {=_xlfn.BYROW(B76, _xlfn.LAMBDA(_xlpm.party, SUMIFS(ledger!J:J, ledger!B:B, _xlpm.party, ledger!E:E, "<>*RD*", ledger!D:D, "Custom", ledger!C:C, "<>Closing CF") ))} -> 0 | P76: =SUM(G76:O76) -> 0 | Q76: =(SUMIF(Table14[Party],B76,Table14[Credit])) -> 0 | R76: =P76-Q76 -> 0 | S76: 10 | T76: 12
B77: Shahid Qasayi | C77: 120149 | D77: 109865.58 | E77: 105800.11 | F77: 4065.4718 | G77: {=(_xlfn.BYROW(B77,_xlfn.LAMBDA(_xlpm.party, (SUMIFS(ledger!J:J,ledger!B:B,_xlpm.party,ledger!E:E,"<>*RD*",ledger!D:D,"Chamki",ledger!C:C,"<>Closing CF")+ SUMIFS(ledger!J:J,ledger!B:B,_xlpm.party,ledger!E:E,"<>*RD*",ledger!D:D,"Crinkle",ledger!C:C,"<>Closing CF") ))))} -> 1058001.1 | H77: {=_xlfn.BYROW(B77, _xlfn.LAMBDA(_xlpm.party, SUMIFS(ledger!J:J, ledger!B:B, _xlpm.party, ledger!E:E, "<>*RD*", ledger!D:D, "Silky", ledger!C:C, "<>Closing CF") ))} -> 52851.134 | I77: {=_xlfn.BYROW(B77, _xlfn.LAMBDA(_xlpm.party, SUMIFS(ledger!J:J, ledger!B:B, _xlpm.party, ledger!E:E, "<>*RD*", ledger!D:D, "Slub", ledger!C:C, "<>Closing CF") ))} -> 0 | J77: {=_xlfn.BYROW(B77, _xlfn.LAMBDA(_xlpm.party, SUMIFS(ledger!J:J, ledger!B:B, _xlpm.party, ledger!E:E, "<>*RD*", ledger!D:D, "Satin", ledger!C:C, "<>Closing CF") ))} -> 0 | K77: {=_xlfn.BYROW(B77, _xlfn.LAMBDA(_xlpm.party, SUMIFS(ledger!J:J, ledger!B:B, _xlpm.party, ledger!E:E, "<>*RD*", ledger!D:D, "Black-chamki", ledger!C:C, "<>Closing CF") ))} -> 0 | L77: {=_xlfn.BYROW(B77, _xlfn.LAMBDA(_xlpm.party, SUMIFS(ledger!J:J, ledger!B:B, _xlpm.party, ledger!E:E, "<>*RD*", ledger!D:D, "Kataan", ledger!C:C, "<>Closing CF") ))} -> 0 | M77: {=_xlfn.BYROW(B77, _xlfn.LAMBDA(_xlpm.party, SUMIFS(ledger!J:J, ledger!B:B, _xlpm.party, ledger!E:E, "<>*RD*", ledger!D:D, "Munaar", ledger!C:C, "<>Closing CF") ))} -> 0 | N77: {=_xlfn.BYROW(B77, _xlfn.LAMBDA(_xlpm.party, SUMIFS(ledger!J:J, ledger!B:B, _xlpm.party, ledger!E:E, "<>*RD*", ledger!D:D, "Super kataan", ledger!C:C, "<>Closing CF") ))} -> 0 | O77: {=_xlfn.BYROW(B77, _xlfn.LAMBDA(_xlpm.party, SUMIFS(ledger!J:J, ledger!B:B, _xlpm.party, ledger!E:E, "<>*RD*", ledger!D:D, "Custom", ledger!C:C, "<>Closing CF") ))} -> 0 | P77: =SUM(G77:O77) -> 1110852.2 | Q77: =(SUMIF(Table14[Party],B77,Table14[Credit])) -> 1106650 | R77: =P77-Q77 -> 4202.2312 | S77: 10 | T77: 12
B78: Hameed corporation | C78: 0 | D78: 0 | E78: 0 | F78: 0 | G78: {=(_xlfn.BYROW(B78,_xlfn.LAMBDA(_xlpm.party, (SUMIFS(ledger!J:J,ledger!B:B,_xlpm.party,ledger!E:E,"<>*RD*",ledger!D:D,"Chamki",ledger!C:C,"<>Closing CF")+ SUMIFS(ledger!J:J,ledger!B:B,_xlpm.party,ledger!E:E,"<>*RD*",ledger!D:D,"Crinkle",ledger!C:C,"<>Closing CF") ))))} -> 0 | H78: {=_xlfn.BYROW(B78, _xlfn.LAMBDA(_xlpm.party, SUMIFS(ledger!J:J, ledger!B:B, _xlpm.party, ledger!E:E, "<>*RD*", ledger!D:D, "Silky", ledger!C:C, "<>Closing CF") ))} -> 0 | I78: {=_xlfn.BYROW(B78, _xlfn.LAMBDA(_xlpm.party, SUMIFS(ledger!J:J, ledger!B:B, _xlpm.party, ledger!E:E, "<>*RD*", ledger!D:D, "Slub", ledger!C:C, "<>Closing CF") ))} -> 0 | J78: {=_xlfn.BYROW(B78, _xlfn.LAMBDA(_xlpm.party, SUMIFS(ledger!J:J, ledger!B:B, _xlpm.party, ledger!E:E, "<>*RD*", ledger!D:D, "Satin", ledger!C:C, "<>Closing CF") ))} -> 0 | K78: {=_xlfn.BYROW(B78, _xlfn.LAMBDA(_xlpm.party, SUMIFS(ledger!J:J, ledger!B:B, _xlpm.party, ledger!E:E, "<>*RD*", ledger!D:D, "Black-chamki", ledger!C:C, "<>Closing CF") ))} -> 0 | L78: {=_xlfn.BYROW(B78, _xlfn.LAMBDA(_xlpm.party, SUMIFS(ledger!J:J, ledger!B:B, _xlpm.party, ledger!E:E, "<>*RD*", ledger!D:D, "Kataan", ledger!C:C, "<>Closing CF") ))} -> 0 | M78: {=_xlfn.BYROW(B78, _xlfn.LAMBDA(_xlpm.party, SUMIFS(ledger!J:J, ledger!B:B, _xlpm.party, ledger!E:E, "<>*RD*", ledger!D:D, "Munaar", ledger!C:C, "<>Closing CF") ))} -> 0 | N78: {=_xlfn.BYROW(B78, _xlfn.LAMBDA(_xlpm.party, SUMIFS(ledger!J:J, ledger!B:B, _xlpm.party, ledger!E:E, "<>*RD*", ledger!D:D, "Super kataan", ledger!C:C, "<>Closing CF") ))} -> 0 | O78: {=_xlfn.BYROW(B78, _xlfn.LAMBDA(_xlpm.party, SUMIFS(ledger!J:J, ledger!B:B, _xlpm.party, ledger!E:E, "<>*RD*", ledger!D:D, "Custom", ledger!C:C, "<>Closing CF") ))} -> 0 | P78: =SUM(G78:O78) -> 0 | Q78: =(SUMIF(Table14[Party],B78,Table14[Credit])) -> 0 | R78: =P78-Q78 -> 0
B79: ibraheem behraam | C79: 23463 | D79: 21454.828 | E79: 0 | F79: 21454.828 | G79: {=(_xlfn.BYROW(B79,_xlfn.LAMBDA(_xlpm.party, (SUMIFS(ledger!J:J,ledger!B:B,_xlpm.party,ledger!E:E,"<>*RD*",ledger!D:D,"Chamki",ledger!C:C,"<>Closing CF")+ SUMIFS(ledger!J:J,ledger!B:B,_xlpm.party,ledger!E:E,"<>*RD*",ledger!D:D,"Crinkle",ledger!C:C,"<>Closing CF") ))))} -> 0 | H79: {=_xlfn.BYROW(B79, _xlfn.LAMBDA(_xlpm.party, SUMIFS(ledger!J:J, ledger!B:B, _xlpm.party, ledger!E:E, "<>*RD*", ledger!D:D, "Silky", ledger!C:C, "<>Closing CF") ))} -> 278912.77 | I79: {=_xlfn.BYROW(B79, _xlfn.LAMBDA(_xlpm.party, SUMIFS(ledger!J:J, ledger!B:B, _xlpm.party, ledger!E:E, "<>*RD*", ledger!D:D, "Slub", ledger!C:C, "<>Closing CF") ))} -> 0 | J79: {=_xlfn.BYROW(B79, _xlfn.LAMBDA(_xlpm.party, SUMIFS(ledger!J:J, ledger!B:B, _xlpm.party, ledger!E:E, "<>*RD*", ledger!D:D, "Satin", ledger!C:C, "<>Closing CF") ))} -> 0 | K79: {=_xlfn.BYROW(B79, _xlfn.LAMBDA(_xlpm.party, SUMIFS(ledger!J:J, ledger!B:B, _xlpm.party, ledger!E:E, "<>*RD*", ledger!D:D, "Black-chamki", ledger!C:C, "<>Closing CF") ))} -> 0 | L79: {=_xlfn.BYROW(B79, _xlfn.LAMBDA(_xlpm.party, SUMIFS(ledger!J:J, ledger!B:B, _xlpm.party, ledger!E:E, "<>*RD*", ledger!D:D, "Kataan", ledger!C:C, "<>Closing CF") ))} -> 0 | M79: {=_xlfn.BYROW(B79, _xlfn.LAMBDA(_xlpm.party, SUMIFS(ledger!J:J, ledger!B:B, _xlpm.party, ledger!E:E, "<>*RD*", ledger!D:D, "Munaar", ledger!C:C, "<>Closing CF") ))} -> 0 | N79: {=_xlfn.BYROW(B79, _xlfn.LAMBDA(_xlpm.party, SUMIFS(ledger!J:J, ledger!B:B, _xlpm.party, ledger!E:E, "<>*RD*", ledger!D:D, "Super kataan", ledger!C:C, "<>Closing CF") ))} -> 0 | O79: {=_xlfn.BYROW(B79, _xlfn.LAMBDA(_xlpm.party, SUMIFS(ledger!J:J, ledger!B:B, _xlpm.party, ledger!E:E, "<>*RD*", ledger!D:D, "Custom", ledger!C:C, "<>Closing CF") ))} -> 0 | P79: =SUM(G79:O79) -> 278912.77 | Q79: =(SUMIF(Table14[Party],B79,Table14[Credit])) -> 306900 | R79: =P79-Q79 -> -27987.235
B80: Zia-ullah karachi | C80: 0 | D80: 0 | E80: 0 | F80: 0 | G80: {=(_xlfn.BYROW(B80,_xlfn.LAMBDA(_xlpm.party, (SUMIFS(ledger!J:J,ledger!B:B,_xlpm.party,ledger!E:E,"<>*RD*",ledger!D:D,"Chamki",ledger!C:C,"<>Closing CF")+ SUMIFS(ledger!J:J,ledger!B:B,_xlpm.party,ledger!E:E,"<>*RD*",ledger!D:D,"Crinkle",ledger!C:C,"<>Closing CF") ))))} -> 0 | H80: {=_xlfn.BYROW(B80, _xlfn.LAMBDA(_xlpm.party, SUMIFS(ledger!J:J, ledger!B:B, _xlpm.party, ledger!E:E, "<>*RD*", ledger!D:D, "Silky", ledger!C:C, "<>Closing CF") ))} -> 0 | I80: {=_xlfn.BYROW(B80, _xlfn.LAMBDA(_xlpm.party, SUMIFS(ledger!J:J, ledger!B:B, _xlpm.party, ledger!E:E, "<>*RD*", ledger!D:D, "Slub", ledger!C:C, "<>Closing CF") ))} -> 0 | J80: {=_xlfn.BYROW(B80, _xlfn.LAMBDA(_xlpm.party, SUMIFS(ledger!J:J, ledger!B:B, _xlpm.party, ledger!E:E, "<>*RD*", ledger!D:D, "Satin", ledger!C:C, "<>Closing CF") ))} -> 0 | K80: {=_xlfn.BYROW(B80, _xlfn.LAMBDA(_xlpm.party, SUMIFS(ledger!J:J, ledger!B:B, _xlpm.party, ledger!E:E, "<>*RD*", ledger!D:D, "Black-chamki", ledger!C:C, "<>Closing CF") ))} -> 0 | L80: {=_xlfn.BYROW(B80, _xlfn.LAMBDA(_xlpm.party, SUMIFS(ledger!J:J, ledger!B:B, _xlpm.party, ledger!E:E, "<>*RD*", ledger!D:D, "Kataan", ledger!C:C, "<>Closing CF") ))} -> 0 | M80: {=_xlfn.BYROW(B80, _xlfn.LAMBDA(_xlpm.party, SUMIFS(ledger!J:J, ledger!B:B, _xlpm.party, ledger!E:E, "<>*RD*", ledger!D:D, "Munaar", ledger!C:C, "<>Closing CF") ))} -> 0 | N80: {=_xlfn.BYROW(B80, _xlfn.LAMBDA(_xlpm.party, SUMIFS(ledger!J:J, ledger!B:B, _xlpm.party, ledger!E:E, "<>*RD*", ledger!D:D, "Super kataan", ledger!C:C, "<>Closing CF") ))} -> 0 | O80: {=_xlfn.BYROW(B80, _xlfn.LAMBDA(_xlpm.party, SUMIFS(ledger!J:J, ledger!B:B, _xlpm.party, ledger!E:E, "<>*RD*", ledger!D:D, "Custom", ledger!C:C, "<>Closing CF") ))} -> 0 | P80: =SUM(G80:O80) -> 0 | Q80: =(SUMIF(Table14[Party],B80,Table14[Credit])) -> 0 | R80: =P80-Q80 -> 0
B81: ZA | C81: 0 | D81: 0 | E81: 0 | F81: 0 | G81: {=(_xlfn.BYROW(B81,_xlfn.LAMBDA(_xlpm.party, (SUMIFS(ledger!J:J,ledger!B:B,_xlpm.party,ledger!E:E,"<>*RD*",ledger!D:D,"Chamki",ledger!C:C,"<>Closing CF")+ SUMIFS(ledger!J:J,ledger!B:B,_xlpm.party,ledger!E:E,"<>*RD*",ledger!D:D,"Crinkle",ledger!C:C,"<>Closing CF") ))))} -> 0 | H81: {=_xlfn.BYROW(B81, _xlfn.LAMBDA(_xlpm.party, SUMIFS(ledger!J:J, ledger!B:B, _xlpm.party, ledger!E:E, "<>*RD*", ledger!D:D, "Silky", ledger!C:C, "<>Closing CF") ))} -> 0 | I81: {=_xlfn.BYROW(B81, _xlfn.LAMBDA(_xlpm.party, SUMIFS(ledger!J:J, ledger!B:B, _xlpm.party, ledger!E:E, "<>*RD*", ledger!D:D, "Slub", ledger!C:C, "<>Closing CF") ))} -> 0 | J81: {=_xlfn.BYROW(B81, _xlfn.LAMBDA(_xlpm.party, SUMIFS(ledger!J:J, ledger!B:B, _xlpm.party, ledger!E:E, "<>*RD*", ledger!D:D, "Satin", ledger!C:C, "<>Closing CF") ))} -> 0 | K81: {=_xlfn.BYROW(B81, _xlfn.LAMBDA(_xlpm.party, SUMIFS(ledger!J:J, ledger!B:B, _xlpm.party, ledger!E:E, "<>*RD*", ledger!D:D, "Black-chamki", ledger!C:C, "<>Closing CF") ))} -> 0 | L81: {=_xlfn.BYROW(B81, _xlfn.LAMBDA(_xlpm.party, SUMIFS(ledger!J:J, ledger!B:B, _xlpm.party, ledger!E:E, "<>*RD*", ledger!D:D, "Kataan", ledger!C:C, "<>Closing CF") ))} -> 0 | M81: {=_xlfn.BYROW(B81, _xlfn.LAMBDA(_xlpm.party, SUMIFS(ledger!J:J, ledger!B:B, _xlpm.party, ledger!E:E, "<>*RD*", ledger!D:D, "Munaar", ledger!C:C, "<>Closing CF") ))} -> 0 | N81: {=_xlfn.BYROW(B81, _xlfn.LAMBDA(_xlpm.party, SUMIFS(ledger!J:J, ledger!B:B, _xlpm.party, ledger!E:E, "<>*RD*", ledger!D:D, "Super kataan", ledger!C:C, "<>Closing CF") ))} -> 0 | O81: {=_xlfn.BYROW(B81, _xlfn.LAMBDA(_xlpm.party, SUMIFS(ledger!J:J, ledger!B:B, _xlpm.party, ledger!E:E, "<>*RD*", ledger!D:D, "Custom", ledger!C:C, "<>Closing CF") ))} -> 0 | P81: =SUM(G81:O81) -> 0 | Q81: =(SUMIF(Table14[Party],B81,Table14[Credit])) -> 0 | R81: =P81-Q81 -> 0
B82: Ahmad Javaid | C82: 0 | D82: 0 | E82: 0 | F82: 0 | G82: {=(_xlfn.BYROW(B82,_xlfn.LAMBDA(_xlpm.party, (SUMIFS(ledger!J:J,ledger!B:B,_xlpm.party,ledger!E:E,"<>*RD*",ledger!D:D,"Chamki",ledger!C:C,"<>Closing CF")+ SUMIFS(ledger!J:J,ledger!B:B,_xlpm.party,ledger!E:E,"<>*RD*",ledger!D:D,"Crinkle",ledger!C:C,"<>Closing CF") ))))} -> 0 | H82: {=_xlfn.BYROW(B82, _xlfn.LAMBDA(_xlpm.party, SUMIFS(ledger!J:J, ledger!B:B, _xlpm.party, ledger!E:E, "<>*RD*", ledger!D:D, "Silky", ledger!C:C, "<>Closing CF") ))} -> 0 | I82: {=_xlfn.BYROW(B82, _xlfn.LAMBDA(_xlpm.party, SUMIFS(ledger!J:J, ledger!B:B, _xlpm.party, ledger!E:E, "<>*RD*", ledger!D:D, "Slub", ledger!C:C, "<>Closing CF") ))} -> 0 | J82: {=_xlfn.BYROW(B82, _xlfn.LAMBDA(_xlpm.party, SUMIFS(ledger!J:J, ledger!B:B, _xlpm.party, ledger!E:E, "<>*RD*", ledger!D:D, "Satin", ledger!C:C, "<>Closing CF") ))} -> 0 | K82: {=_xlfn.BYROW(B82, _xlfn.LAMBDA(_xlpm.party, SUMIFS(ledger!J:J, ledger!B:B, _xlpm.party, ledger!E:E, "<>*RD*", ledger!D:D, "Black-chamki", ledger!C:C, "<>Closing CF") ))} -> 0 | L82: {=_xlfn.BYROW(B82, _xlfn.LAMBDA(_xlpm.party, SUMIFS(ledger!J:J, ledger!B:B, _xlpm.party, ledger!E:E, "<>*RD*", ledger!D:D, "Kataan", ledger!C:C, "<>Closing CF") ))} -> 0 | M82: {=_xlfn.BYROW(B82, _xlfn.LAMBDA(_xlpm.party, SUMIFS(ledger!J:J, ledger!B:B, _xlpm.party, ledger!E:E, "<>*RD*", ledger!D:D, "Munaar", ledger!C:C, "<>Closing CF") ))} -> 0 | N82: {=_xlfn.BYROW(B82, _xlfn.LAMBDA(_xlpm.party, SUMIFS(ledger!J:J, ledger!B:B, _xlpm.party, ledger!E:E, "<>*RD*", ledger!D:D, "Super kataan", ledger!C:C, "<>Closing CF") ))} -> 0 | O82: {=_xlfn.BYROW(B82, _xlfn.LAMBDA(_xlpm.party, SUMIFS(ledger!J:J, ledger!B:B, _xlpm.party, ledger!E:E, "<>*RD*", ledger!D:D, "Custom", ledger!C:C, "<>Closing CF") ))} -> 0 | P82: =SUM(G82:O82) -> 0 | Q82: =(SUMIF(Table14[Party],B82,Table14[Credit])) -> 0 | R82: =P82-Q82 -> 0
B83: Shani Badshah | C83: 0 | D83: 0 | E83: 0 | F83: 0 | G83: {=(_xlfn.BYROW(B83,_xlfn.LAMBDA(_xlpm.party, (SUMIFS(ledger!J:J,ledger!B:B,_xlpm.party,ledger!E:E,"<>*RD*",ledger!D:D,"Chamki",ledger!C:C,"<>Closing CF")+ SUMIFS(ledger!J:J,ledger!B:B,_xlpm.party,ledger!E:E,"<>*RD*",ledger!D:D,"Crinkle",ledger!C:C,"<>Closing CF") ))))} -> 0 | H83: {=_xlfn.BYROW(B83, _xlfn.LAMBDA(_xlpm.party, SUMIFS(ledger!J:J, ledger!B:B, _xlpm.party, ledger!E:E, "<>*RD*", ledger!D:D, "Silky", ledger!C:C, "<>Closing CF") ))} -> 0 | I83: {=_xlfn.BYROW(B83, _xlfn.LAMBDA(_xlpm.party, SUMIFS(ledger!J:J, ledger!B:B, _xlpm.party, ledger!E:E, "<>*RD*", ledger!D:D, "Slub", ledger!C:C, "<>Closing CF") ))} -> 0 | J83: {=_xlfn.BYROW(B83, _xlfn.LAMBDA(_xlpm.party, SUMIFS(ledger!J:J, ledger!B:B, _xlpm.party, ledger!E:E, "<>*RD*", ledger!D:D, "Satin", ledger!C:C, "<>Closing CF") ))} -> 0 | K83: {=_xlfn.BYROW(B83, _xlfn.LAMBDA(_xlpm.party, SUMIFS(ledger!J:J, ledger!B:B, _xlpm.party, ledger!E:E, "<>*RD*", ledger!D:D, "Black-chamki", ledger!C:C, "<>Closing CF") ))} -> 0 | L83: {=_xlfn.BYROW(B83, _xlfn.LAMBDA(_xlpm.party, SUMIFS(ledger!J:J, ledger!B:B, _xlpm.party, ledger!E:E, "<>*RD*", ledger!D:D, "Kataan", ledger!C:C, "<>Closing CF") ))} -> 0 | M83: {=_xlfn.BYROW(B83, _xlfn.LAMBDA(_xlpm.party, SUMIFS(ledger!J:J, ledger!B:B, _xlpm.party, ledger!E:E, "<>*RD*", ledger!D:D, "Munaar", ledger!C:C, "<>Closing CF") ))} -> 0 | N83: {=_xlfn.BYROW(B83, _xlfn.LAMBDA(_xlpm.party, SUMIFS(ledger!J:J, ledger!B:B, _xlpm.party, ledger!E:E, "<>*RD*", ledger!D:D, "Super kataan", ledger!C:C, "<>Closing CF") ))} -> 0 | O83: {=_xlfn.BYROW(B83, _xlfn.LAMBDA(_xlpm.party, SUMIFS(ledger!J:J, ledger!B:B, _xlpm.party, ledger!E:E, "<>*RD*", ledger!D:D, "Custom", ledger!C:C, "<>Closing CF") ))} -> 0 | P83: =SUM(G83:O83) -> 0 | Q83: =(SUMIF(Table14[Party],B83,Table14[Credit])) -> 676071 | R83: =P83-Q83 -> -676071
B84: Rehman Ali | C84: 0 | D84: 0 | E84: 0 | F84: 0 | G84: {=(_xlfn.BYROW(B84,_xlfn.LAMBDA(_xlpm.party, (SUMIFS(ledger!J:J,ledger!B:B,_xlpm.party,ledger!E:E,"<>*RD*",ledger!D:D,"Chamki",ledger!C:C,"<>Closing CF")+ SUMIFS(ledger!J:J,ledger!B:B,_xlpm.party,ledger!E:E,"<>*RD*",ledger!D:D,"Crinkle",ledger!C:C,"<>Closing CF") ))))} -> 0 | H84: {=_xlfn.BYROW(B84, _xlfn.LAMBDA(_xlpm.party, SUMIFS(ledger!J:J, ledger!B:B, _xlpm.party, ledger!E:E, "<>*RD*", ledger!D:D, "Silky", ledger!C:C, "<>Closing CF") ))} -> 0 | I84: {=_xlfn.BYROW(B84, _xlfn.LAMBDA(_xlpm.party, SUMIFS(ledger!J:J, ledger!B:B, _xlpm.party, ledger!E:E, "<>*RD*", ledger!D:D, "Slub", ledger!C:C, "<>Closing CF") ))} -> 0 | J84: {=_xlfn.BYROW(B84, _xlfn.LAMBDA(_xlpm.party, SUMIFS(ledger!J:J, ledger!B:B, _xlpm.party, ledger!E:E, "<>*RD*", ledger!D:D, "Satin", ledger!C:C, "<>Closing CF") ))} -> 0 | K84: {=_xlfn.BYROW(B84, _xlfn.LAMBDA(_xlpm.party, SUMIFS(ledger!J:J, ledger!B:B, _xlpm.party, ledger!E:E, "<>*RD*", ledger!D:D, "Black-chamki", ledger!C:C, "<>Closing CF") ))} -> 0 | L84: {=_xlfn.BYROW(B84, _xlfn.LAMBDA(_xlpm.party, SUMIFS(ledger!J:J, ledger!B:B, _xlpm.party, ledger!E:E, "<>*RD*", ledger!D:D, "Kataan", ledger!C:C, "<>Closing CF") ))} -> 0 | M84: {=_xlfn.BYROW(B84, _xlfn.LAMBDA(_xlpm.party, SUMIFS(ledger!J:J, ledger!B:B, _xlpm.party, ledger!E:E, "<>*RD*", ledger!D:D, "Munaar", ledger!C:C, "<>Closing CF") ))} -> 0 | N84: {=_xlfn.BYROW(B84, _xlfn.LAMBDA(_xlpm.party, SUMIFS(ledger!J:J, ledger!B:B, _xlpm.party, ledger!E:E, "<>*RD*", ledger!D:D, "Super kataan", ledger!C:C, "<>Closing CF") ))} -> 0 | O84: {=_xlfn.BYROW(B84, _xlfn.LAMBDA(_xlpm.party, SUMIFS(ledger!J:J, ledger!B:B, _xlpm.party, ledger!E:E, "<>*RD*", ledger!D:D, "Custom", ledger!C:C, "<>Closing CF") ))} -> 0 | P84: =SUM(G84:O84) -> 0 | Q84: =SUMIF(Table14[Party], B84, Table14[Credit]) -> 0 | R84: =P84-Q84 -> 0
B85: Ahmad Shafique | C85: 0 | D85: 0 | E85: 0 | F85: 0 | G85: {=(_xlfn.BYROW(B85,_xlfn.LAMBDA(_xlpm.party, (SUMIFS(ledger!J:J,ledger!B:B,_xlpm.party,ledger!E:E,"<>*RD*",ledger!D:D,"Chamki",ledger!C:C,"<>Closing CF")+ SUMIFS(ledger!J:J,ledger!B:B,_xlpm.party,ledger!E:E,"<>*RD*",ledger!D:D,"Crinkle",ledger!C:C,"<>Closing CF") ))))} -> 0 | H85: {=_xlfn.BYROW(B85, _xlfn.LAMBDA(_xlpm.party, SUMIFS(ledger!J:J, ledger!B:B, _xlpm.party, ledger!E:E, "<>*RD*", ledger!D:D, "Silky", ledger!C:C, "<>Closing CF") ))} -> 0 | I85: {=_xlfn.BYROW(B85, _xlfn.LAMBDA(_xlpm.party, SUMIFS(ledger!J:J, ledger!B:B, _xlpm.party, ledger!E:E, "<>*RD*", ledger!D:D, "Slub", ledger!C:C, "<>Closing CF") ))} -> 0 | J85: {=_xlfn.BYROW(B85, _xlfn.LAMBDA(_xlpm.party, SUMIFS(ledger!J:J, ledger!B:B, _xlpm.party, ledger!E:E, "<>*RD*", ledger!D:D, "Satin", ledger!C:C, "<>Closing CF") ))} -> 0 | K85: {=_xlfn.BYROW(B85, _xlfn.LAMBDA(_xlpm.party, SUMIFS(ledger!J:J, ledger!B:B, _xlpm.party, ledger!E:E, "<>*RD*", ledger!D:D, "Black-chamki", ledger!C:C, "<>Closing CF") ))} -> 0 | L85: {=_xlfn.BYROW(B85, _xlfn.LAMBDA(_xlpm.party, SUMIFS(ledger!J:J, ledger!B:B, _xlpm.party, ledger!E:E, "<>*RD*", ledger!D:D, "Kataan", ledger!C:C, "<>Closing CF") ))} -> 0 | M85: {=_xlfn.BYROW(B85, _xlfn.LAMBDA(_xlpm.party, SUMIFS(ledger!J:J, ledger!B:B, _xlpm.party, ledger!E:E, "<>*RD*", ledger!D:D, "Munaar", ledger!C:C, "<>Closing CF") ))} -> 0 | N85: {=_xlfn.BYROW(B85, _xlfn.LAMBDA(_xlpm.party, SUMIFS(ledger!J:J, ledger!B:B, _xlpm.party, ledger!E:E, "<>*RD*", ledger!D:D, "Super kataan", ledger!C:C, "<>Closing CF") ))} -> 0 | O85: {=_xlfn.BYROW(B85, _xlfn.LAMBDA(_xlpm.party, SUMIFS(ledger!J:J, ledger!B:B, _xlpm.party, ledger!E:E, "<>*RD*", ledger!D:D, "Custom", ledger!C:C, "<>Closing CF") ))} -> 0 | P85: =SUM(G85:O85) -> 0 | Q85: =SUMIF(Table14[Party], B85, Table14[Credit]) -> 0 | R85: =P85-Q85 -> 0
B86: Hafiz Shawl | C86: 29112 | D86: 26620.337 | E86: 0 | F86: 0 | G86: {=(_xlfn.BYROW(B86,_xlfn.LAMBDA(_xlpm.party, (SUMIFS(ledger!J:J,ledger!B:B,_xlpm.party,ledger!E:E,"<>*RD*",ledger!D:D,"Chamki",ledger!C:C,"<>Closing CF")+ SUMIFS(ledger!J:J,ledger!B:B,_xlpm.party,ledger!E:E,"<>*RD*",ledger!D:D,"Crinkle",ledger!C:C,"<>Closing CF") ))))} -> 0 | H86: {=_xlfn.BYROW(B86, _xlfn.LAMBDA(_xlpm.party, SUMIFS(ledger!J:J, ledger!B:B, _xlpm.party, ledger!E:E, "<>*RD*", ledger!D:D, "Silky", ledger!C:C, "<>Closing CF") ))} -> 0 | I86: {=_xlfn.BYROW(B86, _xlfn.LAMBDA(_xlpm.party, SUMIFS(ledger!J:J, ledger!B:B, _xlpm.party, ledger!E:E, "<>*RD*", ledger!D:D, "Slub", ledger!C:C, "<>Closing CF") ))} -> 0 | J86: {=_xlfn.BYROW(B86, _xlfn.LAMBDA(_xlpm.party, SUMIFS(ledger!J:J, ledger!B:B, _xlpm.party, ledger!E:E, "<>*RD*", ledger!D:D, "Satin", ledger!C:C, "<>Closing CF") ))} -> 0 | K86: {=_xlfn.BYROW(B86, _xlfn.LAMBDA(_xlpm.party, SUMIFS(ledger!J:J, ledger!B:B, _xlpm.party, ledger!E:E, "<>*RD*", ledger!D:D, "Black-chamki", ledger!C:C, "<>Closing CF") ))} -> 0 | L86: {=_xlfn.BYROW(B86, _xlfn.LAMBDA(_xlpm.party, SUMIFS(ledger!J:J, ledger!B:B, _xlpm.party, ledger!E:E, "<>*RD*", ledger!D:D, "Kataan", ledger!C:C, "<>Closing CF") ))} -> 0 | M86: {=_xlfn.BYROW(B86, _xlfn.LAMBDA(_xlpm.party, SUMIFS(ledger!J:J, ledger!B:B, _xlpm.party, ledger!E:E, "<>*RD*", ledger!D:D, "Munaar", ledger!C:C, "<>Closing CF") ))} -> 0 | N86: {=_xlfn.BYROW(B86, _xlfn.LAMBDA(_xlpm.party, SUMIFS(ledger!J:J, ledger!B:B, _xlpm.party, ledger!E:E, "<>*RD*", ledger!D:D, "Super kataan", ledger!C:C, "<>Closing CF") ))} -> 0 | O86: {=_xlfn.BYROW(B86, _xlfn.LAMBDA(_xlpm.party, SUMIFS(ledger!J:J, ledger!B:B, _xlpm.party, ledger!E:E, "<>*RD*", ledger!D:D, "Custom", ledger!C:C, "<>Closing CF") ))} -> 532406.73 | P86: =SUM(G86:O86) -> 532406.73 | Q86: =SUMIF(Table14[Party], B86, Table14[Credit]) -> 0 | R86: =P86-Q86 -> 532406.73
B87: Zahid Ejaz | C87: 0 | D87: 0 | E87: 0 | F87: 0 | G87: {=(_xlfn.BYROW(B87,_xlfn.LAMBDA(_xlpm.party, (SUMIFS(ledger!J:J,ledger!B:B,_xlpm.party,ledger!E:E,"<>*RD*",ledger!D:D,"Chamki",ledger!C:C,"<>Closing CF")+ SUMIFS(ledger!J:J,ledger!B:B,_xlpm.party,ledger!E:E,"<>*RD*",ledger!D:D,"Crinkle",ledger!C:C,"<>Closing CF") ))))} -> 0 | H87: {=_xlfn.BYROW(B87, _xlfn.LAMBDA(_xlpm.party, SUMIFS(ledger!J:J, ledger!B:B, _xlpm.party, ledger!E:E, "<>*RD*", ledger!D:D, "Silky", ledger!C:C, "<>Closing CF") ))} -> 0 | I87: {=_xlfn.BYROW(B87, _xlfn.LAMBDA(_xlpm.party, SUMIFS(ledger!J:J, ledger!B:B, _xlpm.party, ledger!E:E, "<>*RD*", ledger!D:D, "Slub", ledger!C:C, "<>Closing CF") ))} -> 0 | J87: {=_xlfn.BYROW(B87, _xlfn.LAMBDA(_xlpm.party, SUMIFS(ledger!J:J, ledger!B:B, _xlpm.party, ledger!E:E, "<>*RD*", ledger!D:D, "Satin", ledger!C:C, "<>Closing CF") ))} -> 0 | K87: {=_xlfn.BYROW(B87, _xlfn.LAMBDA(_xlpm.party, SUMIFS(ledger!J:J, ledger!B:B, _xlpm.party, ledger!E:E, "<>*RD*", ledger!D:D, "Black-chamki", ledger!C:C, "<>Closing CF") ))} -> 0 | L87: {=_xlfn.BYROW(B87, _xlfn.LAMBDA(_xlpm.party, SUMIFS(ledger!J:J, ledger!B:B, _xlpm.party, ledger!E:E, "<>*RD*", ledger!D:D, "Kataan", ledger!C:C, "<>Closing CF") ))} -> 0 | M87: {=_xlfn.BYROW(B87, _xlfn.LAMBDA(_xlpm.party, SUMIFS(ledger!J:J, ledger!B:B, _xlpm.party, ledger!E:E, "<>*RD*", ledger!D:D, "Munaar", ledger!C:C, "<>Closing CF") ))} -> 0 | N87: {=_xlfn.BYROW(B87, _xlfn.LAMBDA(_xlpm.party, SUMIFS(ledger!J:J, ledger!B:B, _xlpm.party, ledger!E:E, "<>*RD*", ledger!D:D, "Super kataan", ledger!C:C, "<>Closing CF") ))} -> 0 | O87: {=_xlfn.BYROW(B87, _xlfn.LAMBDA(_xlpm.party, SUMIFS(ledger!J:J, ledger!B:B, _xlpm.party, ledger!E:E, "<>*RD*", ledger!D:D, "Custom", ledger!C:C, "<>Closing CF") ))} -> 0 | P87: =SUM(G87:O87) -> 0 | Q87: =SUMIF(Table14[Party], B87, Table14[Credit]) -> 0 | R87: =P87-Q87 -> 0
